Workbook

Sheet Protocolo
A1: PROTOCOLO DE LA REVISIÓN SISTEMÁTICA DE LITERATURA
A2: Paso 0 — Reglas definidas ANTES de filtrar. Este es el 'plan de vuelo': ajusta cada campo a tu proyecto.
A4: 1. Tema / Proyecto | B4: Integración de una IA en una app móvil para la detección de enfermedades en el TALLO del aguacate (Persea americana).
A5: 2. Pregunta de investigación | B5: ¿Qué patógenos afectan el tallo (tronco) del aguacate (Persea americana), qué enfermedades/síntomas producen y cómo se detectan o diagnostican, a nivel mundial y en Latinoamérica?
A6: 3. Objetivo de esta SLR | B6: Reunir y sintetizar la evidencia científica sobre los patógenos del tallo del aguacate para alimentar la base de conocimiento del sistema de IA.
A8: 4. Criterios de INCLUSIÓN
A9: • | B9: Trata sobre aguacate / Persea americana.
A10: • | B10: Menciona uno de los grupos de patógenos considerados.
A11: • | B11: Aporta información sobre el TALLO/tronco (síntomas, cancro, muerte descendente/dieback, pudrición, marchitez, detección).
A12: • | B12: Es un estudio primario (investigación original con datos).
A13: • | B13: Idioma: español o inglés.
A15: 5. Criterios de EXCLUSIÓN
A16: • | B16: Se enfoca ÚNICAMENTE en raíz, hoja o fruto (sin relación con el tallo).
A17: • | B17: Es revisión / survey / mapping / meta-análisis (no es estudio primario).
A18: • | B18: No especifica la especie del patógeno ni el órgano afectado.
A19: • | B19: Registro duplicado (mismo DOI o título en otra base).
A20: • | B20: Fuera del rango de años definido / idioma distinto de español o inglés.
A22: 6. Grupos de patógenos considerados
A23: 1. Phytophthora spp. | B23: Phytophthora cinnamomi
A24: 2. Lasiodiplodia spp. | B24: Lasiodiplodia theobromae
A25: 3. Botryosphaeriaceae | B25: Neofusicoccum parvum
A26: 4. Colletotrichum spp. | B26: C. acutatum, C. gloeosporioides
A27: 5. Fusarium spp. | B27: F. solani, F. oxysporum, F. equiseti
A28: 6. Nectria spp. | B28: N. galligena, N. pseudotrichia, Rugonectria rugulosa
A30: 7. Bases de datos consultadas | B30: Scopus · IEEE Xplore · Web of Science · Springer. (Puedes añadir ScienceDirect / Google Scholar si tu docente lo permite.)
A31: 8. Filtros aplicados | B31: Años: 2010–2025 (AJUSTA según tu docente). Idioma: español / inglés. Tipo: artículos y ponencias (estudios primarios).
A32: 9. Criterios de calidad (Q1–Q10) | B32: Escala por criterio: 0 = no cumple · 1 = cumple parcialmente · 2 = cumple bien. Se puntúan en la hoja 'Calidad_articulos' (total y nivel se calculan solos).
A33: Q1 | B33: El objetivo o pregunta del estudio está claramente definido.
A34: Q2 | B34: Identifica el patógeno a nivel de especie (o al menos género) de forma clara.
A35: Q3 | B35: Describe la enfermedad y los síntomas en el TALLO/tronco con claridad.
... A43: Puntaje / Nivel | B43: Total 0–20 → Alta: 16–20 · Media: 11–15 · Baja: ≤ 10 (cálculo automático).
A44: Validar
A46: 10. Datos a extraer de cada artículo | B46: ID · Autores · Año · DOI · Grupo/Especie · Enfermedad-síntoma del tallo · Región · Método de detección · Resultado/aporte principal.

Sheet Cadenas_de_busqueda
A1: CADENAS DE BÚSQUEDA (registro para reproducibilidad)
A2: Escribe la cadena EXACTA usada en cada base, con su fecha y nº de resultados. Repite cada cadena en las 4 bases y registra los resultados de cada una. Esto hace tu revisión REPRODUCIBLE.
A4: N.º | B4: Grupo | C4: Base de datos | D4: Cadena de búsqueda exacta | E4: Campos | F4: Filtros (años/idioma) | G4: Fecha de búsqueda | H4: N.º resultados | I4: Notas
A5: 1 | B5: TODOS | D5: ("Persea americana" OR avocado) AND ("Phytophthora cinnamomi" OR "Lasiodiplodia theobromae" OR "Neofusicoccum parvum" OR Botryosphaeriaceae OR Colletotrichum OR Fusarium OR Nectria OR Rugonectria) AND (stem OR trunk OR canker OR dieback OR "stem-end rot" OR wilt OR disease OR symptom) | E5: Título-Resumen-Keywords | F5: 2010–2025; es/en | I5: Repetir en Scopus/IEEE/WoS/Springer
A6: 2 | B6: 1. Phytophthora | D6: ("Persea americana" OR avocado) AND "Phytophthora cinnamomi" AND (root OR stem OR trunk OR wilt OR dieback) | E6: Título-Resumen-Keywords | F6: 2010–2025; es/en | I6: Repetir en Scopus/IEEE/WoS/Springer
A7: 3 | B7: 2. Lasiodiplodia | D7: ("Persea americana" OR avocado) AND "Lasiodiplodia theobromae" AND (stem OR trunk OR canker OR "stem-end rot") | E7: Título-Resumen-Keywords | F7: 2010–2025; es/en | I7: Repetir en Scopus/IEEE/WoS/Springer
A8: 4 | B8: 3. Botryosphaeriaceae | D8: ("Persea americana" OR avocado) AND ("Neofusicoccum parvum" OR Botryosphaeriaceae) AND (stem OR trunk OR canker OR dieback) | E8: Título-Resumen-Keywords | F8: 2010–2025; es/en | I8: Repetir en Scopus/IEEE/WoS/Springer
A9: 5 | B9: 4. Colletotrichum | D9: ("Persea americana" OR avocado) AND ("Colletotrichum acutatum" OR "Colletotrichum gloeosporioides") AND (anthracnose OR stem OR canker) | E9: Título-Resumen-Keywords | F9: 2010–2025; es/en | I9: Repetir en Scopus/IEEE/WoS/Springer
A10: 6 | B10: 5. Fusarium | D10: ("Persea americana" OR avocado) AND ("Fusarium solani" OR "Fusarium oxysporum" OR "Fusarium equiseti") AND (wilt OR stem OR trunk OR rot) | E10: Título-Resumen-Keywords | F10: 2010–2025; es/en | I10: Repetir en Scopus/IEEE/WoS/Springer
A11: 7 | B11: 6. Nectria | D11: ("Persea americana" OR avocado) AND (Nectria OR "Rugonectria rugulosa") AND (canker OR trunk OR stem) | E11: Título-Resumen-Keywords | F11: 2010–2025; es/en | I11: Repetir en Scopus/IEEE/WoS/Springer

Sheet Base_consolidada
A1: Base_consolidada
A2: Inventario inicial: TODOS los registros exportados de las bases (Scopus, IEEE, WoS, Springer). Aún no se filtra nada. Asigna un ID único (A0001, A0002, ...) a cada registro.
A3: ID | B3: Base de datos | C3: Título completo | D3: Autores | E3: Año | F3: DOI | G3: Keywords | H3: Abstract | I3: Tipo de documento | J3: Fuente / Revista | K3: Estado inicial | L3: Registro fuente
A4: A0001 | B4: Scopus | C4: Avocado rhizobacteria emit volatile organic compounds with antifungal activity against Fusarium solani, Fusarium sp. associated with Kuroshio shot hole borer, and Colletotrichum gloeosporioides | D4: Guevara-Avendaño E.; Bejarano-Bolívar A.A.; Kiel-Martínez A.-L.; Ramírez-Vázquez M.; Méndez-Bravo A.; von Wobeser E.A.; Sánchez-Rangel D.; Guerrero-Analco J.A.; Eskalen A.; Reverchon F. | E4: 2019 | F4: 10.1016/j.micres.2018.11.009 | G4: Bacillus spp.; Bacterial volatiles; Biological control; Persea americana; Pseudomonas sp.; Rhizosphere; Animals; Antifungal Agents; Bacillus; Biological Control Agents; Coleoptera; Colletotrichum; Fusarium; Persea; Phytophthora; Pseudomonas; Volatile Organic Compounds; Bacillus (bacterium); Bacillus amyloliquefaciens; Bacillus mycoides; Bacteria (microorganisms); Fusarium; Fusarium solani; Fusarium sp.; Glomerella cingulata; Mycelium (genus); Persea americana; Phytophthora; Phytophthora cinnamomi; Pseudomonas; Pseudomonas sp.; Rhizobiales; Bacteria; Bacteriology; Diagnosis; Disease control; Fruits; Gas chromatography; Ketones; Mass spectrometry; Ocean currents; Soils; Sulfur compounds; Volatile organic compounds; antifungal agent; volatile organic compound; Bacillus spp; Bacterial volatiles; Biological controls; Persea americana; Pseudomonas sp; Rhizosphere; antagonism; antimicrobial activity; beetle; biological control; fruit; fungus; growth; pathogen; rhizobacterium; rhizosphere; root rot; volatile organic compound; animal; Bacillus; beetle; biological control agent; Colletotrichum; drug effect; Fusarium; metabolism; microbiology; Persea; pharmacology; Phytophthora; Pseudomonas; Fungi | H4: Recent studies showed that bacterial volatile organic compounds (VOCs) play an important role in the suppression of phytopathogens. The ability of VOCs produced by avocado (Persea americana Mill.) rhizobacteria to suppress the growth of common avocado pathogens was therefore investigated. We evaluated the antifungal activity of VOCs emitted by avocado rhizobacteria in a first screening against Fusarium solani, and in subsequent antagonism assays against Fusarium sp. associated with Kuroshio shot hole borer, Colletotrichum gloeosporioides and Phytophthora cinnamomi, responsible for Fusarium dieback, anthracnosis and Phytophthora root rot in avocado, respectively. We also analyzed the composition of the bacterial volatile profiles by solid phase microextraction (SPME) gas chromatography coupled to mass spectrometry (GC–MS). Seven isolates, belonging to the bacterial genera Bacillus and Pseudomonas, reduced the mycelial growth of F. solani with inhibition percentages higher than 20%. Isolate HA, related to Bacillus amyloliquefaciens, significantly reduced the mycelial growth of Fusarium sp. and C. gloeosporioides and the mycelium density of P. cinnamomi. Isolates SO and SJJ, also members of the genus Bacillus, reduced Fusarium sp. mycelial growth and induced morphological alterations of fungal hyphae whilst isolate HB, close to B. mycoides, inhibited C. gloeosporioides. The analysis of the volatile profiles revealed the presence of ketones, pyrazines and sulfur-containing compounds, previously reported with antifungal activity. Altogether, our results support the potential of avocado rhizobacteria to act as biocontrol agents of avocado fungal pathogens and emphasize the importance of Bacillus spp. for the control of emerging avocado diseases such as Fusarium dieback. © 2018 | I4: Article | J4: Microbiological Research | K4: Importado | L4: scopus_export_Sep 18-2026_4e658477-f683-499d-a469-81d37efaa96b.csv
A5: A0002 | B5: Scopus | C5: Colletotrichum fructicola, a Member of Colletotrichum gloeosporioides sensu lato, is the causal agent of anthracnose and soft rot in avocado fruits cv. "Hass" | D5: Fuentes-Aragón D.; Juárez-Vázquez S.B.; Vargas-Hernández M.; Silva-Rojas H.V. | E5: 2018 | F5: 10.1080/12298093.2018.1454010 | G5: Bayesian inference; Colletotrichum species complex; Fungal infection; Multilocus sequencing typing; Persea americana; Phylogenetic reconstruction | H5: The filamentous Ascomycota Colletotrichum gloeosporioides sensu lato is a fungus that has been reported worldwide as a causal agent of anthracnose disease in avocado and other crops. In Mexico, this species affects fruits from an early stage of development in the orchard until the post-harvest stage. Although fungicides are continuously applied to control Colletotrichum species, pericarp cankers and soft rot mesocarp in fruits are still frequently observed. Considering the lack of a precise description of the causative agent, the aim of the current study was to determine the pathogens involved in this symptomatology. Twenty-four isolates were consistently obtained from the pericarp of avocado fruits cv. "Hass" collected in the central avocado-producing area of Mexico. Morphological features such as colony growth, conidia size, and mycelial appressorium were assessed. Bayesian multilocus phylogenetic analyses were performed using amplified sequences of the internal transcribed spacer region of the nuclear ribosomal DNA; actin, chitin synthase, glyceraldehyde-3-phosphate dehydrogenase partial genes; and APn2-Mat1-2 intergenic spacer and mating type Mat1-2 partial gene from the nine selected isolates. In addition, fruits were inoculated with a conidial suspension and reproducible symptoms confirmed the presence of Colletotrichum fructicola in this area. This pathogenic species can now be added to those previously reported in the country, such as C. acutatum, C. boninense, C. godetiae, C. gloeosporioides, and C. karstii. Disease management programs to reduce the incidence of anthracnose should include C. fructicola to determine its response to fungicides that are routinely applied, considering that the appearance of new species is affecting the commercial quality of the fruits and shifting the original population structure. © 2018 The Author(s). | I5: Article | J5: Mycobiology | K5: Importado | L5: scopus_export_Sep 18-2026_82c23d75-ee65-4935-bf31-12365c1693d4.csv
A6: A0003 | B6: Scopus | C6: Colletotrichum perseae and Colletotrichum gloeosporioides sensu strictu Causing Stem Lesion and Dieback in Avocado in Italy | D6: Vecchio L.; Martino I.; Guarnaccia V.; Polizzi G.; Aiello D. | E6: 2026 | F6: 10.3390/horticulturae12010111 | G6: Colletotrichum species; Persea americana; stem and fruit infections | H6: In the last decade, avocado production has increased in Italy due to the fruit’s high nutritional quality and economic value. During 2024, stem lesions, wood discoloration and dieback, often starting at the grafting point, were observed in young plants in a nursery in Sicily (Italy). Colletotrichum-like colonies were frequently isolated from symptomatic tissues. Multi-locus phylogenetic analysis (gapdh, chs-1, act, tub2, cal, gs and ApMat) was conducted on 11 representative isolates, identifying 6 as C. perseae and 5 as C. gloeosporioides sensu stricto (s.s.). Two representative isolates were selected for pathogenicity tests performed on 2-year-old avocado plants cultivated in a greenhouse. After two months, necrotic lesions, wood discoloration and reddish-brown streaking at the inoculation point were induced in both species. Additional inoculations of avocado fruit confirmed the ability of both species to cause fruit rot. All inoculated fungi were successfully re-isolated and identified, fulfilling Koch’s postulates. This is the first report of stem lesions and dieback caused by Colletotrichum species and the first occurrence of C. perseae in avocado plants in Europe. The results highlight the importance of early monitoring in nurseries during the propagation process and contribute to a better understanding of fungal diseases in avocado crops in Italy. © 2026 by the authors. | I6: Article | J6: Horticulturae | K6: Importado | L6: scopus_export_Sep 17-2026_64f2de15-f34e-4ffa-b356-5d490b5ac07b.csv | scopus_export_Sep 18-2026_82c23d75-ee65-4935-bf31-12365c1693d4.csv
A7: A0004 | B7: Scopus | C7: Colletotrichum siamense is the main aetiological agent of anthracnose of avocado in south-eastern Brazil | D7: Soares M.G.O.; Alves E.; Silveira A.L.; Pereira F.D.; Guimarães S.S.C. | E7: 2021 | F7: 10.1111/ppa.13262 | G7: infectious process; multilocus phylogeny; pathogenicity; Persea americana; post-harvest disease; Brazil; Colletotrichum; Colletotrichum boninense; Persea americana; anthracnose; bacterium; deciduous tree; etiology; genetic variation; inoculation; isolated population; morphology; phylogenetics; sporulation | H7: Anthracnose caused by species of Colletotrichum is considered one of the main postharvest diseases for avocado. In this study, Colletotrichum isolates associated with avocado anthracnose, collected in different states of Brazil, were evaluated through phylogenetic analysis, morphological characterization, and pathogenicity assays. Moreover, the events during pathogen infection of avocados were examined by scanning electron microscopy. To assess the genetic diversity of 54 Colletotrichum isolates, partial sequence analysis of the gene gapdh was performed. According to the generated groupings and the geographical origins of isolates, a subset of 14 strains was selected for performing multilocus phylogeny analysis (using sequences of gapdh, act, tub2, and ApMat). Two species previously described were identified: C. siamense belonging to the C. gloeosporioides species complex and Colletotrichum karstii belonging to the C. boninense species complex. All Colletotrichum strains evaluated caused typical symptoms of anthracnose in avocado fruits. Conidia of the most virulent strain germinated between 6 and 12 hr after inoculation (hai). Penetration through wounds occurred 48 hai, tissue colonization occurred between 144 and 240 hai, and sporulation took place at 240 hai via the production of an acervulus, conidiophores, and conidia. The findings shed light on the aetiology of avocado anthracnose in Brazil and provide a better understanding of the infection process of this pathogen, which may assist in the development of disease management strategies. © 2020 British Society for Plant Pathology | I7: Article | J7: Plant Pathology | K7: Importado | L7: scopus_export_Sep 17-2026_64f2de15-f34e-4ffa-b356-5d490b5ac07b.csv
A8: A0005 | B8: Scopus | C8: Colletotrichum species causing anthracnose on avocado fruit in Mexico: Current status | D8: Fuentes-Aragón D.; Silva-Rojas H.V.; Guarnaccia V.; Mora-Aguilera J.A.; Aranda-Ocampo S.; Bautista-Martínez N.; Téliz-Ortíz D. | E8: 2020 | F8: 10.1111/ppa.13234 | G8: Colletotrichum jiangxiense sexual morph; Colletotrichum species; multilocus phylogenetic analyses; pathogenicity test; Persea americana; Mexico [North America]; Colletotrichum; Colletotrichum nymphaeae; Colletotrichum sp.; Persea americana; anthracnose; bacterium; crop plant; fruit; genetic analysis; morphology; pathogenicity; phylogenetics | H8: Colletotrichum species cause anthracnose disease in tropical and subtropical fruit crops worldwide. Mexico is the main producer and exporter of avocado (Persea americana) globally and has yearly outbreaks of anthracnose on this crop. However, which specific Colletotrichum spp. cause these outbreaks in avocado-producing regions remain uncertain; thus, the objective of the present study was to identify the species responsible. A survey performed in six production regions of Mexico yielded 232 isolates, from which a subset of 104 strains was selected based on morphological characteristics and origin. This subset was sequenced and haplotypes were analysed in the gapdh partial gene. Finally, 31 strains were identified through multilocus phylogenetic analyses using the sequences of the internal transcribed spacer region and six loci. This study revealed the presence of two species previously reported in Mexico (C. karsti and C. godetiae), three novel records in Mexico (C. siamense, C. fioriniae, and C. cigarro), four novel records on avocado (C. chrysophilum, C. jiangxiense, C. tropicale, and C. nymphaeae), and two novel lineages (Colletotrichum sp. 1 and Colletotrichum sp. 2). C. siamense was the most prevalent, while the species reported for the first time on avocado, including the novel lineages, were the least prevalent. C. karsti was the most widespread (four regions), followed by C. siamense, C. jiangxiense, and C. chrysophilum (three regions). Pathogenicity tests showed that all species caused anthracnose on avocado fruit. These findings will be useful for improving the management of avocado anthracnose outbreaks in Mexico. © 2020 British Society for Plant Pathology | I8: Article | J8: Plant Pathology | K8: Importado | L8: scopus_export_Sep 17-2026_2fb2f4b0-ee23-499b-9e91-17eb9cc8aaf8.csv
A9: A0006 | B9: Scopus | C9: Ecofriendly management of anthracnose on avocado caused by Colletotrichum perseae in the Mediterranean basin | D9: Vecchio L.; Arrebola E.; Polizzi G.; Vitale A. | E9: 2026 | F9: 10.1002/jsf2.70088 | G9: anthracnose; avocado; Bacillus; biological control agents; sustainable agriculture; Trichoderma | H9: Background: Colletotrichum perseae, recently reported in Europe, causes stem and twig lesions and dieback, and fruit rot on avocado in several countries. Due to EU severe restrictions, there is an urgent need for sustainable alternatives to fungicides. This study aims to evaluate the preventative activity of trade bioformulates against C. perseae across detached twig, greenhouse pot-plant grown, and postharvest fruit experiments. Results: All biological treatments have significantly managed twig anthracnose infections ranging by 37%–91% reductions. Bacillus amyloliquefaciens QST713, chitosan, Trichoderma gamsii + Trichoderma asperellum mixture, and Equisetum arvense based bioformulates showed a similar efficacy of the standard fungicide (pyraclostrobin) whilst sweet orange essential oils were less effective. In potted plants grown in greenhouse, T. asperellum T34 followed by T. gamsii + T. asperellum mixture bioformulates revealed the most effective in reducing internal lesions caused by C. perseae. On the other hand, bioformulate containing B. amyloliquefaciens D747 revealed the most effective treatment in minimizing C. perseae anthracnose lesions under post-harvest conditions. Conclusion: The paper clearly showed that some trade bioformulates could represent a highly effective, environmentally friendly option for managing C. perseae of avocado. The implementation of such an approach should be imperative for developing performant strategies for other avocado diseases. This process should begin with preventive applications of Trichoderma species as T34 in nursery and preserve the health in postharvest by using B. amyloliquefaciens strains-based formulates. Indeed, the strategic adoption of these trade bioalternatives provides a concrete pathway to replace chemical fungicides. © 2026 The Author(s). JSFA Reports published by John Wiley & Sons Ltd on behalf of Society of Chemical Industry. | I9: Article | J9: JSFA reports | K9: Importado | L9: scopus_export_Sep 17-2026_64f2de15-f34e-4ffa-b356-5d490b5ac07b.csv
A10: A0007 | B10: Scopus | C10: Effect of pectin-based edible emulsion coating on changes in quality of avocado exposed to Lasiodiplodia theobromae infection | D10: Maftoonazad N.; Ramaswamy H.S.; Moalemiyan M.; Kushalappa A.C. | E10: 2007 | F10: 10.1016/j.carbpol.2006.11.020 | G10: Avocado; Coating; Color; Edible film; Lasiodiplodia theobromae; Pectin; Respiration rate; Storage; Texture; Carbohydrates; Emulsions; Food Storage; Fruits; Fungi; Persea; Botryosphaeria rhodina; Persea americana; Emulsions; Food storage; Fruits; Fungi; Edible films; Lasiodiplodia theobromae; Pectin; Respiration rate; Uncoated fruits; Carbohydrates | H10: This study was carried out to evaluate the effect of pectin-based edible emulsion coating on activity and disease severity of Lasiodiplodia theobromae in avocados, and their subsequent influence on the fruit quality. In order to assess the influence of coating and disease, avocados were sorted and devided into four equal lots and all were incubated at 20 °C for up to 4 days. The first and second lots constituted samples which were stored as coated and uncoated, respectively, without fungal inoculation. The third and fourth lots were coated and un-coated fruits inoculated with the fungal disease. For coating, a previously standardized pectin-based emulsion was used. The incubated fruits were examined for the spread of disease, respiration rate and quality parameters, color and texture. As the incubation time increased, the volume of disease (VDS) increased, which in turn influenced the respiration rate (RR) in both coated and uncoated fruits. However, the coated fruits sustained a significantly slower rate of disease spread and RR. Similarly, the associated quality changes (texture and color) were much lower in coated fruits as compared with the control. Thus, the pectin based coating was effective in controlling the spread and severity of stem end rot in avocados. Changes in physical and physiological parameters of coated and uncoated fruits were well described by some form of semi-logarithmic models and were related to the VDS as well as case dependent incubation time. © 2007. | I10: Article | J10: Carbohydrate Polymers | K10: Importado | L10: scopus_export_Sep 18-2026_8f28b456-611a-478a-9b87-bb5029e250f3.csv
A11: A0008 | B11: Scopus | C11: Effect of seaweed extract on avocado root growth, yield and post-harvest quality in far north Queensland, Australia | D11: Arioli T.; Villalta O.N.; Hepworth G.; Farnsworth B.; Mattner S.W. | E11: 2024 | F11: 10.1007/s10811-023-02933-0 | G11: Ascophyllum nodosum; Biostimulant; Durvillaea potatorum; Persea americana; Phytophthora cinnamomi | H11: Seaweed extracts are proven to increase productivity in many agricultural crops, but there is limited research on their use in avocado production. Therefore, we evaluated the effectiveness of a seaweed extract from Durvillaea potatorum and Ascophyllum nodosum on avocado yield, revenue and post-harvest fruit quality in a series of field experiments in Australia, and on seedling root growth in a pot experiment. The field experiments were conducted on commercial farms across three different locations in northern Queensland over four years and utilised avocado trees with different ages, cultivars (Hass and Shepard) and inoculum pressures from Phytophthora cinnamomi. Results showed that the application of the seaweed extract by fertigation significantly improved avocado yield (kg fruit per tree) by 38%, fruit firmness by 4% (skin) and 22% (flesh) and fruit skin colour by 1° (hue), and an upgraded visual ripeness score. The increases in yield were associated with greater number of fruits per tree (up to 42%) indicating the liquid seaweed extract improved fruit set and retention per tree. Regular soil application of the seaweed extract to young trees (cv. Hass) in pots increased the root fresh weight by 22%. Overall, the regular application of the seaweed extract to avocado trees was found to be practical and economically viable for improving fruit production and post-harvest quality in Australian orchards. © The Author(s) 2023. | I11: Article | J11: Journal of Applied Phycology | K11: Importado | L11: scopus_export_Sep 18-2026_162c1d26-553e-41ee-8ea1-e9ecd3a7eea2.csv
A12: A0009 | B12: Scopus | C12: Emerging pathogens and disease dynamics threatening avocado production in southern Türkiye | D12: Çalış Ö.; Çelik S.; Fidan H.; Tek M.I.; Shah M.; Tozlu I.; Wani S.H. | E12: 2024 | F12: 10.1007/s41348-024-00954-6 | G12: Anthracnose; Avocado; Branch canker; Dieback; Fungal diseases; Soil-borne pathogens; Turkey; anthracnose; biological control; dieback; fruit; fungal disease; fungus; pathogen; pathogenicity; soilborne disease | H12: Avocado (Persea americana Milll.) holds a pivotal position in global fruit crops, contributing significantly to the economies of tropical and subtropical regions. However, the rising incidence of diseases poses a substantial risk to avocado production. This comprehensive study investigated the disease landscape in Antalya, the largest avocado cultivation area in the Türkiye. A survey of 2537 avocado trees across 11 regions from 2020 to 2021 revealed alarming disease incidences, particularly in the eastern regions of Gazipasa and Alanya. Dieback, branch canker, anthracnose, and soil-borne root rot were identified as the primary diseases affecting tree canopies, twigs, and branches. Morphological and molecular analyzes unveiled a spectrum of pathogens, with Colletotrichum gloeosporioides dominating in the Mediterranean region. Notably, Phytophthora cinnamomi emerged as a severe threat, causing root rot and decline in avocado trees. Fusarium solani and Fusarium oxysporum, known for their association with tropical fruit crops, were identified in the western parts of Antalya. Additionally, we have detected Neofusicoccum parvum, Lasiodiplodia theobromae, and Neopestalotiopsis rosae in collected samples from avocado trees. The identified pathogens exhibited varying levels of severity in branch canker and anthracnose on avocado branches and leaves. Furthermore, pathogenicity evaluations shed light on the potential of these pathogens to induce severe symptoms, emphasizing the urgency for effective control measures. The exploration of cultural and biological control strategies are crucial for mitigating the impact of branch canker, dieback, and anthracnose diseases, ensuring the sustainability of avocado cultivation in the region. © The Author(s) 2024. | I12: Article | J12: Journal of Plant Diseases and Protection | K12: Importado | L12: scopus_export_Sep 17-2026_64f2de15-f34e-4ffa-b356-5d490b5ac07b.csv | scopus_export_Sep 18-2026_8f28b456-611a-478a-9b87-bb5029e250f3.csv
A13: A0010 | B13: Scopus | C13: Expression of several Phytophthora cinnamomi putative RxLRs provides evidence for virulence roles in avocado | D13: Joubert M.; Backer R.; Engelbrecht J.; Van Den Berg N. | E13: 2021 | F13: 10.1371/journal.pone.0254645 | G13: Persea; Phylogeny; Phytophthora; Virulence; fungal protein; RxLR protein; unclassified drug; amino acid sequence; Article; avocado; controlled study; fungal genome; fungal virulence; gene; gene expression; gene expression profiling; nonhuman; nucleotide sequence; phylogeny; Phytophthora cinnamomi; Phytophthora root rot; root rot; RxLR gene; parasitology; pathogenicity; Persea; Phytophthora; virulence | H13: Phytophthora cinnamomi is a plant pathogenic oomycete that causes Phytophthora root rot of avocado (PRR). Currently, there is a limited understanding of the molecular interactions underlying this disease. Other Phytophthora species employ an arsenal of effector proteins to manipulate host physiology, of which the RxLR effectors contribute to virulence by interfering with host immune responses. The aim of this study was to identify candidate RxLR effectors in P. cinnamomi that play a role in establishing PRR, and to infer possible functions for these effectors. We identified 61 candidate RxLR genes which were expressed during infection of a susceptible avocado rootstock. Several of these genes were present in multiple copies in the P. cinnamomi genome, suggesting that they may contribute to pathogen fitness. Phylogenetic analysis of the manually predicted RxLR protein sequences revealed 12 P. cinnamomi RxLRs that were related to characterised effectors in other Phytophthora spp., providing clues to their functions in planta. Expression profiles of nine more RxLRs point to possible virulence roles in avocado-highlighting a way forward for studies of this interaction. This study represents the first investigation of the expression of P. cinnamomi RxLR genes during the course of avocado infection, and puts forward a pipeline to pinpoint effector genes with potential as virulence determinants, providing a foundation for the future functional characterization of RxLRs that contribute to P. cinnamomi virulence in avocado. © 2021 Joubert et al. This is an open access article distributed under the terms of the Creative Commons Attribution License, which permits unrestricted use, distribution, and reproduction in any medium, provided the original author and source are credited. | I13: Article | J13: PLoS ONE | K13: Importado | L13: scopus_export_Sep 17-2026_64f2de15-f34e-4ffa-b356-5d490b5ac07b.csv
A14: A0011 | B14: Scopus | C14: First Record of Colletotrichum anthrisci Causing Anthracnose on Avocado Fruits in Chile | D14: Bustamante M.I.; Osorio-Navarro C.; Fernández Y.; Bourret T.B.; Zamorano A.; Henríquez-Sáez J.L. | E14: 2022 | F14: 10.3390/pathogens11101204 | G14: etiology; Persea americana; postharvest disease; streptomycin; anthracnose; Article; avocado; Colletotrichum; conidium; controlled study; DNA extraction; DNA sequencing; fungus isolation; mycelial growth; nonhuman; phylogeny; sporogenesis; temperature | H14: Anthracnose caused by Colletotrichum species is one of the most frequent and damaging fungal diseases affecting avocado fruits (Persea americana Mill.) worldwide. In Chile, the disease incidence has increased over the last decades due to the establishment of commercial groves in more humid areas. Since 2018, unusual symptoms of anthracnose have been observed on Hass avocado fruits, with lesions developing a white to gray sporulation. Morphological features and multi-locus phylogenetic analyses using six DNA barcodes (act, chs-1, gapdh, his3, ITS, and tub2) allowed the identification of the causal agent as Colletotrichum anthrisci, a member of the dematium species complex. Pathogenicity was confirmed by inoculating healthy Hass avocado fruits with representative isolates, reproducing the same symptoms initially observed, and successfully reisolating the same isolates from the margin of the necrotic pulp. Previously, several Colletotrichum species belonging to other species complexes have been associated with avocado anthracnose in other countries. To our knowledge, this is the first record of C. anthrisci and of a species of the dematium species complex causing anthracnose on avocado fruits in Chile and worldwide. © 2022 by the authors. | I14: Article | J14: Pathogens | K14: Importado | L14: scopus_export_Sep 17-2026_64f2de15-f34e-4ffa-b356-5d490b5ac07b.csv
A15: A0012 | B15: Scopus | C15: First Report of Fusarium equiseti Causing Postharvest Fruit Rot of Avocado in Türkiye | D15: Bozoğlu T.; Derviş S.; Özer G.; Türkkan M. | E15: 2025 | F15: 10.1111/jph.70131 | G15: Fusarium equiseti; Persea americana; postharvest fruit rot; rpb2 phylogeny; stem-end rot; tef1; Black Sea; amplification; fruit; inoculation; molecular analysis; phylogeny; RNA; root rot | H15: In September 2024, postharvest fruit rot, including stem-end rot, was observed on avocado in the Altınordu district of Ordu province, located in the Eastern Black Sea Region of Türkiye. A market survey revealed that 5% of fruit exhibited fruit rot symptoms, a subset of which displayed stem-end rot symptoms, including brown to black lesions extending into the mesocarp, shrivelling and fungal mycelium growth. Fusarium equiseti was identified as the causal agent through morphological characterisation and molecular analysis using PCR amplification and sequencing of translation elongation factor 1-alpha (tef1) and RNA polymerase II second largest subunit (rpb2) gene sequences, including phylogenetic analysis. Artificial inoculation and subsequent re-isolation confirmed Koch's postulates, verifying F. equiseti as the causal pathogen. This is the first report of F. equiseti causing both fruit rot and stem-end rot on avocado in Türkiye, highlighting the need for improved postharvest disease management strategies to reduce economic losses in Türkiye's avocado industry. © 2025 The Author(s). Journal of Phytopathology published by Wiley-VCH GmbH. | I15: Article | J15: Journal of Phytopathology | K15: Importado | L15: scopus_export_Sep 17-2026_64f2de15-f34e-4ffa-b356-5d490b5ac07b.csv | scopus_export_Sep 18-2026_4e658477-f683-499d-a469-81d37efaa96b.csv
... A21: A0018 | B21: Scopus | C21: Identification and Pathogenicity of Botryosphaeriaceae, Colletotrichum, and Phytophthora Species Associated with Avocado Diseases in Italy | D21: Linaldeddu B.T.; Bregant C.; Muscas J.; Maddau L.; Vecchio L.; Polizzi G.; Aiello D. | E21: 2026 | F21: 10.3390/agriculture16101035 | G21: Botryosphaeriaceae; co-infections; holistic diagnosis; oomycetes | H21: With the rapid expansion of avocado cultivation in southern Italy, growers have had to deal with the emergence of new diseases often caused by invasive and polyphagous pathogens responsible for leaf spot, branch cankers, dieback and fruit and root rot. Given the severity of these emerging diseases, a study was conducted in the main avocado growing areas in Sardinia and Sicily (Italy) to isolate and characterize the causal agents. Specifically, a total of 430 symptomatic leaf, fruit, branch, stem and root samples were collected and examined. Isolations performed on both non-selective and selective growth media yielded 22 species (fungi and oomycetes) belonging to the genera Botryosphaeria, Colletotrichum, Diplodia, Dothiorella, Macrophomina, Neofusicoccum and Phytophthora, including 14 new host–pathogen records in Italy. Notably, Neofusicoccum australe, Phytophthora cinnamomi and Phytophthora palmivora emerged as the main pathogens involved in the emerging avocado diseases. The identified pathogens were often isolated simultaneously from the same plants, which exhibited a complex of symptoms. Pathogenicity bioassays have helped to clarify the differences in aggressiveness among the different species and their specificity towards the different plant organs. The results achieved suggest that avocado orchards’ productivity and profitability is threatened by a plethora of unrelated pathogens whose control represents a major challenge for the success of this crop in Italy. © 2026 by the authors. | I21: Article | J21: Agriculture (Switzerland) | K21: Importado | L21: scopus_export_Sep 18-2026_96199bb3-e2ff-4aa3-a2d7-ec2db6aced85.csv
A22: A0019 | B22: Scopus | C22: Identification and Pathogenicity of Fungal Pathogens Associated with Stem End Rots of Avocado Fruits in Kenya | D22: Wanjiku E.K.; Waceke J.W.; Wanjala B.W.; Mbaka J.N. | E22: 2020 | F22: 10.1155/2020/4063697 | H22: Losses associated with stem end rot (SER) of avocado fruits have been reported in all avocado growing regions of the world. In Kenya, mature avocado fruits present SER symptoms during storage and marketing, but the disease causal agent(s) has not been established. This study aimed to identify the fungal pathogen(s) associated with avocado SER in Kenya and evaluate its pathogenicity. Fungal isolates were collected from symptomatic avocado fruits from randomly selected orchards and major markets within Murang'a County, a major avocado growing region in Kenya, between September 2017 and March 2018. A total of 207 and 125 fungal isolates, recovered from orchards and major markets, respectively, were identified morphologically and further confirmed by molecular techniques. The identified isolates were Lasiodiplodia theobromae (39.8%), Neofusicoccum parvum (24.4%), Nectria pseudotrichia (18.4%), Fusarium solani (7.2%), F. oxysporum (5.1%), F. equiseti (3.9%), and Geotricum candidum (1.2%). Geotricum candidum was exclusively recovered from fruits from the market. In the pathogenicity test, L. theobromae, N. parvum, and N. pseudotrichia caused the most severe SER symptoms. Consequently, they were considered to be the major pathogens of SER of avocado fruits in Kenya. To our knowledge, this is the first report of SER pathogen of avocado fruits in Kenya. Given the significant contribution of avocado fruits to household income and foreign exchange in Kenya, this information is significant to further develop management strategies of postharvest loss of avocado fruits in Kenya. © 2020 E. K. Wanjiku et al. | I22: Article | J22: International Journal of Microbiology | K22: Importado | L22: scopus_export_Sep 18-2026_6573fc91-2043-414f-a3dc-1112c7ddea01.csv
A23: A0020 | B23: Scopus | C23: Identification and pathogenicity of fungal pathogens on avocado 034 in Vietnam | D23: Lieu M.D.; Huynh T.B.T.; Nguyen T.B.; Phuong T.V.; Dang T.K.T.; Nguyen T.H. | E23: 2025 | F23: 10.26656/fr.2017.9(5).332 | G23: Avocado; Fungal pathogen; Pathogenicity; Post-harvest; Article; Aspergillus flavus; Aspergillus niger; avocado; Colletotrichum; fungal pathogen; Fusarium solani; gene sequence; Geotrichum; growth rate; infectious agent; Lasiodiplodia theobromae; microscopy; Mucor; mycelium; nonhuman; pathogenicity; relative humidity; Sanger sequencing; soybean; Viet Nam | H23: Avocado (Persea americana Mill.) is a popular fruit because of its high nutritional content and high economic value. However, this fruit is susceptible to microbial invasion, especially diseases caused by fungi, causing heavy post-harvest losses. The study aimed to determine the origin of fungal pathogens through isolation and identification based on microscopic morphological characteristics, pathogenicity tests, and gene sequences. Significant fungal pathogens causing spoilage diseases on avocados were identified by isolating spoiled avocado samples from five regions in Lam Dong province. Samples of avocado 034 (Persea americana Mill. Cv. 034) with natural disease symptoms were collected with 138 representatives of six genera, including Lasiodiplodia spp., Colletotrichum spp., Aspergillus spp., Fusarium spp., Geotrichum spp., and Mucor spp. The growth rate of mycelium showed the genus Mucor spp. had the fastest growth on PDA medium at 30oC, followed by the genera Lasiodiplodia spp., Colletotrichum spp., Aspergillus spp., Fusarium spp. and Geotrichum spp. However, the pathogenicity test evaluation indicated that the genera causing the most severe damage on avocados were Lasiodiplodia spp and Colletotrichum spp., with 77.78% and 67.90% of the spoilage rate, respectively. Next were the genera Fusarium spp., Aspergillus spp., Geotrichum spp., and Mucor spp., with damage ranging from 40.74% to 42.59%. © 2025 The Authors. | I23: Article | J23: Food Research | K23: Importado | L23: scopus_export_Sep 17-2026_64f2de15-f34e-4ffa-b356-5d490b5ac07b.csv
A24: A0021 | B24: Scopus | C24: Identification of Phytophthora cinnamomi CRN effectors and their roles in manipulating cell death during Persea americana infection | D24: Midgley K.A.; van den Berg N.; Backer R.; Swart V. | E24: 2024 | F24: 10.1186/s12864-024-10358-3 | G24: Alleles; Crinkler effectors; Hemibiotroph; In silico; Molecular characterization; Phytophthora; Plant-pathogen interactions; Protein prediction; Cell Death; Persea; Phytophthora; Plant Diseases; allele; Article; avocado; cell death; controlled study; gene expression profiling; host range; infection; nonhuman; phylogenetic tree; phylogeny; Phytophthora cinnamomi; prediction; protein structure; reverse transcription polymerase chain reaction; RNA sequence; RNA sequencing; Sanger sequencing; single nucleotide polymorphism; validation process; genetics; microbiology; pathogenicity; Persea; physiology; Phytophthora; plant disease | H24: The oomycete Phytophthora cinnamomi is a devastating plant pathogen with a notably broad host range. It is the causal agent of Phytophthora root rot (PRR), arguably the most economically important yield-limiting disease in Persea americana (avocado). Despite this, our understanding of the mechanisms P. cinnamomi employs to infect and successfully colonize avocado remains limited, particularly regarding the pathogen’s ability to maintain its biotrophic and necrotrophic lifestyles during infection. The pathogen utilises a large repertoire of effector proteins which function in facilitating and establishing disease in susceptible host plants. Crinkling and necrosis effectors (CRN/Crinklers) are suspected to manipulate cell death to aid in maintenance of the pathogens biotrophic and necrotrophic lifestyles during different stages of infection. The current study identified 25 P. cinnamomi CRN effectors from the GKB4 genome using an HMM profile and assigned putative function to them as either cell death inducers or suppressors. Function was assigned to 10 PcinCRNs by analysing their RNA-seq expression profiles, relatedness to other functionally characterised Phytophthora CRNs and tertiary protein predictions. The full-length coding sequences for these PcinCRNs were confirmed by Sanger sequencing, six of which were found to have two divergent alleles. The presence of alleles indicates that the proteins encoded may perform contradicting functions in cell death manipulation, or function in different host plant species. Overall, this study provides a foundation for future research on P. cinnamomi infection and cell death manipulation mechanisms. © The Author(s) 2024. | I24: Article | J24: BMC Genomics | K24: Importado | L24: scopus_export_Sep 17-2026_64f2de15-f34e-4ffa-b356-5d490b5ac07b.csv
A25: A0022 | B25: Scopus | C25: Identification, pathogenicity and distribution of the causal agents of dieback in avocado orchards in Spain | D25: Arjona-Girona I.; Ruano-Rosa D.; López-Herrera C.J. | E25: 2019 | F25: 10.5424/sjar/2019171-13561 | G25: Botryosphaeriaceae; Colletotrichum; Lasiodiplodia; Neofusicoccum; Persea americana | H25: An increased incidence of dieback from branches in several avocado orchards in southern Spain was observed in 2014. Surveys were conducted from May to October 2014, sampling the affected branches to isolate the causal agents. A total of 68 fungal isolates, recovered from ten avocado orchards, were identified, by morphological characterisation and DNA sequencing, as belonging to the genera: Neofusicoccum parvum (50%), Colletotrichum gloeosporioides (17.6%), Neofusicoccum luteum (16.2%), Neofusicoccum australe (13.2%), Neofusicoccum mediterraneum (1.5%) and Lasiodiplodia theobromae (1.5%). A decreasing level of virulence in artificial inoculations on avocado plants was observed in N. parvum, N. luteum, N. mediterraneum, N. australe, C. gloeosporioides and L. theobromae, there were significant differences among N. parvum and the rest of species of this genus, and significant differences were only observed between N. luteum and C. gloeosporioides. The geographical distribution of N. parvum and N. Luteum covers different areas, while C. gloeosporioides and N. australe are located only in the areas around Benamocarra and Vélez-Málaga (southern Spain), while N. mediterraneum and L. theobromae appear only occasionally. This is the first study of avocado branch cankers in Spain which identifies the causal agents and establishes their pathogenicity groups, with N. parvum as the most important causal agent of avocado dieback in this area. © 2019 INIA. | I25: Article | J25: Spanish Journal of Agricultural Research | K25: Importado | L25: scopus_export_Sep 18-2026_8f28b456-611a-478a-9b87-bb5029e250f3.csv
A26: A0023 | B26: Scopus | C26: Integrated proposal for management of root rot caused by Phytophthora cinnamomi in avocado cv. Hass crops | D26: Ramírez-Gil J.G.; Morales-Osorio J.G. | E26: 2020 | F26: 10.1016/j.cropro.2020.105271 | G26: Biological control; New alternatives; Reduction of disease; Sustainable diseases management; Bacillus sp.; Basidiomycota; Bovinae; Persea americana; Phytophthora cinnamomi; Trichoderma; alga; biocontrol agent; biological control; crop plant; disease control; fungicide; fungus; integrated approach; microorganism; pathogen; pesticide application; root rot; symptom | H26: Phytophthora cinnamomi is the most important pathogen in avocado crops that causes the disease named avocado root rot (PRR). This disease affects the root system and induces multiple symptoms that end with plant death and causes large economic losses. PRR management is based almost exclusively on the use of fungicides (metalaxyl and phosphites). This situation led to inefficient management practices with apparently satisfactory results only in short periods. The objective of this work was to evaluate different PRR management practices under in vitro, net house and field conditions. The initial part of the study was carried out under in vitro and net house conditions evaluating different types of ions (boron, zinc and manganese chelate), the auxin α naphthaleneacetic, fungicides (potassium phosphite, fosetyl aluminium and metalaxyl) and microorganisms associated with biological control of diseases. For field conditions, the most promising strategies were selected, which included fungicide use (rotation of metalaxyl and phosphites), organic matter in the form of residues of vegetables and mushrooms, use of foliar (manganese) and soil (calcium, magnesium, phosphorus, and silicon) ions, additions of bovine manure, beneficial microorganisms (Rizoglomus fasciculatum, Trichoderma sp., and Bacillus sp.), edaphic application of auxin and an energy source (sucrose). Results indicated that individual control methods of PRR are not sustainable over time. However, the implementation of a disease integrated management program including several strategies of control proved to be effective for PRR. At the same time that PRR was satisfactorily managed, the economic sustainability was achieved and it was possible to reduce the reliance on phosphonate applications. © 2020 Elsevier Ltd | I26: Article | J26: Crop Protection | K26: Importado | L26: scopus_export_Sep 18-2026_162c1d26-553e-41ee-8ea1-e9ecd3a7eea2.csv
A27: A0024 | B27: Scopus | C27: Integrated Strategies to Reduce Botryosphaeriaceae-Associated Dieback in Avocado Under Mediterranean Climatic Stress | D27: Guirado-Manzano L.; Santamaría-Ortega J.F.; Sarmiento D.; Guirado E.; Pulido-Ruiz M.; de Vicente A.; Fernández-Ortuño D.; Cazorla F.M.; Arrebola E. | E27: 2026 | F27: 10.3390/horticulturae12060673 | G27: autumn pruning; avocado; eco-friendly control; gibberellic acid; integrated disease management; Neofusicoccum; potassium silicate | H27: Avocado (Persea americana Mill.) is gaining economic relevance in Mediterranean regions such as southern Spain. In recent years, production has been severely affected by dieback caused by Botryosphaeriaceae species, a problem intensified under drought conditions. Conventional chemical control has shown limited effectiveness due to the scarce availability of fungicides and the difficulty of targeting pathogens colonizing lignified tissues. This study therefore evaluated eco-friendly control strategies comparing their performance with conventional fungicides and complementary cultural practices within an integrated management framework. Varietal tolerance significantly influenced symptom development and yield, with younger trees (1–2 years old) being more susceptible. Among the tested treatments, potassium silicate (K-Link) was associated with moderate reduction in disease intensity, with decreases in disease index ranging from 5–10%. Other products, including the biostimulant Brotolom® SOILFORCE (BTL) and the disinfectant Huwa San® TR50, also showed reductions in disease severity (approximately 5% and up to 14%, respectively), although their effects varied depending on cultivar and season. Cultural practices such as autumn pruning reduced symptoms and improved yield but required greater economic and labor inputs. In contrast, gibberellic acid was highly effective, reducing flowering, improving canopy balance, decreasing dieback incidence by 28%, and increasing yield by 34%. Integrating eco-friendly products, particularly potassium silicate, with targeted cultural practices and gibberellic acid application provides effective and sustainable tools to mitigate avocado dieback under Mediterranean conditions. © 2026 by the authors. | I27: Article | J27: Horticulturae | K27: Importado | L27: scopus_export_Sep 18-2026_96199bb3-e2ff-4aa3-a2d7-ec2db6aced85.csv
A28: A0025 | B28: Scopus | C28: Lasiodiplodia theobromae disease symptom development in young avocado (Persea americana L.) plants depends on the inoculation method | D28: Rodríguez-Gálvez E.; Haro-Diaz C.; Maza-Aguirre S.; Canahuire-Castillo F.; Sullón-Saucedo J.; Deising H.B. | E28: 2025 | F28: 10.1007/s40858-025-00700-9 | G28: Avocado; External and internal necrosis; Lasiodiplodia theobromae; Persea americana; Symptom development; Virulence | H28: Lasiodiplodia theobromae is a pathogenic fungus of more than 500 plant species, including avocado (Persea americana Mill.). The global production volume of avocado exceeded 911,000 metric tons in 2023. Although detailed quantitative surveys of yield losses caused by L. theobromae are not available for most avocado-producing regions, estimates indicate that this pathogen is associated with stem-end rot disease in 30-35% of plots located in the Department of Antioquia in Colombia (Ramírez-Gil et al. Heliyon 7: e05905, 2021), suggesting an enormous economic impact. As yield losses strongly depend on the virulence of isolates, a reliable method for determining their aggressiveness is indispensable for initiating disease control measures. In this study, we compared progression of external and internal necrosis caused by the aggressive L. theobromae isolate LA-VLCA3 inoculated into wounded middle parts of the stem and onto excised apices. Irrespective of the inoculation method, internal progression of necrosis preceded that of external necrosis. Spreading of external and internal necrosis was significantly more severe in plants inoculated at the apex than in mid-stem inoculated plants. We conclude that apex inoculation causes stronger symptoms and is therefore better suited to compare virulence of isolates than mid-stem inoculation. © The Author(s) 2025. | I28: Article | J28: Tropical Plant Pathology | K28: Importado | L28: scopus_export_Sep 17-2026_64f2de15-f34e-4ffa-b356-5d490b5ac07b.csv | scopus_export_Sep 18-2026_8f28b456-611a-478a-9b87-bb5029e250f3.csv
A29: A0026 | B29: Scopus | C29: Multigene phylogeny and diversity of Phytophthora and Phytopythium species associated with avocado root rot in India and development of a point-of-care LAMP assay for Phytophthora cinnamomi and Phytopythium vexans | D29: Madhu G.S.; Rani A.T.; Muralidhara B.M.; Deepak G.N.; Rajendiran S.; Ayyandurai M.; Venkataravanappa V. | E29: 2025 | F29: 10.1016/j.pmpp.2025.102735 | G29: Avocado; LAMP; Phytophthora cinnamomi; Phytophthora species; Phytopythium vexans | H29: Avocado root rot, predominantly caused by Phytophthora cinnamomi poses a major threat to avocado cultivation worldwide. However, the potential role of other Phytophthora and Phytophthora-like oomycete species in avocado decline remains largely unexplored. To address this knowledge gap, surveys were conducted across avocado orchards in the Western Ghats region of Karnataka, Kerala, and Tamil Nadu, India, to assess the diversity and pathogenicity of Phytophthora and Phytopythium species associated with root rot. Oomycete isolates were recovered from symptomatic root samples collected from 42 avocado orchards. Morphological characterization, coupled with multilocus sequence analysis targeting the internal transcribed spacer (ITS) region, cytochrome c oxidase subunit 1 (COX1), and β-tubulin (β-tub) genes, facilitated species identification. Furthermore, pathogenicity tests confirmed the virulence of the isolates. Among the surveyed orchards, Phytophthora species were isolated from 26 orchards, with P. cinnamomi being the most frequently detected, occurring in 22 orchards. Additionally, P. tropicalis was identified in 2 orchards, while P. nicotianae and P. kelmanii were each found in 1 orchard. In parallel, 9 Phytopythium isolates were recovered, with Phytopythium vexans detected in 7 orchards and Phytopythium chamaehyphon in 2 orchards. Among all isolates, P. cinnamomi exhibited the highest virulence, underscoring its primary role in avocado root rot. To facilitate early and accurate detection of the predominant pathogens, Phytophthora cinnamomi and Phytopythium vexans, in infected plants and nursery seedlings, a loop-mediated isothermal amplification (LAMP) assay was developed. The sensitivity of LAMP assay detection limits for P. cinnamomi was 25 pg, while for Pp. vexans was detected at 50 pg. This assay provides a rapid, highly sensitive, and reliable diagnostic tool, strengthening disease surveillance and management strategies for avocado cultivation in the region. This study highlighted the novel host record of P. Kelmanii and Pp. chamaehyphon in avocado root rot and Pp. vexans first report in India. © 2025 Elsevier Ltd | I29: Article | J29: Physiological and Molecular Plant Pathology | K29: Importado | L29: scopus_export_Sep 18-2026_162c1d26-553e-41ee-8ea1-e9ecd3a7eea2.csv
A30: A0027 | B30: Scopus | C30: Penetration by Botryosphaeriaceae species in avocado, guava and persimmon fruit during postharvest | D30: Navarro B.L.; Edwards Molina J.P.; Nogueira Júnior A.F. | E30: 2022 | F30: 10.1111/jph.13055 | G30: Botryosphaeria dothidea; Diospyros kaki; Lasiodiplodia pseudotheobromae; Neofusicoccum parvum; Persea americana; postharvest diseases; Psidium guajava; scanning electron microscopy; Botryosphaeria dothidea; Botryosphaeriaceae; Diospyros; Diospyros kaki; Dothidea; Lasiodiplodia; Persea americana; Psidium guajava; aggression; disease control; fruit; fungus; host specificity; scanning electron microscopy; stomata | H30: Botryosphaeriaceae species have a wide host range and a worldwide distribution. These fungal species can colonize several plant organs, such as the trunk, leaves and fruit. Some Botryosphaeriaceae species cause important diseases on persimmon, avocado and guava fruit. However, there is a lack of information regarding the mechanisms of penetration by Botryosphaeriaceae species on these tropical and subtropical fruits. This study aimed to better understand the mechanisms involved in fungal penetration, host specificity and aggressiveness of Botryosphaeria dothidea, Lasiodiplodia pseudotheobromae and Neofusicoccum parvum on avocado (Persea americana), guava (Psidium guajava) and persimmon (Diospyros kaki) fruit. Scanning electron microscopy (SEM) image analysis showed that in avocado fruit, the three studied Botryosphaeriaceae species penetrated through lenticels. In guava fruit, penetration through stomata was verified for Botryosphaeria dothidea and Neofusicoccum parvum. In persimmon fruit, an appressoria-like structure was observed for B. dothidea, which suggests direct penetration. Disease incidence in wounded fruit was 24% higher than in non-wounded fruit. L. pseudotheobromae and N. parvum showed differences in aggressiveness in guava fruit. The longest incubation period was observed for N. parvum inoculated on guava, with an average of 4.5 days, and the shortest incubation period was verified for B. dothidea inoculated on avocado, with an average of 2.8 days. The area under the disease progress curve (AUDPC) did not differ between Botryosphaeriaceae species on avocado, whereas on guava and persimmon fruit, the AUDPC was lower for B. dothidea. The information regarding penetration mechanisms and aggressiveness is important to improve postharvest disease control strategies. © 2021 The Authors. Journal of Phytopathology published by Wiley-VCH GmbH | I30: Article | J30: Journal of Phytopathology | K30: Importado | L30: scopus_export_Sep 17-2026_64f2de15-f34e-4ffa-b356-5d490b5ac07b.csv
A31: A0028 | B31: Scopus | C31: Phylogenetic diversity and pathogenicity of Colletotrichum species associated with avocado anthracnose in Chile | D31: Bustamante M.I.; Fernández Y.; Navarro C.O.; Cárdenas C.; Bourret T.B.; Eskalen A.; Henríquez-Sáez J.L. | E31: 2026 | F31: 10.36253/phyto-16790 | G31: Etiology; Persea americana; postharvest disease | H31: Anthracnose, caused by Colletotrichum species, is a major disease of avocado (Persea americana) that significantly reduces fruit quality and export potential in Chile. Colletotrichum species associated with this disease were identified and their pathogenicity to avocado was assessed. In the summer of 2018, healthy fruits (n = 1,335) were sampled from three commercial groves located in the Metropolitan, O’Higgins and Valparaíso regions of Chile, and from a non-commercial grove and local markets. Fruits were stored until symptoms developed, indicating anthracnose incidence in commercial groves ranging from 10 to 50%. A total of 146 fungal isolates were obtained from symptomatic fruit and were initially identified as Colletotrichum spp. Fifty representative isolates were further identified through multilocus phylogenetic analyses. Ten species belonging to four species complexes were identified. Colletotrichum cf. cigarro was the most frequent taxon (n = 17), followed by C. pyricola (n = 9), C. gloeosporioides (n = 6), C. jiangxiense (n = 5), C. karsti (n = 4), C. anthrisci (n = 3), C. brassicicola (n = 3), C. laurosilvaticum (n = 1), C. fructicola (n = 1), and C. perseae (n = 1). Pathogenicity tests reproduced anthracnose symptoms in inoculated fruits, whereas control fruits remained symptomless, and revealed differences in virulence among isolates and species. This study provides the first report of C. brassicicola, C. laurosilvaticum and C. pyricola as causal agents of avocado anthracnose, highlights the diversity of Colletotrichum species in Chilean avocado groves, and provides insights for improved management strategies for avocado anthracnose. © 2026 Author(s). This is an open access, peer-reviewed article published by Firenze University Press (https://www.fupress.com) and distributed, except where otherwise noted, under the terms of the CC BY 4.0 License for content and CC0 1.0 Universal for metadata. | I31: Article | J31: Phytopathologia Mediterranea | K31: Importado | L31: scopus_export_Sep 17-2026_64f2de15-f34e-4ffa-b356-5d490b5ac07b.csv
A32: A0029 | B32: Scopus | C32: Phytophthora cinnamomi Populations Affecting Avocado in California Show Low Differentiation, Phenotypic Variability, and Introductions from Mexico | D32: Shands A.C.; Mondragón-Flores A.; Valencia V.; Hua V.; Cauldron N.C.; Grünwald N.J.; Fernández-Pavía S.P.; Manosalva P.M. | E32: 2025 | F32: 10.1094/MPMI-08-24-0101-R | G32: oomycete; Phytophthora root rot; ploidy; population biology; potassium phosphite; California; Genetic Variation; Mexico; Persea; Phenotype; Phylogeny; Phytophthora; Plant Diseases; Plant Roots; California; genetic variation; genetics; Mexico; microbiology; parasitology; pathogenicity; Persea; phenotype; phylogeny; physiology; Phytophthora; plant disease; plant root | H32: Phytophthora root rot (PRR), caused by Phytophthora cinnamomi, is one of the most devastating avocado diseases worldwide. We previously reported a group of genetically distinct, more virulent, and less fungicide-sensitive isolates corresponding to the A2 clade II clonal population in southern avocado-growing regions in California that may have originated from Mexico. To test this hypothesis, we assessed the genetic and phenotypic diversity of the California and Mexico avocado P. cinnamomi populations. We found that P. cinnamomi populations in these two locations belong to the two previously described A2 clades. Higher genetic differentiation was detected among Mexican isolates when compared with the populations from California; however, most Mexican isolates clustered with the California A2 clade II populations, providing evidence for the Mexican origin of these isolates in southern avocado-growing regions. With the exception of one diploid Mexican isolate, all isolates were estimated to be triploid based on inferred allele ratios. Despite clonality, wide phenotypic variability was detected within and among populations regarding growth rate, optimal growth temperature, fungicide sensitivity, and virulence. Interestingly, contrasting virulence patterns were found depending on the host and infected tissue utilized. This study reveals the adaptative capacity of clonal P. cinnamomi populations to local environments and control methods. Pathogen migration between Mexico and California was also inferred, which highlights a pathway that should be surveilled if further emergence is to be avoided. Monitoring and characterizing the P. cinnamomi populations is critical to developing effective and durable PRR control methods to ensure the sustainability of the avocado industry worldwide. © 2025 The Author(s). | I32: Article | J32: Molecular Plant-Microbe Interactions | K32: Importado | L32: scopus_export_Sep 18-2026_162c1d26-553e-41ee-8ea1-e9ecd3a7eea2.csv
A33: A0030 | B33: Scopus | C33: Phytophthora root rot induces compositional and functional changes in avocado rhizosphere bacterial communities | D33: Alfaro-García R.G.; Vargas-Mejía P.; Patiño-Conde V.; Rebollar E.A.; Guerrero-Analco J.A.; Vega-Arreguín J.; Reverchon F.; Méndez-Bravo A. | E33: 2026 | F33: 10.1093/femsmc/xtag025 | G33: Dysbiosis; Metatranscriptomics; Persea americana; Phytophthora cinnamomi; Rhizobacteria; Stress response | H33: Understanding how plant pathogens modulate the rhizosphere microbiota is essential to integrated disease management. Here, the compositional and functional shifts in the avocado rhizosphere bacteriome induced by Phytophthora cinnamomi were assessed to identify bacterial taxa enriched in the symptomatic condition and elucidate the microbial functions modulated by the infection. Metabarcoding and metatranscriptomics analyses revealed that Phytophthora root rot (PRR) induced compositional shifts in bacterial communities, leading to the enrichment of members of MND1, RB41, and Nitrospira. Functional analysis showed that this enrichment might be due to the release of nutrients following root rot, as carbohydrate metabolism was stimulated in rhizobacterial communities of infected trees. Moreover, the relative abundance of transcripts from genes associated with stress response and cell signaling increased in some of the most active genera in the rhizosphere of PRR-symptomatic trees, suggesting their potential to mitigate the adverse effects of infection. These findings highlight the need to combine compositional and functional microbiome data to differentiate between taxa attracted by nutrient release and those contributing to the plant defense. The interactions of beneficial bacterial taxa with the pathogen should be further studied, as they may constitute promising biocontrol agents. © The Author(s) 2026. Published by Oxford University Press on behalf of FEMS. This is an Open Access article distributed under the terms of the Creative Commons Attribution License (https://creativecommons.org/licenses/by/4.0/), which permits unrestricted reuse, distribution, and reproduction in any medium, provided the original work is properly cited. | I33: Article | J33: FEMS Microbes | K33: Importado | L33: scopus_export_Sep 17-2026_64f2de15-f34e-4ffa-b356-5d490b5ac07b.csv
A34: A0031 | B34: Scopus | C34: Phytophthora Root Rot Modifies the Composition of the Avocado Rhizosphere Microbiome and Increases the Abundance of Opportunistic Fungal Pathogens | D34: Solís-García I.A.; Ceballos-Luna O.; Cortazar-Murillo E.M.; Desgarennes D.; Garay-Serrano E.; Patiño-Conde V.; Guevara-Avendaño E.; Méndez-Bravo A.; Reverchon F. | E34: 2021 | F34: 10.3389/fmicb.2020.574110 | G34: Fusarium; Mortierella; Persea americana; rhizosphere microbial communities; root necrotizing fungi; chloramphenicol; DNA 16S; polyketide; RNA 16S; Acidobacteria; Actinobacteria; antibiotic resistance; Article; avocado; Bacillales; Bacillus; bacterial microbiome; bacterium identification; bacterium isolation; Bacteroidetes; Burkholderiales; Chloroflexi; defoliation; DNA extraction; Dothideomycetes; Firmicutes; Fusarium; gene amplification; gene sequence; health status; Helotiales; Lasiodiplodia; metagenomics; microbial community; microbial diversity; microbiome; morphotype; Mortierella; mycelial growth; nonhuman; pathogenicity; Phytophthora; Planctomycetes; plant growth; polymerase chain reaction; Proteobacteria; Pseudomonadales; quorum sensing; Rhizobiales; rhizosphere; root rot; Sanger sequencing; Scytalidium; Veracruz (state); Verrucomicrobia | H34: The structure and function of rhizosphere microbial communities are affected by the plant health status. In this study, we investigated the effect of root rot on the avocado rhizosphere microbiome, using 16S rDNA and ITS sequencing. Furthermore, we isolated potential fungal pathogens associated with root rot symptoms and assessed their pathogenic activity on avocado. We found that root rot did not affect species richness, diversity or community structure, but induced changes in the relative abundance of several microbial taxa. Root rot increased the proportion of Pseudomonadales and Burkholderiales in the rhizosphere but reduced that of Actinobacteria, Bacillus spp. and Rhizobiales. An increase in putative opportunistic fungal pathogens was also detected in the roots of symptomatic trees; the potential pathogenicity of Mortierella sp., Fusarium spp., Lasiodiplodia sp. and Scytalidium sp., is reported for the first time for the State of Veracruz, Mexico. Root rot also potentially modified the predicted functions carried out by rhizobacteria, reducing the proportion of categories linked with the lipid and amino-acid metabolisms whilst promoting those associated with quorum sensing, virulence, and antibiotic resistance. Altogether, our results could help identifying microbial taxa associated to the disease causal agents and direct the selection of plant growth-promoting bacteria for the development of biocontrol microbial consortia. © Copyright © 2021 Solís-García, Ceballos-Luna, Cortazar-Murillo, Desgarennes, Garay-Serrano, Patiño-Conde, Guevara-Avendaño, Méndez-Bravo and Reverchon. | I34: Article | J34: Frontiers in Microbiology | K34: Importado | L34: scopus_export_Sep 17-2026_64f2de15-f34e-4ffa-b356-5d490b5ac07b.csv
... A38: A0035 | B38: Scopus | C38: Role of the oxidative metabolism in induced resistance or susceptibility mechanism during the interaction of avocado with Phytophthora cinnamomi Rands.; [Papel do metabolismo oxidativo na resistência induzida ou mecanismo de suscetibilidade durante a interação do abacate com Phytophthora cinnamomi Rands.] | D38: Guarnizo N.; Rivera O.J.M.; Herrero V.F.; Florez J.E.M.; Jaramillo C.A.P.; Oliveros D.; Lorza E.A.R. | E38: 2025 | F38: 10.1590/0100-5405/264502 | G38: antioxidant; apoptosis; oxidative stress; Persea americana; Phytophthora root rot; plant defense | H38: The disease caused by the oomycete Phytophthora cinnamomi Rands affects most avocado (Persea americana) varieties, requiring additional tools for the selection of resistant materials. In the present study, induction of defense responses related to the oxidative metabolism in avocado was evaluated as a support for establishing its role in the defense responses during infection by this oomycete. Infection trials were carried out with the avocado clones ‘Duke 7’ (tolerant) and ‘Hass’ (susceptible), which had their stem base inoculated with the pathogen and whole leaves sampled at 0, 3, 24, 48 and 120 hours after infection (hai), for subsequent evaluation of the activities of the enzymes superoxide dismutase (SOD) and ascorbate peroxidase (APX), as well as for assessment of free radical scavenging capacity, total polyphenol content and caspase 3-like activity. The area under the disease progress curve was 1.3 and 14.8 (cm.day-1) for ‘Duke 7’ and ‘Hass’, respectively, and the former showed high resistance to the oomycete, which correlated with higher APX activity, higher free radical scavenger activity, and expression of caspase 3-like activity. Resistance or susceptibility in avocado during interaction with Phytophthora cinnamomi is suggested to be mediated by the participation of induced and innate antioxidants and by the induction of apoptosis responses in the resistant genotype ‘Duke 7’, whereas there is lack of such responses in ‘Hass’, the susceptible genotype. © 2025, Universidade Estadual Paulista (UNESP). All rights reserved. | I38: Article | J38: Summa Phytopathologica | K38: Importado | L38: scopus_export_Sep 17-2026_64f2de15-f34e-4ffa-b356-5d490b5ac07b.csv
A39: A0036 | B39: Scopus | C39: Suppression of Stem-End Rot on Avocado Fruit Using Trichoderma spp. In the Central Highlands of Kenya | D39: Wanjiku E.K.; Waceke J.W.; Mbaka J.N. | E39: 2021 | F39: 10.1155/2021/8867858 | H39: Demand for organic avocado fruits, together with stringent food safety standards in the global market, has made producers to use alternative, safe, and consumer-friendly strategies of controlling the postharvest fungal disease of avocado fruits. This study assessed the in vitro efficacy of Trichoderma spp. (T. atroviride, T. virens, T. asperellum, and T. harzianum) against isolated avocado stem-end rot (SER) fungal pathogens (Lasiodiplodia theobromae, Neofusicoccum parvum, Nectria pseudotrichia, and Fusarium solani) using a dual culture technique. The Trichoderma spp. were also evaluated singly on postharvest "Hass"avocado fruits. Spore suspension at 5 × 104 conidial/ml of the Trichoderma spp. was applied on the avocado fruits at three time points, twenty-four hours before the fungal pathogen (preinoculation), at the same time as the fungal pathogen (concurrent inoculation), and 24 hours after the fungal pathogen (postinoculation). In the in vitro study, T. atroviride showed the highest mycelial growth inhibition against N. parvum (48%), N. pseudotrichia (55%), and F. solani (32.95%), while T. harzianum had the highest mycelial growth inhibition against L. theobromae. Trichoderma asperellum was the least effective in inhibiting the mycelial growth of all the pathogens. Similarly, T. virens showed the highest mycelial growth inhibition against N. pseudotrichia at 45% inhibition. On postharvest "Hass"fruits, T. atroviride showed the highest efficacy against N. parvum, N. pseudotrichia, and F. solani in all the applications. Trichoderma virens and T. harzianum were most effective against all the pathogens during postinoculation, while Lasiodiplodia theobromae was best controlled by T. virens, T. harzianum, and T. asperellum during postinoculation. Both T. atroviride and T. harzianum present a potential alternative to synthetic fungicides against postharvest diseases of avocado fruits, and further tests under field conditions to be done to validate their efficacy. The possibility of using Trichoderma spp. in the management of SER on avocado fruits at a commercial level should also be explored. © 2021 E. K. Wanjiku et al. | I39: Article | J39: Advances in Agriculture | K39: Importado | L39: scopus_export_Sep 18-2026_6573fc91-2043-414f-a3dc-1112c7ddea01.csv
A40: A0037 | B40: Scopus | C40: The expression of the NPR1-dependent defense response pathway genes in Persea americana (Mill.) following infection with Phytophthora cinnamomi | D40: Backer R.; Naidoo S.; van den Berg N. | E40: 2023 | F40: 10.1186/s12870-023-04541-z | G40: NPR1; Pathogenesis-related; Persea americana; Phytophthora cinnamomi; RNA-sequencing; Salicylic acid; Systemic acquired resistance | H40: A plant’s defense against pathogens involves an extensive set of phytohormone regulated defense signaling pathways. The salicylic acid (SA)-signaling pathway is one of the most well-studied in plant defense. The bulk of SA-related defense gene expression and the subsequent establishment of systemic acquired resistance (SAR) is dependent on the nonexpressor of pathogenesis-related genes 1 (NPR1). Therefore, understanding the NPR1 pathway and all its associations has the potential to provide valuable insights into defense against pathogens. The causal agent of Phytophthora root rot (PRR), Phytophthora cinnamomi, is of particular importance to the avocado (Persea americana) industry, which encounters considerable economic losses on account of this pathogen each year. Furthermore, P. cinnamomi is a hemibiotrophic pathogen, suggesting that the SA-signaling pathway plays an essential role in the initial defense response. Therefore, the NPR1 pathway which regulates downstream SA-induced gene expression would be instrumental in defense against P. cinnamomi. Thus, we identified 92 NPR1 pathway-associated orthologs from the P. americana West Indian pure accession genome and interrogated their expression following P. cinnamomi inoculation, using RNA-sequencing data. In total, 64 and 51 NPR1 pathway-associated genes were temporally regulated in the partially resistant (Dusa®) and susceptible (R0.12) P. americana rootstocks, respectively. Furthermore, 42 NPR1 pathway-associated genes were differentially regulated when comparing Dusa® to R0.12. Although this study suggests that SAR was established successfully in both rootstocks, the evidence presented indicated that Dusa® suppressed SA-signaling more effectively following the induction of SAR. Additionally, contrary to Dusa®, data from R0.12 suggested a substantial lack of SA- and NPR1-related defense gene expression during some of the earliest time-points following P. cinnamomi inoculation. This study represents the most comprehensive investigation of the SA-induced, NPR1-dependent pathway in P. americana to date. Lastly, this work provides novel insights into the likely mechanisms governing P. cinnamomi resistance in P. americana. © 2023, The Author(s). | I40: Article | J40: BMC Plant Biology | K40: Importado | L40: scopus_export_Sep 18-2026_162c1d26-553e-41ee-8ea1-e9ecd3a7eea2.csv
A41: A0038 | B41: Scopus | C41: Unveiling the Predisposing Factors for the Development of Branch Canker and Dieback in Avocado: A Case of Study in Chilean Orchards | D41: Valencia A.L.; Saavedra-Torrico J.; Rosales I.M.; Mártiz J.; Retamales A.; Link A.; Gil P.M. | E41: 2022 | F41: 10.3390/horticulturae8121121 | G41: Botryosphaeriaceae; incidence; multivariate analysis; Persea americana; wood diseases | H41: Chilean avocado orchards have been affected by branch canker and dieback, mainly associated with pathogens species of the family Botryosphaeriaceae. Producers often relate water stress to these phenomena; however, predisposing factors for these diseases in Chilean orchards have not been reported. Therefore, the objective of this study was to identify the main climate, planting, and management variables associated with branch canker and dieback in Chilean avocado orchards. Multivariable statistical analyses (PCA and PLS-DA) were performed to analyze 76 variables possibly associated with the incidence of these diseases during two consecutive growing seasons. Our findings indicated that branch canker and dieback are mainly conditioned by orchard variables such as plant age, canopy volume, trunk diameter, leaf area index, and planting density. Variables associated with aged orchards, such as high age, high canopy volume, and high trunk diameter, appeared to be more associated with high incidence levels than were younger orchards with higher planting densities and high tree vigor levels. In addition, abiotic stresses, such as frost and overirrigation, were associated as secondary factors affecting these diseases’ development in avocado orchards. Moreover, this study allowed us to determine that branch canker and dieback can develop indistinctly in the different Chilean agroclimatic zones. © 2022 by the authors. | I41: Article | J41: Horticulturae | K41: Importado | L41: scopus_export_Sep 17-2026_64f2de15-f34e-4ffa-b356-5d490b5ac07b.csv | scopus_export_Sep 18-2026_96199bb3-e2ff-4aa3-a2d7-ec2db6aced85.csv
A42: A0039 | B42: Science Direct | C42: Anti-oomycete activity and plant growth promoting properties of avocado fungal endophytes | D42: Nieves-Campos, Emma I.; Méndez-Bravo, Alejandro; Pérez-Bautista, Yareli; Llanderal-Mendoza, Jesús; Guevara-Avendaño, Edgar; Solís-García, Itzel A.; Diyarza-Sandoval, Nayeli A.; Contreras-Ramos, Silvia M.; Rodriguez-Campos, Jacobo; Méndez-Bravo, Alfonso; Reverchon, Frédérique | E42: 2024 | F42: 10.1016/j.rhisph.2024.100931 | G42: Endophytic fungi; Indoles | H42: Fungal endophytes are known as promising plant growth-promoting microorganisms. Surprisingly, despite the economic importance of avocado, the antimicrobial and plant growth-promoting properties of its fungal endophytes have seldom been investigated. Our objectives were to evaluate the anti-oomycete activity of avocado fungal endophytes and assess their potential plant growth-promoting properties, using Arabidopsis thaliana as a model plant. In total, 89 fungal isolates were obtained from the roots of avocado trees and grouped into 24 morphotypes. One isolate per morphotype was randomly selected to assess its antagonistic activity against Phytophthora cinnamomi through dual culture assays. The strongest inhibition of P. cinnamomi was induced by endophytic fungi belonging to the Fusarium, Mortierella and Penicillium genera. The six most promising fungal isolates were selected to assess their plant growth-promoting traits in co-inoculation assays with A. thaliana. All tested fungal endophytes were able to modify the plant root architecture and increase the number of lateral roots. Moreover, an accumulation of auxins was detected in the xylem and meristematic zone of plants inoculated with Mortierella sp. PC-T3-3.1 and Metapochonia sp. PC-T2-4.2, whilst auxin accumulation was restricted to the emerging lateral roots of plants inoculated with Penicillium sp. C-T0-3.1. Indole quantification showed that Penicillium sp. C-T0-3.1 produced the highest concentration of indole acetic acid (IAA) and indole butyric acid (IBA), despite the lack of auxin responsiveness in plants in the co-inoculation assays. Mortierella sp. PC-T3-3.1 and Metapochonia sp. PC-T2-4.2 produced more IAA and IBA when co-inoculated with A. thaliana than when growing alone, which suggests that sensing of plant signals could induce the production of auxin-like compounds by these two endophytes. Collectively, our findings contribute to elucidate the mechanisms underpinning the plant growth-promoting activity of avocado fungal endophytes, which will be key to harness their full metabolic potential. | I42: Article | J42: Rhizosphere | K42: Importado | L42: S2452219824000867.ris
A43: A0040 | B43: Science Direct | C43: Avocado rhizobacteria emit volatile organic compounds with antifungal activity against Fusarium solani, Fusarium sp. associated with Kuroshio shot hole borer, and Colletotrichum gloeosporioides | D43: Guevara-Avendaño, Edgar; Bejarano-Bolívar, Alix Adriana; Kiel-Martínez, Ana-Luisa; Ramírez-Vázquez, Mónica; Méndez-Bravo, Alfonso; von Wobeser, Eneas Aguirre; Sánchez-Rangel, Diana; Guerrero-Analco, José A.; Eskalen, Akif; Reverchon, Frédérique | E43: 2019 | F43: 10.1016/j.micres.2018.11.009 | G43: Bacterial volatiles; spp.; Biological control; sp.; Rhizosphere | H43: Recent studies showed that bacterial volatile organic compounds (VOCs) play an important role in the suppression of phytopathogens. The ability of VOCs produced by avocado (Persea americana Mill.) rhizobacteria to suppress the growth of common avocado pathogens was therefore investigated. We evaluated the antifungal activity of VOCs emitted by avocado rhizobacteria in a first screening against Fusarium solani, and in subsequent antagonism assays against Fusarium sp. associated with Kuroshio shot hole borer, Colletotrichum gloeosporioides and Phytophthora cinnamomi, responsible for Fusarium dieback, anthracnosis and Phytophthora root rot in avocado, respectively. We also analyzed the composition of the bacterial volatile profiles by solid phase microextraction (SPME) gas chromatography coupled to mass spectrometry (GC–MS). Seven isolates, belonging to the bacterial genera Bacillus and Pseudomonas, reduced the mycelial growth of F. solani with inhibition percentages higher than 20%. Isolate HA, related to Bacillus amyloliquefaciens, significantly reduced the mycelial growth of Fusarium sp. and C. gloeosporioides and the mycelium density of P. cinnamomi. Isolates SO and SJJ, also members of the genus Bacillus, reduced Fusarium sp. mycelial growth and induced morphological alterations of fungal hyphae whilst isolate HB, close to B. mycoides, inhibited C. gloeosporioides. The analysis of the volatile profiles revealed the presence of ketones, pyrazines and sulfur-containing compounds, previously reported with antifungal activity. Altogether, our results support the potential of avocado rhizobacteria to act as biocontrol agents of avocado fungal pathogens and emphasize the importance of Bacillus spp. for the control of emerging avocado diseases such as Fusarium dieback. | I43: Article | J43: Microbiological Research | K43: Importado | L43: S0944501318310164.ris
A44: A0041 | B44: Science Direct | C44: Bioprospecting of microbial agents and their metabolites as potential inhibitors of Phytophthora cinnamomi, the causal agent of avocado root rot | D44: Ayyandurai, M.; Theradimani, M.; Harish, S.; Manonmani, K.; Madhu, G.S.; Yesu Raja, I.; Balakumbahan, R.; Kavitha Pushpam, A. | E44: 2024 | F44: 10.1016/j.pmpp.2024.102362 | G44: Avocado; SEM; GC-MS | H44: Phytophthora Root Rot (PRR) is one of the economically important diseases infecting avocado causing substantial yield losses worldwide. In this study, the root rot pathogen infecting avocado has been characterized and potential bioagents targeting PRR have been identified through molecular approaches. Field surveys revealed varying degrees of disease severity (54 %–17.5 %) and incidence (50 %–10 %) in Western Ghats of Tamil Nadu, India. The pathogen was isolated and identified as Phytophthora spp. based on morphology which depicted typical coralloid-type growth patterns. Besides, phylogenetic analysis with the ITS, ras-related protein and COX genes showed closed similarity with P. cinnamomi. The isolates showed significant variation in pathogenicity, with PC(TKI)-10 exhibiting the highest severity (70 %) developing typical symptoms. In vitro efficacy assays through dual-plate and volatiles revealed potential inhibitory effects of Trichoderma harzianum T (MP)-7 (81.11 %) and Bacillus amyloliquefaciens B (TI)-3 (76.67 %) against P. cinnamomi, and Scanning Electron Microscopy (SEM) provided insights into the antagonistic mechanisms, revealing physical interactions and enzymatic lysis of the pathogen by T (MP)-7 and B (TI)-3. Furthermore, Gas Chromatography-Mass Spectrometry (GC-MS) analysis identified bioactive compounds in the crude extracts of these bioagents, elucidating their metabolic pathways and potential modes of action against P. cinnamomi. Our findings highlights the importance of P. cinnamomi in avocado and the mechanism of fungal and bacterial bioagents in the sustainable management of the disease. | I44: Article | J44: Physiological and Molecular Plant Pathology | K44: Importado | L44: S0885576524001462.ris
A45: A0042 | B45: Science Direct | C45: Comparison of cross inoculation potential of South African avocado and mango isolates of Colletotrichum gloeosporioides | D45: Sanders, G.M.; Korsten, L. | E45: 2003 | F45: 10.1078/0944-5013-00186 | G45: avocado; mango; inoculation study | H45: Summary | I45: Article | J45: Microbiological Research | K45: Importado | L45: S0944501304701135.ris
A46: A0043 | B46: Science Direct | C46: Flooding and Phytophthora cinnamomi: Effects on photosynthesis and chlorophyll fluorescence in shoots of non-grafted Persea americana (Mill.) rootstocks differing in tolerance to Phytophthora root rot | D46: Reeksting, B.J.; Taylor, N.J.; van den Berg, N. | E46: 2014 | F46: 10.1016/j.sajb.2014.08.004 | G46: Avocado; Fluorescence; Gas exchange; Flooding | H46: Losses in the production of avocado (Persea americana (Mill.)) are incurred due to Phytophthora root rot (PRR), a disease of the feeder roots that results in tree-dieback and eventual tree death. Avocado is also a flood-sensitive species and flooding exacerbates the effects of PRR. The avocado industry relies on the use of rootstocks tolerant to PRR to minimise losses. The present study compared the gas exchange and chlorophyll fluorescence responses of avocado rootstock plants of ‘Dusa™’, the current South African industry standard, with ‘Duke 7’, and the selections R0.12 and R0.06 which show reduced and superior tolerance to PRR, respectively. A decline in stomatal conductance (gs) and net CO2 assimilation (PN) over the 30day evaluation period were early responses to flooding. ‘Dusa™’, the more tolerant rootstock plants, demonstrated a better recovery in PN and gs in response to inoculation; however, both rootstocks performed poorly under flooded conditions. A decline in PN in infected ‘Duke 7’ plants appeared to be associated with stomatal limitations due to reduced stomatal conductance. The decline in PN and gs was not apparent in infected ‘Dusa™’ plants. Non-stomatal limitations to PN in rootstock plants exposed to flooding were also evident as indicated by increases in the ratio of internal to atmospheric CO2 concentrations (Ci/Ca). Impaired photosynthetic capacity in flooded rootstock plants was reflected by reduced photosystem II efficiency and photochemical quenching. In comparison to ‘Dusa™’, R0.12 rootstock plants showed reduced PN and gs following inoculation with Phytophthora cinnamomi whereas the more tolerant R0.06 rootstock plants revealed sustained photosynthetic activity. Interestingly R0.06 was the only rootstock able to maintain PN and gs in non-inoculated, flooded plants. | I46: Article | J46: South African Journal of Botany | K46: Importado | L46: S0254629914001604.ris
A47: A0044 | B47: Science Direct | C47: Multigene phylogeny and diversity of Phytophthora and Phytopythium species associated with avocado root rot in India and development of a point-of-care LAMP assay for Phytophthora cinnamomi and Phytopythium vexans | D47: Madhu, G.S.; Rani, A.T.; Muralidhara, B.M.; Deepak, G. Nayan; Rajendiran, S.; Ayyandurai, M.; Venkataravanappa, V. | E47: 2025 | F47: 10.1016/j.pmpp.2025.102735 | G47: Avocado; LAMP; species | H47: Avocado root rot, predominantly caused by Phytophthora cinnamomi poses a major threat to avocado cultivation worldwide. However, the potential role of other Phytophthora and Phytophthora-like oomycete species in avocado decline remains largely unexplored. To address this knowledge gap, surveys were conducted across avocado orchards in the Western Ghats region of Karnataka, Kerala, and Tamil Nadu, India, to assess the diversity and pathogenicity of Phytophthora and Phytopythium species associated with root rot. Oomycete isolates were recovered from symptomatic root samples collected from 42 avocado orchards. Morphological characterization, coupled with multilocus sequence analysis targeting the internal transcribed spacer (ITS) region, cytochrome c oxidase subunit 1 (COX1), and β-tubulin (β-tub) genes, facilitated species identification. Furthermore, pathogenicity tests confirmed the virulence of the isolates. Among the surveyed orchards, Phytophthora species were isolated from 26 orchards, with P. cinnamomi being the most frequently detected, occurring in 22 orchards. Additionally, P. tropicalis was identified in 2 orchards, while P. nicotianae and P. kelmanii were each found in 1 orchard. In parallel, 9 Phytopythium isolates were recovered, with Phytopythium vexans detected in 7 orchards and Phytopythium chamaehyphon in 2 orchards. Among all isolates, P. cinnamomi exhibited the highest virulence, underscoring its primary role in avocado root rot. To facilitate early and accurate detection of the predominant pathogens, Phytophthora cinnamomi and Phytopythium vexans, in infected plants and nursery seedlings, a loop-mediated isothermal amplification (LAMP) assay was developed. The sensitivity of LAMP assay detection limits for P. cinnamomi was 25 pg, while for Pp. vexans was detected at 50 pg. This assay provides a rapid, highly sensitive, and reliable diagnostic tool, strengthening disease surveillance and management strategies for avocado cultivation in the region. This study highlighted the novel host record of P. Kelmanii and Pp. chamaehyphon in avocado root rot and Pp. vexans first report in India. | I47: Article | J47: Physiological and Molecular Plant Pathology | K47: Importado | L47: S0885576525001742.ris
A48: A0045 | B48: Science Direct | C48: Shifts in the structure of rhizosphere bacterial communities of avocado after Fusarium dieback | D48: Bejarano-Bolívar, Alix A.; Lamelas, Araceli; Aguirre von Wobeser, Eneas; Sánchez-Rangel, Diana; Méndez-Bravo, Alfonso; Eskalen, Akif; Reverchon, Frédérique | E48: 2021 | F48: 10.1016/j.rhisph.2021.100333 | G48: Biological control; Microbial diversity; Rhizosphere core microbiome | H48: The rhizosphere microbiome is critical for plant growth and protection against plant pathogens. However, rhizosphere microbial communities are likely to be restructured upon plant infection by fungal pathogens. Our objective was to determine the shifts in rhizosphere bacterial communities of avocado trees (Persea americana Mill.) after Fusarium dieback (FD), a disease triggered by the symbiotic fungi of invasive ambrosia beetles (Euwallacea kuroshio and Euwallacea sp. nr. fornicatus), using 16S rDNA gene amplicon sequencing and a culture-dependent approach. Rhizosphere soil samples were collected from five asymptomatic and five FD-symptomatic avocado trees in a Californian orchard. Sequence analysis showed that diversity metrics of the rhizosphere bacterial communities associated with asymptomatic avocado trees were larger than those of communities from FD-symptomatic trees. Moreover, FD produced significant shifts in rhizobacterial community structure, which were mainly caused by rare OTUs. Bacterial taxa such as Armatimonadetes, Sporocytophaga or Cellvibrio were exclusively associated with the rhizosphere of asymptomatic trees and may act as an insurance mechanism against fungal invasions. Conversely, genera such as Myxococcus or Lysobacter, which have been described as effective biocontrol agents against Fusarium oxysporum, Colletotrichum gloeosporioides or Rhizoctonia spp., among other phytopathogens, were only found in the rhizosphere of FD-symptomatic trees. The culturable bacterial communities in the rhizosphere of both FD-symptomatic and asymptomatic trees were dominated by isolates from the Bacillus and Pseudomonas genera, indicating that potential biocontrol agents against FD may be isolated from healthy and diseased avocado trees. Altogether, our results showed that FD elicited shifts in the avocado rhizosphere microbiome, which could potentially affect soil microbial processes, and provide a basis for the selection of biocontrol agents that could be used for FD prevention. | I48: Article | J48: Rhizosphere | K48: Importado | L48: S245221982100029X.ris
A49: A0046 | B49: Springer | C49: Branch canker battles: understanding and managing the Botryosphaeriaceae in avocado | D49: Möller, Heike; Slippers, Bernard; van den Berg, Noëlani | E49: 2025 | F49: 10.1007/s12600-024-01227-6 | H49: Avocado holds an important position in global agriculture and economic development. However, this thriving industry faces significant challenges from fungal pathogens, particularly those in the Botryosphaeriaceae. These fungi have emerged as major pathogens across various hosts, causing branch cankers, dieback, and fruit rots in avocados. These diseases reduce fruit quality and lead to substantial yield losses, threatening the profitability and sustainability of avocado production. This review consolidates current knowledge on Botryosphaeriaceae species affecting avocados, with a focus on their diversity, disease dynamics, detection methods, management strategies, and recent omics advances related to species reported in avocados. Given the escalating global production and economic importance of avocados, understanding, and effectively managing Botryosphaeriaceae infections is crucial. The review aims to identify research gaps and propose future research avenues to enhance disease management practices in avocado cultivation. | I49: Article | J49: Phytoparasitica | K49: Importado | L49: 10.1007_s12600-024-01227-6-citation.ris
A50: A0047 | B50: Springer | C50: Emerging pathogens and disease dynamics threatening avocado production in southern Türkiye | D50: Çalış, Özer; Çelik, Sefanur; Fidan, Hakan; Tek, Mumin Ibrahim; Shah, Mehraj; Tozlu, Ilhami; Wani, Shabir Hussain | E50: 2024 | F50: 10.1007/s41348-024-00954-6 | H50: Avocado (Persea americana Milll.) holds a pivotal position in global fruit crops, contributing significantly to the economies of tropical and subtropical regions. However, the rising incidence of diseases poses a substantial risk to avocado production. This comprehensive study investigated the disease landscape in Antalya, the largest avocado cultivation area in the Türkiye. A survey of 2537 avocado trees across 11 regions from 2020 to 2021 revealed alarming disease incidences, particularly in the eastern regions of Gazipasa and Alanya. Dieback, branch canker, anthracnose, and soil-borne root rot were identified as the primary diseases affecting tree canopies, twigs, and branches. Morphological and molecular analyzes unveiled a spectrum of pathogens, with Colletotrichum gloeosporioides dominating in the Mediterranean region. Notably, Phytophthora cinnamomi emerged as a severe threat, causing root rot and decline in avocado trees. Fusarium solani and Fusarium oxysporum, known for their association with tropical fruit crops, were identified in the western parts of Antalya. Additionally, we have detected Neofusicoccum parvum, Lasiodiplodia theobromae, and Neopestalotiopsis rosae in collected samples from avocado trees. The identified pathogens exhibited varying levels of severity in branch canker and anthracnose on avocado branches and leaves. Furthermore, pathogenicity evaluations shed light on the potential of these pathogens to induce severe symptoms, emphasizing the urgency for effective control measures. The exploration of cultural and biological control strategies are crucial for mitigating the impact of branch canker, dieback, and anthracnose diseases, ensuring the sustainability of avocado cultivation in the region. | I50: Article | J50: Journal of Plant Diseases and Protection | K50: Importado | L50: 10.1007_s41348-024-00954-6-citation.ris
A51: A0048 | B51: Springer | C51: Lasiodiplodia theobromae disease symptom development in young avocado (Persea americana L.) plants depends on the inoculation method | D51: Rodríguez-Gálvez, Edgar; Haro-Diaz, Cesar; Maza-Aguirre, Samir; Canahuire-Castillo, Fátima; Sullón-Saucedo, Julio; Deising, Holger B. | E51: 2025 | F51: 10.1007/s40858-025-00700-9 | H51: Lasiodiplodia theobromae is a pathogenic fungus of more than 500 plant species, including avocado (Persea americana Mill.). The global production volume of avocado exceeded 911,000 metric tons in 2023. Although detailed quantitative surveys of yield losses caused by L. theobromae are not available for most avocado-producing regions, estimates indicate that this pathogen is associated with stem-end rot disease in 30-35% of plots located in the Department of Antioquia in Colombia (Ramírez-Gil et al. Heliyon 7: e05905, 2021), suggesting an enormous economic impact. As yield losses strongly depend on the virulence of isolates, a reliable method for determining their aggressiveness is indispensable for initiating disease control measures. In this study, we compared progression of external and internal necrosis caused by the aggressive L. theobromae isolate LA-VLCA3 inoculated into wounded middle parts of the stem and onto excised apices. Irrespective of the inoculation method, internal progression of necrosis preceded that of external necrosis. Spreading of external and internal necrosis was significantly more severe in plants inoculated at the apex than in mid-stem inoculated plants. We conclude that apex inoculation causes stronger symptoms and is therefore better suited to compare virulence of isolates than mid-stem inoculation. | I51: Article | J51: Tropical Plant Pathology | K51: Importado | L51: 10.1007_s40858-025-00700-9-citation.ris
A53: Registros por base de datos | B53: Conteo
A54: Scopus | B54: =COUNTIF($B$4:$B$51,"Scopus") -> 38
A55: IEEE Xplore | B55: =COUNTIF($B$4:$B$51,"IEEE Xplore") -> 0
A56: Web of Science | B56: =COUNTIF($B$4:$B$51,"Web of Science") -> 0
A57: Springer | B57: =COUNTIF($B$4:$B$51,"Springer") -> 3
A58: Science Direct | B58: =COUNTIF($B$4:$B$51,"Science Direct") -> 7
A59: Total | B59: =SUM(B54:B58) -> 48

Sheet Duplicados_y_exclusion
A1: Duplicados_y_exclusion
A2: Primer filtro: marca y descarta duplicados (mismo DOI/título) y exclusiones (revisiones/surveys). Conserva un único registro por estudio. Cada descarte lleva su motivo.
A3: ID original | B3: Base de datos | C3: Título completo | D3: DOI | E3: Tipo de exclusión | F3: Motivo de exclusión | G3: Duplicado | H3: Tipo de estudio detectado | I3: Decisión

Sheet Tamizaje_Tit_Abs_Keys
A1: Tamizaje_Titulo_Abstract_Keywords
A2: Cribado por título, abstract y keywords. Registra la evidencia de cada eje y decide si el registro pasa a evaluación de calidad.
A3: ID | B3: Base de datos | C3: Título completo | D3: Keywords principales | E3: Resumen técnico del abstract | F3: Evidencia de Inteligencia Artificial | G3: Evidencia de HCI / UX / UCD / usability | H3: Evidencia de aplicación móvil | I3: Evidencia de design / framework / methodology / approach | J3: Evidencia de agricultura / farming / smart agriculture | K3: Tipo de estudio (Primario / Revisión / Otro) | L3: Nivel de alineación con el objetivo | M3: Motivo de clasificación | N3: ¿Pasa a evaluación de calidad?

Sheet Calidad_articulos
A1: Calidad_articulos
A2: Evaluación de calidad de lo que pasó el tamizaje. Q1-Q10 se puntúan 0/1/2; el puntaje total (0-20) y el nivel de calidad se CALCULAN SOLOS.
A3: ID | B3: Base de datos | C3: Título completo | D3: Q1 | E3: Q2 | F3: Q3 | G3: Q4 | H3: Q5 | I3: Q6 | J3: Q7 | K3: Q8 | L3: Q9 | M3: Q10 | N3: Puntaje total | O3: Nivel de calidad | P3: Observaciones de calidad
N4: =IF(COUNT(D4:M4)=0,"",SUM(D4:M4)) | O4: =IF(N4="","",IF(N4>=16,"Alta calidad",IF(N4>=11,"Media calidad","Baja calidad")))
N5: =IF(COUNT(D5:M5)=0,"",SUM(D5:M5)) | O5: =IF(N5="","",IF(N5>=16,"Alta calidad",IF(N5>=11,"Media calidad","Baja calidad")))
N6: =IF(COUNT(D6:M6)=0,"",SUM(D6:M6)) | O6: =IF(N6="","",IF(N6>=16,"Alta calidad",IF(N6>=11,"Media calidad","Baja calidad")))
N7: =IF(COUNT(D7:M7)=0,"",SUM(D7:M7)) | O7: =IF(N7="","",IF(N7>=16,"Alta calidad",IF(N7>=11,"Media calidad","Baja calidad")))
N8: =IF(COUNT(D8:M8)=0,"",SUM(D8:M8)) | O8: =IF(N8="","",IF(N8>=16,"Alta calidad",IF(N8>=11,"Media calidad","Baja calidad")))
N9: =IF(COUNT(D9:M9)=0,"",SUM(D9:M9)) | O9: =IF(N9="","",IF(N9>=16,"Alta calidad",IF(N9>=11,"Media calidad","Baja calidad")))
N10: =IF(COUNT(D10:M10)=0,"",SUM(D10:M10)) | O10: =IF(N10="","",IF(N10>=16,"Alta calidad",IF(N10>=11,"Media calidad","Baja calidad")))
N11: =IF(COUNT(D11:M11)=0,"",SUM(D11:M11)) | O11: =IF(N11="","",IF(N11>=16,"Alta calidad",IF(N11>=11,"Media calidad","Baja calidad")))
N12: =IF(COUNT(D12:M12)=0,"",SUM(D12:M12)) | O12: =IF(N12="","",IF(N12>=16,"Alta calidad",IF(N12>=11,"Media calidad","Baja calidad")))
N13: =IF(COUNT(D13:M13)=0,"",SUM(D13:M13)) | O13: =IF(N13="","",IF(N13>=16,"Alta calidad",IF(N13>=11,"Media calidad","Baja calidad")))
N14: =IF(COUNT(D14:M14)=0,"",SUM(D14:M14)) | O14: =IF(N14="","",IF(N14>=16,"Alta calidad",IF(N14>=11,"Media calidad","Baja calidad")))
N15: =IF(COUNT(D15:M15)=0,"",SUM(D15:M15)) | O15: =IF(N15="","",IF(N15>=16,"Alta calidad",IF(N15>=11,"Media calidad","Baja calidad")))
... N303: =IF(COUNT(D303:M303)=0,"",SUM(D303:M303)) | O303: =IF(N303="","",IF(N303>=16,"Alta calidad",IF(N303>=11,"Media calidad","Baja calidad")))

Sheet Articulos_finales
A1: Articulos_finales
A2: Selección final razonada: analiza el aporte de cada artículo y decide Incluir o Reserva, con su justificación.
A3: ID | B3: Base de datos | C3: Título completo | D3: Año | E3: Autores | F3: DOI | G3: Tipo de estudio | H3: Aporte principal | I3: Relación con Objetivo 1 | J3: Evidencia de IA | K3: Evidencia de HCI/UX | L3: Evidencia de mobile app | M3: Evidencia de design/framework/methodology/approach | N3: Evidencia de agricultura | O3: Nivel de alineación con el objetivo | P3: Nivel de calidad | Q3: Decisión final (Incluir / Reserva) | R3: Justificación final

Sheet Articulos_finales_ok
A1: Autor | B1: Estudio | C1: Técnica IA | D1: Método HCI | E1: Plataforma móvil | F1: Evaluación UX

Sheet Resumen_ejecutivo
A1: Resumen_ejecutivo
A3: Métrica | B3: Valor | C3: Definición | E3: Base de datos | F3: Seleccionados | G3: Incluir | H3: Reserva | J3: Duplicados y revisiones
A4: Número total de artículos analizados | B4: =COUNTA(Base_consolidada!A:A)-3 -> 55 | C4: Total consolidado de registros importados. | E4: Scopus | F4: =COUNTIF(Articulos_finales!B:B,"Scopus") -> 0 | G4: =COUNTIFS(Articulos_finales!B:B,"Scopus",Articulos_finales!Q:Q,"Incluir") -> 0 | H4: =COUNTIFS(Articulos_finales!B:B,"Scopus",Articulos_finales!Q:Q,"Reserva") -> 0 | J4: =B5+B6 -> 0
A5: Número de duplicados encontrados | B5: =COUNTIF(Duplicados_y_exclusion!G:G,"Sí") -> 0 | C5: Registros repetidos respecto al estudio preferente. | E5: IEEE Xplore | F5: =COUNTIF(Articulos_finales!B:B,"IEEE Xplore") -> 0 | G5: =COUNTIFS(Articulos_finales!B:B,"IEEE Xplore",Articulos_finales!Q:Q,"Incluir") -> 0 | H5: =COUNTIFS(Articulos_finales!B:B,"IEEE Xplore",Articulos_finales!Q:Q,"Reserva") -> 0
A6: Número de revisiones/surveys/mapping/meta-análisis excluidos | B6: =COUNTIF(Duplicados_y_exclusion!E:E,"Revisión sistemática")+COUNTIF(Duplicados_y_exclusion!E:E,"Literature review")+COUNTIF(Duplicados_y_exclusion!E:E,"Survey")+COUNTIF(Duplicados_y_exclusion!E:E,"Mapping study")+COUNTIF(Duplicados_y_exclusion!E:E,"Meta-análisis") -> 0 | C6: Exclusiones por ser estudios de revisión. | E6: Web of Science | F6: =COUNTIF(Articulos_finales!B:B,"Web of Science") -> 0 | G6: =COUNTIFS(Articulos_finales!B:B,"Web of Science",Articulos_finales!Q:Q,"Incluir") -> 0 | H6: =COUNTIFS(Articulos_finales!B:B,"Web of Science",Articulos_finales!Q:Q,"Reserva") -> 0
A7: Número de estudios primarios detectados | B7: =COUNTIF(Duplicados_y_exclusion!H:H,"Primario") -> 0 | C7: Detección automática por título/abstract/keywords disponibles. | E7: Springer | F7: =COUNTIF(Articulos_finales!B:B,"Springer") -> 0 | G7: =COUNTIFS(Articulos_finales!B:B,"Springer",Articulos_finales!Q:Q,"Incluir") -> 0 | H7: =COUNTIFS(Articulos_finales!B:B,"Springer",Articulos_finales!Q:Q,"Reserva") -> 0
A8: Número de artículos que pasaron el tamizaje | B8: =COUNTIF(Tamizaje_Tit_Abs_Keys!N:N,"Sí") -> 0 | C8: Registros mantenidos con alineación media o alta. | E8: Science Direct | F8: =COUNTIF(Articulos_finales!B:B,"Science Direct") -> 0 | G8: =COUNTIFS(Articulos_finales!B:B,"Science Direct",Articulos_finales!Q:Q,"Incluir") -> 0 | H8: =COUNTIFS(Articulos_finales!B:B,"Science Direct",Articulos_finales!Q:Q,"Reserva") -> 0
A9: Número de artículos de alta calidad | B9: =COUNTIF(Calidad_articulos!O:O,"Alta calidad") -> 0 | C9: Artículos con 16 a 20 puntos.
A10: Número final de artículos seleccionados | B10: =COUNTA(Articulos_finales!A:A)-3 -> 0 | C10: Artículos incluidos o en reserva en la selección final.
A12: Principales patrones encontrados
A13: (Completa al final: principales patrones que encontraste en los artículos.)
A15: Principales técnicas de IA identificadas
A16: (Completa: principales grupos/patógenos y métodos de detección identificados.)
A18: Principales enfoques de HCI/UX identificados
A19: (Completa: principales síntomas/enfermedades del tallo identificados.)
A21: Vacíos detectados en la literatura
A22: (Completa: vacíos que detectaste en la literatura.)
A24: Recomendación final
A25: (Completa: tu recomendación final.)
