Workbook

Sheet Guia_avance
A1: Guía de avance de la matriz v5 – se completa en orden según el itinerario
A3: Hoja | B3: Actividad del itinerario | C3: Qué se registra | D3: Estado
A4: Protocolo | B4: 1. Inducción | C4: Resumen del protocolo v3 (objetivo, RQ, criterios, calidad). | D4: Completada (validada el 01/10/2026)
A5: Cadenas_de_busqueda | B5: 3. Búsqueda y organización | C5: Las 16 cadenas ejecutadas, con fecha y registros exportados. | D5: Completada (validada el 01/10/2026)
A6: Base_consolidada | B6: 3. Búsqueda y organización | C6: Todos los registros exportados, con ID y categoría. | D6: Completada (validada el 01/10/2026)
A7: Duplicados_y_exclusion | B7: 4. PRISMA | C7: Duplicados y estudios secundarios retirados antes del cribado. | D7: Completada (validada el 02/10/2026)
A8: Tamizaje_Tit_Abs_Keys | B8: 4. PRISMA | C8: Cribado por título, resumen y palabras clave. | D8: Completada (validada el 02/10/2026)
A9: Texto_completo | B9: 4. PRISMA | C9: Elegibilidad a texto completo y motivos de exclusión. | D9: Completada (validada el 02/10/2026)
A10: Calidad_articulos | B10: 5. Calidad | C10: Q1–Q10 de los estudios elegibles. | D10: Completada (validada el 02/10/2026)
A11: Articulos_finales | B11: 6. Extracción y análisis | C11: Extracción de datos y decisión final (Incluir/Reserva). | D11: Completada (validada el 02/10/2026)
A12: Articulos_finales_ok | B12: 6. Extracción y análisis | C12: Tablas de síntesis. | D12: Completada (validada el 02/10/2026)
A13: Resumen_ejecutivo | B13: 6. Extracción y análisis | C13: Patrones, vacíos y recomendación. | D13: Completada (validada el 02/10/2026)
A14: PRISMA | B14: 7. Diagrama PRISMA | C14: Conteos del diagrama de flujo (automáticos) y comprobaciones; figura en 04_PRISMA/PRISMA_2020_diagrama_v2.png. | D14: Completada (validada el 02/10/2026)
... A17: Nota | B17: 8. Redacción de la SLR | C17: La Actividad 8 no tiene hoja en esta matriz: su entregable es SLR_SmartAgriculture/05_Redaccion_SLR/SLR_tallos_aguacate_v1.docx (tablas generadas desde esta matriz). | D17: Entregada el 02/10/2026 (pendiente de validación)

Sheet Protocolo
A1: PROTOCOLO DE LA REVISIÓN SISTEMÁTICA – resumen del Protocolo_SLR_SmartAgriculture_v3.docx (Actividad 1)
A2: Una sola revisión sistemática y un solo diagrama PRISMA, con dos categorías de estudios evaluadas con sus propios criterios. Solo se usan fuentes de Grupos v2.
A3: 1. Tema / Proyecto | B3: Smart Agriculture: aplicación móvil con IA para diagnosticar enfermedades y alteraciones visibles en el TALLO del aguacate.
A4: 2. Objetivo | B4: Analizar y sintetizar la literatura sobre las enfermedades del tallo del aguacate (agentes, síntomas visibles, métodos de detección) y sobre los sistemas de IA para el diagnóstico de enfermedades en cultivos (técnicas, datos, métricas, implementación e IPO), para fundamentar una aplicación móvil de diagnóstico en tallos.
A5: 3. Pregunta principal | B5: ¿Qué evidencia científica existe sobre las enfermedades y alteraciones del tallo del aguacate y sobre los sistemas basados en IA para el diagnóstico de enfermedades en cultivos, que permita fundamentar el desarrollo de una aplicación móvil para el diagnóstico en tallos de aguacate?
A6: RQ1 | B6: ¿Qué agentes causales y enfermedades afectan al tallo, las ramas y el tronco del aguacate, y en qué regiones se han reportado?
A7: RQ2 | B7: ¿Qué síntomas visibles producen estas enfermedades y qué métodos se utilizan para su detección y diagnóstico?
A8: RQ3 | B8: ¿Qué técnicas de IA y visión por computador, conjuntos de datos y métricas se emplean en los sistemas de diagnóstico de enfermedades en cultivos?
A9: RQ4 | B9: ¿Qué características de implementación (plataforma, inferencia, funcionamiento sin conexión) y de IPO presentan estos sistemas?
A10: RQ5 | B10: ¿Qué brechas y oportunidades se identifican para desarrollar una aplicación móvil de diagnóstico de enfermedades en tallos de aguacate?
A11: 4. Bases de datos | B11: Scopus, ScienceDirect y Springer Link. IEEE Xplore y Web of Science no se consultaron por falta de acceso institucional (limitación).
A12: 5. Grupos de cadenas | B12: Fitopatológicas (17–18/09/2026; 2003–2026) · Tecnológicas (25/09/2026; 2015–2026) · Complementarias C16–C18 en ScienceDirect (01/10/2026): recuperan revisiones que no entran a la síntesis y sirven de fuente para los antecedentes y el estado del arte.
A13: 6. Idioma | B13: Español o inglés.
A14: 7. Método | B14: Directrices de Kitchenham y Charters (como se citó en Martinelli et al., 2024) y declaración PRISMA (aplicada en Lin et al., 2026; Majdalawieh et al., 2025; Odounfa et al., 2024; Sajitha et al., 2024). Un revisor principal, con la tutora como segunda instancia.
A15: CATEGORÍA FITOPATOLÓGICA
A16: CI-F1 | B16: Trata sobre aguacate (Persea americana).
A17: CI-F2 | B17: Menciona uno de los grupos de patógenos considerados (Phytophthora, Lasiodiplodia, Botryosphaeriaceae, Colletotrichum, Fusarium, Nectria/Rugonectria).
A18: CI-F3 | B18: Aporta información sobre el tallo, ramas o tronco (síntomas, cancro, muerte descendente, pudrición, marchitez, detección).
A19: CI-F4 | B19: Es un estudio primario, en español o inglés, publicado entre 2003 y 2026.
A20: CE-F1 | B20: Se enfoca únicamente en raíz, hoja o fruto, sin relación con el tallo (incluye la pudrición peduncular o “stem-end rot” del fruto).
A21: CE-F2 | B21: Es revisión, survey, mapping o metaanálisis.
A22: CE-F3 | B22: No especifica la especie del patógeno ni el órgano afectado.
A23: CE-F4 / CE-F5 | B23: Duplicado; fuera del periodo o del idioma.
A24: Q1–Q10 fitopatológicos | B24: Q1 objetivo claro · Q2 patógeno identificado · Q3 síntomas en tallo descritos · Q4 aguacate · Q5 metodología replicable · Q6 evidencia (imágenes, mediciones, secuencias) · Q7 métodos de detección útiles para la app · Q8 contexto geográfico · Q9 resultados coherentes · Q10 fuente confiable y actual.
A25: CATEGORÍA TECNOLÓGICA
A26: CI-T1 | B26: Aborda la detección, clasificación o diagnóstico de enfermedades de plantas o cultivos.
A27: CI-T2 | B27: Usa IA, machine learning, deep learning o visión por computador.
A28: CI-T3 | B28: Se relaciona con una aplicación móvil, dispositivo o sistema de apoyo (o analiza su viabilidad).
A29: CI-T4 | B29: Es un estudio primario, en español o inglés, publicado entre 2015 y 2026.
A30: CE-T1 | B30: No usa IA ni métodos de aprendizaje automático.
A31: CE-T2 | B31: No aborda enfermedades de plantas (p. ej., madurez, calidad del fruto, estrés hídrico).
A32: CE-T3 / CE-T4 | B32: Revisión o estudio secundario; duplicado o fuera del periodo o idioma.
A33: Q1–Q10 tecnológicos | B33: Q1 objetivo claro · Q2 problema de detección definido · Q3 dataset especificado · Q4 modelo replicable · Q5 métricas con validación adecuada · Q6 comparación con otros modelos · Q7 implementación en app o dispositivo · Q8 IPO/UX/usabilidad · Q9 resultados coherentes y reproducibles · Q10 fuente confiable y actual.
A34: PUNTUACIÓN Y DECISIÓN
A35: Escala | B35: 0 = no cumple · 1 = parcial · 2 = cumple. Total 0–20 → Alta 16–20 · Media 11–15 · Baja ≤ 10.
A36: Decisión final | B36: Incluir si la calidad es Alta o Media y la alineación con el objetivo es Alta o Media; en otro caso, Reserva (se cita, pero no entra en la síntesis).
A37: Datos a extraer | B37: Fitopatológicos: patógeno, especie, órgano, síntomas en tallo, método de detección, país, aporte. Tecnológicos: modelo, dataset, métrica, plataforma e inferencia, IPO/usabilidad, país, aporte.

Sheet Cadenas_de_busqueda
A1: CADENAS DE BÚSQUEDA (registro para reproducibilidad)
A2: Se completa en la Actividad 3 del itinerario. Registro de las cadenas EXACTAS ejecutadas, con fecha y n.º de registros exportados (bitácora de búsqueda). IEEE Xplore y Web of Science no se consultaron por falta de acceso institucional.
A4: N.º | B4: Grupo | C4: Base de datos | D4: Cadena de búsqueda exacta | E4: Campos | F4: Filtros (años/idioma) | G4: Fecha de búsqueda | H4: N.º registros exportados | I4: Notas
A5: CADENAS FITOPATOLÓGICAS (17 y 18/09/2026)
A6: 1 | B6: Fitopatológica – todos los grupos de patógenos | C6: Scopus | D6: ("Persea americana" OR avocado) AND ("Phytophthora cinnamomi" OR "Lasiodiplodia theobromae" OR "Neofusicoccum parvum" OR Botryosphaeriaceae OR Colletotrichum OR Fusarium OR Nectria OR Rugonectria) AND (stem OR trunk OR canker OR dieback OR "stem-end rot" OR wilt OR disease OR symptom) | E6: Título-Resumen-Keywords | F6: 2003–2026; es/en | G6: 2026-09-17 | H6: 19 | I6: Export: scopus_export_Sep 17-2026_64f2de15. Cadena general, todos los grupos. Total de resultados (hits) no registrado (limitación declarada).
A7: 2 | B7: Fitopatológica – todos los grupos de patógenos | C7: Science Direct | D7: ("Persea americana" OR avocado) AND ("Phytophthora" OR Botryosphaeriaceae OR Colletotrichum OR Fusarium OR Nectria OR Rugonectria) | E7: Título-Resumen-Keywords | F7: 2003–2026; es/en | G7: 2026-09-18 | H7: 7 | I7: 7 registros (A0039–A0045), .ris en Grupos v2/Todos/Science Direct. Total de resultados (hits) no registrado (limitación declarada).
A8: 3 | B8: Fitopatológica – todos los grupos de patógenos | C8: Springer Link | D8: ("Persea americana" OR avocado) AND ("Phytophthora cinnamomi" OR "Lasiodiplodia theobromae" OR "Neofusicoccum parvum" OR Botryosphaeriaceae OR Colletotrichum OR Fusarium OR Nectria OR Rugonectria) AND (stem OR trunk OR canker OR dieback OR "stem-end rot" OR wilt OR disease OR symptom) | E8: Título-Resumen-Keywords | F8: 2003–2026; es/en | G8: 2026-09-17 | H8: 3 | I8: 3 registros (A0046–A0048), .ris en Grupos v2/Todos/springer. Total de resultados (hits) no registrado (limitación declarada).
A9: 4 | B9: Fitopatológica – 1. Phytophthora | C9: Scopus | D9: ("Persea americana" OR avocado) AND "Phytophthora cinnamomi" AND (root OR stem OR trunk OR wilt OR dieback) | E9: Título-Resumen-Keywords | F9: 2003–2026; es/en | G9: 2026-09-18 | H9: 7 | I9: Export: scopus_export_Sep 18-2026_162c1d26. Total de resultados (hits) no registrado (limitación declarada).
A10: 5 | B10: Fitopatológica – 2. Lasiodiplodia | C10: Scopus | D10: ("Persea americana" OR avocado) AND "Lasiodiplodia theobromae" AND (stem OR trunk OR canker OR "stem-end rot") | E10: Título-Resumen-Keywords | F10: 2003–2026; es/en | G10: 2026-09-18 | H10: 4 | I10: Export: scopus_export_Sep 18-2026_8f28b456. Total de resultados (hits) no registrado (limitación declarada).
A11: 6 | B11: Fitopatológica – 3. Botryosphaeriaceae | C11: Scopus | D11: ("Persea americana" OR avocado) AND ("Neofusicoccum parvum" OR Botryosphaeriaceae) AND (stem OR trunk OR canker OR dieback) | E11: Título-Resumen-Keywords | F11: 2003–2026; es/en | G11: 2026-09-18 | H11: 6 | I11: Export: scopus_export_Sep 18-2026_96199bb3. Total de resultados (hits) no registrado (limitación declarada).
A12: 7 | B12: Fitopatológica – 4. Colletotrichum | C12: Scopus | D12: ("Persea americana" OR avocado) AND ("Colletotrichum acutatum" OR "Colletotrichum gloeosporioides") AND (anthracnose OR stem OR canker) | E12: Título-Resumen-Keywords | F12: 2003–2026; es/en | G12: 2026-09-17 / 2026-09-18 | H12: 4 | I12: Dos exports: Sep 17-2026_2fb2f4b0 (1) + Sep 18-2026_82c23d75 (3). Total de resultados (hits) no registrado (limitación declarada).
A13: 8 | B13: Fitopatológica – 5. Fusarium | C13: Scopus | D13: ("Persea americana" OR avocado) AND ("Fusarium solani" OR "Fusarium oxysporum" OR "Fusarium equiseti") AND (wilt OR stem OR trunk OR rot) | E13: Título-Resumen-Keywords | F13: 2003–2026; es/en | G13: 2026-09-18 | H13: 2 | I13: Export: scopus_export_Sep 18-2026_4e658477. Total de resultados (hits) no registrado (limitación declarada).
A14: 9 | B14: Fitopatológica – 6. Nectria | C14: Scopus | D14: ("Persea americana" OR avocado) AND (Nectria OR "Rugonectria rugulosa") AND (canker OR trunk OR stem) | E14: Título-Resumen-Keywords | F14: 2003–2026; es/en | G14: 2026-09-18 | H14: 4 | I14: Export: scopus_export_Sep 18-2026_6573fc91. Total de resultados (hits) no registrado (limitación declarada).
A15: CADENAS TECNOLÓGICAS (25/09/2026)
A16: 12 | B16: Tecnológica – Aguacate+IA (stem) | C16: Scopus | D16: ( "Persea americana" OR avocado ) AND ( "deep learning" OR "machine learning" OR "computer vision" OR CNN OR "image classification" ) AND ( stem OR detection OR classification ) | E16: Título-Resumen-Keywords | F16: 2015–2026; es/en | G16: 2026-09-25 | H16: 13 | I16: Exportación conjunta de las cadenas 12–14: 13 registros; 1 duplicado dentro de Scopus (T0001, presente en dos exportaciones) → 12 únicos (T0001–T0012). Total de resultados (hits) no registrado (limitación declarada).
A17: 13 | B17: Tecnológica – Enfermedad+IA+HCI | C17: Scopus | D17: ( "plant disease" OR "crop disease" OR "leaf disease" ) AND ( "deep learning" OR "machine learning" OR "computer vision" OR "artificial intelligence" ) AND ( usability OR "user experience" OR UX OR "human-computer interaction" OR HCI OR "user interface" OR "user-centered design" ) | E17: Título-Resumen-Keywords | F17: 2015–2026; es/en | G17: 2026-09-25 | H17: 0 | I17: Sus registros se contabilizan en la cadena 12 (exportación conjunta). Total de resultados (hits) no registrado (limitación declarada).
A18: 14 | B18: Tecnológica – Aguacate+IA (disease/pest) | C18: Scopus | D18: (avocado OR "Persea americana") AND ("deep learning" OR "machine learning" OR "computer vision" OR CNN OR "image classification" OR "artificial intelligence") AND (disease OR detection OR classification OR pest) | E18: Título-Resumen-Keywords | F18: 2015–2026; es/en | G18: 2026-09-25 | H18: 0 | I18: Sus registros se contabilizan en la cadena 12 (exportación conjunta). Total de resultados (hits) no registrado (limitación declarada).
A19: 15 | B19: Tecnológica – Aguacate+IA+HCI | C19: Springer Link | D19: ("persea americana" OR avocado) AND ("deep learning" OR "machine learning" OR "computer vision") AND (usability OR "user experience" OR "human-computer interaction" OR "user interface") | E19: Título-Resumen-Keywords | F19: 2015–2026; es/en | G19: 2026-09-25 | H19: 1 | I19: 1 registro exportado (T0013); .ris en Grupos v2/Todos/springer. Total de resultados (hits) no registrado (limitación declarada).
A20: CADENAS COMPLEMENTARIAS EN SCIENCEDIRECT (01/10/2026) – revisiones para el estado del arte
A21: 16 | B21: Complementaria – Smart agriculture + IA | C21: Science Direct | D21: ("smart agriculture" OR "smart farming" OR "precision agriculture") AND ("deep learning" OR "computer vision") AND review | E21: Título-Resumen-Keywords | F21: No registrado (registros de 2024–2026, en inglés) | G21: 2026-10-01 | H21: 4 | I21: ScienceDirect_citations_1790890165413.ris: Odounfa 2024 (T0014), Yuan 2026 (T0015), Lin 2026 (T0016), Majdalawieh 2025 (T0017). Total de resultados (hits) no registrado (limitación declarada).
A22: 17 | B22: Complementaria – Detección de enfermedades en plantas con imágenes | C22: Science Direct | D22: ("plant disease" OR "crop disease") AND ("deep learning" OR CNN) AND (detection OR classification) | E22: Título-Resumen-Keywords | F22: No registrado (registros de 2024–2026, en inglés) | G22: 2026-10-01 | H22: 3 | I22: ScienceDirect_citations_1790890637540.ris: Saini 2026 (T0018), Sajitha 2024 (T0019) y Majdalawieh 2025, ya recuperado en la cadena 16 (1 duplicado dentro de ScienceDirect). Total de resultados (hits) no registrado (limitación declarada).
A23: 18 | B23: Complementaria – Apps móviles + HCI en agricultura | C23: Science Direct | D23: ("mobile application" OR smartphone) AND (agriculture OR farmer*) AND (usability OR "user-centered design" OR "user experience") | E23: Título-Resumen-Keywords | F23: No registrado (registro de 2024, en inglés) | G23: 2026-10-01 | H23: 1 | I23: ScienceDirect_citations_1790891064720.ris: Martinelli 2024 (T0020). Total de resultados (hits) no registrado (limitación declarada).
A25: RESUMEN DE LA BÚSQUEDA
B26: Registros exportados – Scopus | H26: =SUMIF($C$5:$C$23,"Scopus",$H$5:$H$23) -> 59
B27: Registros exportados – ScienceDirect | H27: =SUMIF($C$5:$C$23,"Science Direct",$H$5:$H$23) -> 15
B28: Registros exportados – Springer Link | H28: =SUMIF($C$5:$C$23,"Springer Link",$H$5:$H$23) -> 4
B29: Total de registros exportados | H29: =SUM(H26,H27,H28) -> 78
B30: Duplicados dentro de la misma base (8 Scopus fitopatológicos, 1 Scopus tecnológico, 1 ScienceDirect) | H30: 10
B31: Registros únicos por base (hoja Base_consolidada) | H31: =COUNTA(Base_consolidada!$A$4:$A$200) -> 68
B32: Comprobación: exportados − duplicados internos = únicos | H32: =IF(H29-H30=H31,"Correcto","Revisar") -> Correcto
A34: Nota metodológica: | B34: Se conservan los números originales de las cadenas (1–9, 12–15 y 16–18); los números 10 y 11 no se usaron, por lo que son 16 cadenas en total. Los totales de resultados (hits) no se registraron al buscar, por lo que el PRISMA parte de los registros exportados (limitación declarada). IEEE Xplore y Web of Science no se consultaron por falta de acceso institucional. Las cadenas 16–18 son más cortas porque ScienceDirect limita a ocho los operadores booleanos por campo (Yuan et al., 2026); los filtros de año e idioma de estas cadenas no se registraron.

Sheet Base_consolidada
A1: Base_consolidada
A2: Actividad 3 del itinerario. Registros únicos por base (78 exportados − 10 duplicados dentro de la misma base = 68), con su ID y categoría. Aún no se filtra nada: los duplicados entre bases y las revisiones se marcan en la Actividad 4 (hoja Duplicados_y_exclusion). Datos tomados de las exportaciones de Scopus (.csv), ScienceDirect y Springer Link (.ris).
A3: ID | B3: Base de datos | C3: Título completo | D3: Autores | E3: Año | F3: DOI | G3: Keywords | H3: Abstract | I3: Tipo de documento | J3: Fuente / Revista | K3: Estado inicial | L3: Registro fuente | M3: Categoría | O3: RESUMEN DE LA BASE CONSOLIDADA
A4: A0001 | B4: Scopus | C4: Avocado rhizobacteria emit volatile organic compounds with antifungal activity against Fusarium solani, Fusarium sp. associated with Kuroshio shot hole borer, and Colletotrichum gloeosporioides | D4: Guevara-Avendaño E.; Bejarano-Bolívar A.A.; Kiel-Martínez A.-L.; Ramírez-Vázquez M.; Méndez-Bravo A.; von Wobeser E.A.; Sánchez-Rangel D.; Guerrero-Analco J.A.; Eskalen A.; Reverchon F. | E4: 2019 | F4: 10.1016/j.micres.2018.11.009 | G4: Bacillus spp.; Bacterial volatiles; Biological control; Persea americana; Pseudomonas sp.; Rhizosphere; Animals; Antifungal Agents; Bacillus; Biological Control Agents; Coleoptera; Colletotrichum; Fusarium; Persea; Phytophthora; Pseudomonas; Volatile Organic Compounds; Bacillus (bacterium); Bacillus amyloliquefaciens; Bacillus mycoides; Bacteria (microorganisms); Fusarium; Fusarium solani; Fusarium sp.; Glomerella cingulata; Mycelium (genus); Persea americana; Phytophthora; Phytophthora cinnamomi; Pseudomonas; Pseudomonas sp.; Rhizobiales; Bacteria; Bacteriology; Diagnosis; Disease control; Fruits; Gas chromatography; Ketones; Mass spectrometry; Ocean currents; Soils; Sulfur compounds; Volatile organic compounds; antifungal agent; volatile organic compound; Bacillus spp; Bacterial volatiles; Biological controls; Persea americana; Pseudomonas sp; Rhizosphere; antagonism; antimicrobial activity; beetle; biological control; fruit; fungus; growth; pathogen; rhizobacterium; rhizosphere; root rot; volatile organic compound; animal; Bacillus; beetle; biological control agent; Colletotrichum; drug effect; Fusarium; metabolism; microbiology; Persea; pharmacology; Phytophthora; Pseudomonas; Fungi | H4: Recent studies showed that bacterial volatile organic compounds (VOCs) play an important role in the suppression of phytopathogens. The ability of VOCs produced by avocado (Persea americana Mill.) rhizobacteria to suppress the growth of common avocado pathogens was therefore investigated. We evaluated the antifungal activity of VOCs emitted by avocado rhizobacteria in a first screening against Fusarium solani, and in subsequent antagonism assays against Fusarium sp. associated with Kuroshio shot hole borer, Colletotrichum gloeosporioides and Phytophthora cinnamomi, responsible for Fusarium dieback, anthracnosis and Phytophthora root rot in avocado, respectively. We also analyzed the composition of the bacterial volatile profiles by solid phase microextraction (SPME) gas chromatography coupled to mass spectrometry (GC–MS). Seven isolates, belonging to the bacterial genera Bacillus and Pseudomonas, reduced the mycelial growth of F. solani with inhibition percentages higher than 20%. Isolate HA, related to Bacillus amyloliquefaciens, significantly reduced the mycelial growth of Fusarium sp. and C. gloeosporioides and the mycelium density of P. cinnamomi. Isolates SO and SJJ, also members of the genus Bacillus, reduced Fusarium sp. mycelial growth and induced morphological alterations of fungal hyphae whilst isolate HB, close to B. mycoides, inhibited C. gloeosporioides. The analysis of the volatile profiles revealed the presence of ketones, pyrazines and sulfur-containing compounds, previously reported with antifungal activity. Altogether, our results support the potential of avocado rhizobacteria to act as biocontrol agents of avocado fungal pathogens and emphasize the importance of Bacillus spp. for the control of emerging avocado diseases such as Fusarium dieback. © 2018 | I4: Article | J4: Microbiological Research | K4: Importado | L4: scopus_export_Sep 18-2026_4e658477-f683-499d-a469-81d37efaa96b.csv | M4: Fitopatológico | O4: Registros únicos por base | P4: =COUNTA($A$4:$A$71) -> 68
A5: A0002 | B5: Scopus | C5: Colletotrichum fructicola, a Member of Colletotrichum gloeosporioides sensu lato, is the causal agent of anthracnose and soft rot in avocado fruits cv. "Hass" | D5: Fuentes-Aragón D.; Juárez-Vázquez S.B.; Vargas-Hernández M.; Silva-Rojas H.V. | E5: 2018 | F5: 10.1080/12298093.2018.1454010 | G5: Bayesian inference; Colletotrichum species complex; Fungal infection; Multilocus sequencing typing; Persea americana; Phylogenetic reconstruction | H5: The filamentous Ascomycota Colletotrichum gloeosporioides sensu lato is a fungus that has been reported worldwide as a causal agent of anthracnose disease in avocado and other crops. In Mexico, this species affects fruits from an early stage of development in the orchard until the post-harvest stage. Although fungicides are continuously applied to control Colletotrichum species, pericarp cankers and soft rot mesocarp in fruits are still frequently observed. Considering the lack of a precise description of the causative agent, the aim of the current study was to determine the pathogens involved in this symptomatology. Twenty-four isolates were consistently obtained from the pericarp of avocado fruits cv. "Hass" collected in the central avocado-producing area of Mexico. Morphological features such as colony growth, conidia size, and mycelial appressorium were assessed. Bayesian multilocus phylogenetic analyses were performed using amplified sequences of the internal transcribed spacer region of the nuclear ribosomal DNA; actin, chitin synthase, glyceraldehyde-3-phosphate dehydrogenase partial genes; and APn2-Mat1-2 intergenic spacer and mating type Mat1-2 partial gene from the nine selected isolates. In addition, fruits were inoculated with a conidial suspension and reproducible symptoms confirmed the presence of Colletotrichum fructicola in this area. This pathogenic species can now be added to those previously reported in the country, such as C. acutatum, C. boninense, C. godetiae, C. gloeosporioides, and C. karstii. Disease management programs to reduce the incidence of anthracnose should include C. fructicola to determine its response to fungicides that are routinely applied, considering that the appearance of new species is affecting the commercial quality of the fruits and shifting the original population structure. © 2018 The Author(s). | I5: Article | J5: Mycobiology | K5: Importado | L5: scopus_export_Sep 18-2026_82c23d75-ee65-4935-bf31-12365c1693d4.csv | M5: Fitopatológico | O5: Scopus | P5: =COUNTIF($B$4:$B$71,"Scopus") -> 50
A6: A0003 | B6: Scopus | C6: Colletotrichum perseae and Colletotrichum gloeosporioides sensu strictu Causing Stem Lesion and Dieback in Avocado in Italy | D6: Vecchio L.; Martino I.; Guarnaccia V.; Polizzi G.; Aiello D. | E6: 2026 | F6: 10.3390/horticulturae12010111 | G6: Colletotrichum species; Persea americana; stem and fruit infections | H6: In the last decade, avocado production has increased in Italy due to the fruit’s high nutritional quality and economic value. During 2024, stem lesions, wood discoloration and dieback, often starting at the grafting point, were observed in young plants in a nursery in Sicily (Italy). Colletotrichum-like colonies were frequently isolated from symptomatic tissues. Multi-locus phylogenetic analysis (gapdh, chs-1, act, tub2, cal, gs and ApMat) was conducted on 11 representative isolates, identifying 6 as C. perseae and 5 as C. gloeosporioides sensu stricto (s.s.). Two representative isolates were selected for pathogenicity tests performed on 2-year-old avocado plants cultivated in a greenhouse. After two months, necrotic lesions, wood discoloration and reddish-brown streaking at the inoculation point were induced in both species. Additional inoculations of avocado fruit confirmed the ability of both species to cause fruit rot. All inoculated fungi were successfully re-isolated and identified, fulfilling Koch’s postulates. This is the first report of stem lesions and dieback caused by Colletotrichum species and the first occurrence of C. perseae in avocado plants in Europe. The results highlight the importance of early monitoring in nurseries during the propagation process and contribute to a better understanding of fungal diseases in avocado crops in Italy. © 2026 by the authors. | I6: Article | J6: Horticulturae | K6: Importado | L6: scopus_export_Sep 17-2026_64f2de15-f34e-4ffa-b356-5d490b5ac07b.csv | scopus_export_Sep 18-2026_82c23d75-ee65-4935-bf31-12365c1693d4.csv | M6: Fitopatológico | O6: ScienceDirect | P6: =COUNTIF($B$4:$B$71,"Science Direct") -> 14
A7: A0004 | B7: Scopus | C7: Colletotrichum siamense is the main aetiological agent of anthracnose of avocado in south-eastern Brazil | D7: Soares M.G.O.; Alves E.; Silveira A.L.; Pereira F.D.; Guimarães S.S.C. | E7: 2021 | F7: 10.1111/ppa.13262 | G7: infectious process; multilocus phylogeny; pathogenicity; Persea americana; post-harvest disease; Brazil; Colletotrichum; Colletotrichum boninense; Persea americana; anthracnose; bacterium; deciduous tree; etiology; genetic variation; inoculation; isolated population; morphology; phylogenetics; sporulation | H7: Anthracnose caused by species of Colletotrichum is considered one of the main postharvest diseases for avocado. In this study, Colletotrichum isolates associated with avocado anthracnose, collected in different states of Brazil, were evaluated through phylogenetic analysis, morphological characterization, and pathogenicity assays. Moreover, the events during pathogen infection of avocados were examined by scanning electron microscopy. To assess the genetic diversity of 54 Colletotrichum isolates, partial sequence analysis of the gene gapdh was performed. According to the generated groupings and the geographical origins of isolates, a subset of 14 strains was selected for performing multilocus phylogeny analysis (using sequences of gapdh, act, tub2, and ApMat). Two species previously described were identified: C. siamense belonging to the C. gloeosporioides species complex and Colletotrichum karstii belonging to the C. boninense species complex. All Colletotrichum strains evaluated caused typical symptoms of anthracnose in avocado fruits. Conidia of the most virulent strain germinated between 6 and 12 hr after inoculation (hai). Penetration through wounds occurred 48 hai, tissue colonization occurred between 144 and 240 hai, and sporulation took place at 240 hai via the production of an acervulus, conidiophores, and conidia. The findings shed light on the aetiology of avocado anthracnose in Brazil and provide a better understanding of the infection process of this pathogen, which may assist in the development of disease management strategies. © 2020 British Society for Plant Pathology | I7: Article | J7: Plant Pathology | K7: Importado | L7: scopus_export_Sep 17-2026_64f2de15-f34e-4ffa-b356-5d490b5ac07b.csv | M7: Fitopatológico | O7: Springer Link | P7: =COUNTIF($B$4:$B$71,"Springer Link") -> 4
A8: A0005 | B8: Scopus | C8: Colletotrichum species causing anthracnose on avocado fruit in Mexico: Current status | D8: Fuentes-Aragón D.; Silva-Rojas H.V.; Guarnaccia V.; Mora-Aguilera J.A.; Aranda-Ocampo S.; Bautista-Martínez N.; Téliz-Ortíz D. | E8: 2020 | F8: 10.1111/ppa.13234 | G8: Colletotrichum jiangxiense sexual morph; Colletotrichum species; multilocus phylogenetic analyses; pathogenicity test; Persea americana; Mexico [North America]; Colletotrichum; Colletotrichum nymphaeae; Colletotrichum sp.; Persea americana; anthracnose; bacterium; crop plant; fruit; genetic analysis; morphology; pathogenicity; phylogenetics | H8: Colletotrichum species cause anthracnose disease in tropical and subtropical fruit crops worldwide. Mexico is the main producer and exporter of avocado (Persea americana) globally and has yearly outbreaks of anthracnose on this crop. However, which specific Colletotrichum spp. cause these outbreaks in avocado-producing regions remain uncertain; thus, the objective of the present study was to identify the species responsible. A survey performed in six production regions of Mexico yielded 232 isolates, from which a subset of 104 strains was selected based on morphological characteristics and origin. This subset was sequenced and haplotypes were analysed in the gapdh partial gene. Finally, 31 strains were identified through multilocus phylogenetic analyses using the sequences of the internal transcribed spacer region and six loci. This study revealed the presence of two species previously reported in Mexico (C. karsti and C. godetiae), three novel records in Mexico (C. siamense, C. fioriniae, and C. cigarro), four novel records on avocado (C. chrysophilum, C. jiangxiense, C. tropicale, and C. nymphaeae), and two novel lineages (Colletotrichum sp. 1 and Colletotrichum sp. 2). C. siamense was the most prevalent, while the species reported for the first time on avocado, including the novel lineages, were the least prevalent. C. karsti was the most widespread (four regions), followed by C. siamense, C. jiangxiense, and C. chrysophilum (three regions). Pathogenicity tests showed that all species caused anthracnose on avocado fruit. These findings will be useful for improving the management of avocado anthracnose outbreaks in Mexico. © 2020 British Society for Plant Pathology | I8: Article | J8: Plant Pathology | K8: Importado | L8: scopus_export_Sep 17-2026_2fb2f4b0-ee23-499b-9e91-17eb9cc8aaf8.csv | M8: Fitopatológico | O8: Fitopatológicos (A0001–A0048) | P8: =COUNTIF($M$4:$M$71,"Fitopatológico") -> 48
A9: A0006 | B9: Scopus | C9: Ecofriendly management of anthracnose on avocado caused by Colletotrichum perseae in the Mediterranean basin | D9: Vecchio L.; Arrebola E.; Polizzi G.; Vitale A. | E9: 2026 | F9: 10.1002/jsf2.70088 | G9: anthracnose; avocado; Bacillus; biological control agents; sustainable agriculture; Trichoderma | H9: Background: Colletotrichum perseae, recently reported in Europe, causes stem and twig lesions and dieback, and fruit rot on avocado in several countries. Due to EU severe restrictions, there is an urgent need for sustainable alternatives to fungicides. This study aims to evaluate the preventative activity of trade bioformulates against C. perseae across detached twig, greenhouse pot-plant grown, and postharvest fruit experiments. Results: All biological treatments have significantly managed twig anthracnose infections ranging by 37%–91% reductions. Bacillus amyloliquefaciens QST713, chitosan, Trichoderma gamsii + Trichoderma asperellum mixture, and Equisetum arvense based bioformulates showed a similar efficacy of the standard fungicide (pyraclostrobin) whilst sweet orange essential oils were less effective. In potted plants grown in greenhouse, T. asperellum T34 followed by T. gamsii + T. asperellum mixture bioformulates revealed the most effective in reducing internal lesions caused by C. perseae. On the other hand, bioformulate containing B. amyloliquefaciens D747 revealed the most effective treatment in minimizing C. perseae anthracnose lesions under post-harvest conditions. Conclusion: The paper clearly showed that some trade bioformulates could represent a highly effective, environmentally friendly option for managing C. perseae of avocado. The implementation of such an approach should be imperative for developing performant strategies for other avocado diseases. This process should begin with preventive applications of Trichoderma species as T34 in nursery and preserve the health in postharvest by using B. amyloliquefaciens strains-based formulates. Indeed, the strategic adoption of these trade bioalternatives provides a concrete pathway to replace chemical fungicides. © 2026 The Author(s). JSFA Reports published by John Wiley & Sons Ltd on behalf of Society of Chemical Industry. | I9: Article | J9: JSFA reports | K9: Importado | L9: scopus_export_Sep 17-2026_64f2de15-f34e-4ffa-b356-5d490b5ac07b.csv | M9: Fitopatológico | O9: Tecnológicos (T0001–T0020) | P9: =COUNTIF($M$4:$M$71,"Tecnológico") -> 20
A10: A0007 | B10: Scopus | C10: Effect of pectin-based edible emulsion coating on changes in quality of avocado exposed to Lasiodiplodia theobromae infection | D10: Maftoonazad N.; Ramaswamy H.S.; Moalemiyan M.; Kushalappa A.C. | E10: 2007 | F10: 10.1016/j.carbpol.2006.11.020 | G10: Avocado; Coating; Color; Edible film; Lasiodiplodia theobromae; Pectin; Respiration rate; Storage; Texture; Carbohydrates; Emulsions; Food Storage; Fruits; Fungi; Persea; Botryosphaeria rhodina; Persea americana; Emulsions; Food storage; Fruits; Fungi; Edible films; Lasiodiplodia theobromae; Pectin; Respiration rate; Uncoated fruits; Carbohydrates | H10: This study was carried out to evaluate the effect of pectin-based edible emulsion coating on activity and disease severity of Lasiodiplodia theobromae in avocados, and their subsequent influence on the fruit quality. In order to assess the influence of coating and disease, avocados were sorted and devided into four equal lots and all were incubated at 20 °C for up to 4 days. The first and second lots constituted samples which were stored as coated and uncoated, respectively, without fungal inoculation. The third and fourth lots were coated and un-coated fruits inoculated with the fungal disease. For coating, a previously standardized pectin-based emulsion was used. The incubated fruits were examined for the spread of disease, respiration rate and quality parameters, color and texture. As the incubation time increased, the volume of disease (VDS) increased, which in turn influenced the respiration rate (RR) in both coated and uncoated fruits. However, the coated fruits sustained a significantly slower rate of disease spread and RR. Similarly, the associated quality changes (texture and color) were much lower in coated fruits as compared with the control. Thus, the pectin based coating was effective in controlling the spread and severity of stem end rot in avocados. Changes in physical and physiological parameters of coated and uncoated fruits were well described by some form of semi-logarithmic models and were related to the VDS as well as case dependent incubation time. © 2007. | I10: Article | J10: Carbohydrate Polymers | K10: Importado | L10: scopus_export_Sep 18-2026_8f28b456-611a-478a-9b87-bb5029e250f3.csv | M10: Fitopatológico | O10: Recuperados en dos exportaciones de la misma base | P10: =COUNTIF($L$4:$L$71,"*|*") -> 10
A11: A0008 | B11: Scopus | C11: Effect of seaweed extract on avocado root growth, yield and post-harvest quality in far north Queensland, Australia | D11: Arioli T.; Villalta O.N.; Hepworth G.; Farnsworth B.; Mattner S.W. | E11: 2024 | F11: 10.1007/s10811-023-02933-0 | G11: Ascophyllum nodosum; Biostimulant; Durvillaea potatorum; Persea americana; Phytophthora cinnamomi | H11: Seaweed extracts are proven to increase productivity in many agricultural crops, but there is limited research on their use in avocado production. Therefore, we evaluated the effectiveness of a seaweed extract from Durvillaea potatorum and Ascophyllum nodosum on avocado yield, revenue and post-harvest fruit quality in a series of field experiments in Australia, and on seedling root growth in a pot experiment. The field experiments were conducted on commercial farms across three different locations in northern Queensland over four years and utilised avocado trees with different ages, cultivars (Hass and Shepard) and inoculum pressures from Phytophthora cinnamomi. Results showed that the application of the seaweed extract by fertigation significantly improved avocado yield (kg fruit per tree) by 38%, fruit firmness by 4% (skin) and 22% (flesh) and fruit skin colour by 1° (hue), and an upgraded visual ripeness score. The increases in yield were associated with greater number of fruits per tree (up to 42%) indicating the liquid seaweed extract improved fruit set and retention per tree. Regular soil application of the seaweed extract to young trees (cv. Hass) in pots increased the root fresh weight by 22%. Overall, the regular application of the seaweed extract to avocado trees was found to be practical and economically viable for improving fruit production and post-harvest quality in Australian orchards. © The Author(s) 2023. | I11: Article | J11: Journal of Applied Phycology | K11: Importado | L11: scopus_export_Sep 18-2026_162c1d26-553e-41ee-8ea1-e9ecd3a7eea2.csv | M11: Fitopatológico
A12: A0009 | B12: Scopus | C12: Emerging pathogens and disease dynamics threatening avocado production in southern Türkiye | D12: Çalış Ö.; Çelik S.; Fidan H.; Tek M.I.; Shah M.; Tozlu I.; Wani S.H. | E12: 2024 | F12: 10.1007/s41348-024-00954-6 | G12: Anthracnose; Avocado; Branch canker; Dieback; Fungal diseases; Soil-borne pathogens; Turkey; anthracnose; biological control; dieback; fruit; fungal disease; fungus; pathogen; pathogenicity; soilborne disease | H12: Avocado (Persea americana Milll.) holds a pivotal position in global fruit crops, contributing significantly to the economies of tropical and subtropical regions. However, the rising incidence of diseases poses a substantial risk to avocado production. This comprehensive study investigated the disease landscape in Antalya, the largest avocado cultivation area in the Türkiye. A survey of 2537 avocado trees across 11 regions from 2020 to 2021 revealed alarming disease incidences, particularly in the eastern regions of Gazipasa and Alanya. Dieback, branch canker, anthracnose, and soil-borne root rot were identified as the primary diseases affecting tree canopies, twigs, and branches. Morphological and molecular analyzes unveiled a spectrum of pathogens, with Colletotrichum gloeosporioides dominating in the Mediterranean region. Notably, Phytophthora cinnamomi emerged as a severe threat, causing root rot and decline in avocado trees. Fusarium solani and Fusarium oxysporum, known for their association with tropical fruit crops, were identified in the western parts of Antalya. Additionally, we have detected Neofusicoccum parvum, Lasiodiplodia theobromae, and Neopestalotiopsis rosae in collected samples from avocado trees. The identified pathogens exhibited varying levels of severity in branch canker and anthracnose on avocado branches and leaves. Furthermore, pathogenicity evaluations shed light on the potential of these pathogens to induce severe symptoms, emphasizing the urgency for effective control measures. The exploration of cultural and biological control strategies are crucial for mitigating the impact of branch canker, dieback, and anthracnose diseases, ensuring the sustainability of avocado cultivation in the region. © The Author(s) 2024. | I12: Article | J12: Journal of Plant Diseases and Protection | K12: Importado | L12: scopus_export_Sep 17-2026_64f2de15-f34e-4ffa-b356-5d490b5ac07b.csv | scopus_export_Sep 18-2026_8f28b456-611a-478a-9b87-bb5029e250f3.csv | M12: Fitopatológico
A13: A0010 | B13: Scopus | C13: Expression of several Phytophthora cinnamomi putative RxLRs provides evidence for virulence roles in avocado | D13: Joubert M.; Backer R.; Engelbrecht J.; Van Den Berg N. | E13: 2021 | F13: 10.1371/journal.pone.0254645 | G13: Persea; Phylogeny; Phytophthora; Virulence; fungal protein; RxLR protein; unclassified drug; amino acid sequence; Article; avocado; controlled study; fungal genome; fungal virulence; gene; gene expression; gene expression profiling; nonhuman; nucleotide sequence; phylogeny; Phytophthora cinnamomi; Phytophthora root rot; root rot; RxLR gene; parasitology; pathogenicity; Persea; Phytophthora; virulence | H13: Phytophthora cinnamomi is a plant pathogenic oomycete that causes Phytophthora root rot of avocado (PRR). Currently, there is a limited understanding of the molecular interactions underlying this disease. Other Phytophthora species employ an arsenal of effector proteins to manipulate host physiology, of which the RxLR effectors contribute to virulence by interfering with host immune responses. The aim of this study was to identify candidate RxLR effectors in P. cinnamomi that play a role in establishing PRR, and to infer possible functions for these effectors. We identified 61 candidate RxLR genes which were expressed during infection of a susceptible avocado rootstock. Several of these genes were present in multiple copies in the P. cinnamomi genome, suggesting that they may contribute to pathogen fitness. Phylogenetic analysis of the manually predicted RxLR protein sequences revealed 12 P. cinnamomi RxLRs that were related to characterised effectors in other Phytophthora spp., providing clues to their functions in planta. Expression profiles of nine more RxLRs point to possible virulence roles in avocado-highlighting a way forward for studies of this interaction. This study represents the first investigation of the expression of P. cinnamomi RxLR genes during the course of avocado infection, and puts forward a pipeline to pinpoint effector genes with potential as virulence determinants, providing a foundation for the future functional characterization of RxLRs that contribute to P. cinnamomi virulence in avocado. © 2021 Joubert et al. This is an open access article distributed under the terms of the Creative Commons Attribution License, which permits unrestricted use, distribution, and reproduction in any medium, provided the original author and source are credited. | I13: Article | J13: PLoS ONE | K13: Importado | L13: scopus_export_Sep 17-2026_64f2de15-f34e-4ffa-b356-5d490b5ac07b.csv | M13: Fitopatológico
A14: A0011 | B14: Scopus | C14: First Record of Colletotrichum anthrisci Causing Anthracnose on Avocado Fruits in Chile | D14: Bustamante M.I.; Osorio-Navarro C.; Fernández Y.; Bourret T.B.; Zamorano A.; Henríquez-Sáez J.L. | E14: 2022 | F14: 10.3390/pathogens11101204 | G14: etiology; Persea americana; postharvest disease; streptomycin; anthracnose; Article; avocado; Colletotrichum; conidium; controlled study; DNA extraction; DNA sequencing; fungus isolation; mycelial growth; nonhuman; phylogeny; sporogenesis; temperature | H14: Anthracnose caused by Colletotrichum species is one of the most frequent and damaging fungal diseases affecting avocado fruits (Persea americana Mill.) worldwide. In Chile, the disease incidence has increased over the last decades due to the establishment of commercial groves in more humid areas. Since 2018, unusual symptoms of anthracnose have been observed on Hass avocado fruits, with lesions developing a white to gray sporulation. Morphological features and multi-locus phylogenetic analyses using six DNA barcodes (act, chs-1, gapdh, his3, ITS, and tub2) allowed the identification of the causal agent as Colletotrichum anthrisci, a member of the dematium species complex. Pathogenicity was confirmed by inoculating healthy Hass avocado fruits with representative isolates, reproducing the same symptoms initially observed, and successfully reisolating the same isolates from the margin of the necrotic pulp. Previously, several Colletotrichum species belonging to other species complexes have been associated with avocado anthracnose in other countries. To our knowledge, this is the first record of C. anthrisci and of a species of the dematium species complex causing anthracnose on avocado fruits in Chile and worldwide. © 2022 by the authors. | I14: Article | J14: Pathogens | K14: Importado | L14: scopus_export_Sep 17-2026_64f2de15-f34e-4ffa-b356-5d490b5ac07b.csv | M14: Fitopatológico
A15: A0012 | B15: Scopus | C15: First Report of Fusarium equiseti Causing Postharvest Fruit Rot of Avocado in Türkiye | D15: Bozoğlu T.; Derviş S.; Özer G.; Türkkan M. | E15: 2025 | F15: 10.1111/jph.70131 | G15: Fusarium equiseti; Persea americana; postharvest fruit rot; rpb2 phylogeny; stem-end rot; tef1; Black Sea; amplification; fruit; inoculation; molecular analysis; phylogeny; RNA; root rot | H15: In September 2024, postharvest fruit rot, including stem-end rot, was observed on avocado in the Altınordu district of Ordu province, located in the Eastern Black Sea Region of Türkiye. A market survey revealed that 5% of fruit exhibited fruit rot symptoms, a subset of which displayed stem-end rot symptoms, including brown to black lesions extending into the mesocarp, shrivelling and fungal mycelium growth. Fusarium equiseti was identified as the causal agent through morphological characterisation and molecular analysis using PCR amplification and sequencing of translation elongation factor 1-alpha (tef1) and RNA polymerase II second largest subunit (rpb2) gene sequences, including phylogenetic analysis. Artificial inoculation and subsequent re-isolation confirmed Koch's postulates, verifying F. equiseti as the causal pathogen. This is the first report of F. equiseti causing both fruit rot and stem-end rot on avocado in Türkiye, highlighting the need for improved postharvest disease management strategies to reduce economic losses in Türkiye's avocado industry. © 2025 The Author(s). Journal of Phytopathology published by Wiley-VCH GmbH. | I15: Article | J15: Journal of Phytopathology | K15: Importado | L15: scopus_export_Sep 17-2026_64f2de15-f34e-4ffa-b356-5d490b5ac07b.csv | scopus_export_Sep 18-2026_4e658477-f683-499d-a469-81d37efaa96b.csv | M15: Fitopatológico
A16: A0013 | B16: Scopus | C16: First report of Phytophthora cinnamomi causing avocado root rot in India | D16: Madhu G.S.; Rani A.T.; Muralidhara B.M.; Rajendiran S.; Sriram S.; Venkataravanappa V. | E16: 2023 | F16: 10.1007/s42161-023-01471-5 | G16: Avocado; Phytophthora cinnamomi; Root rot | H16: [No abstract available] | I16: Article | J16: Journal of Plant Pathology | K16: Importado | L16: scopus_export_Sep 18-2026_162c1d26-553e-41ee-8ea1-e9ecd3a7eea2.csv | M16: Fitopatológico
A17: A0014 | B17: Scopus | C17: Four new fungal pathogens causing avocado dieback in Brazil | D17: Silva T.F.; Pimentel Duarte J.L.; Vélez-Olmedo J.B.; Anderson dos Santos Vieira W.; Bassay Blum L.E.; Pinho D.B. | E17: 2025 | F17: 10.1016/j.cropro.2025.107168 | G17: Canker; Diagnosis; Persea americana; Phylogeny; Plant disease complex; Brazil; dicotyledon; dieback; etiology; fungal disease; fungus; pathogenicity; phylogeny; RNA | H17: Dieback is a disease with a complex etiology that results in the death of branches or entire plants in avocado producing regions. Losses associated with this disease have already been reported in the main producing regions of Brazil. The etiological agents of this disease are different and an association between fungi is often observed. This study aimed to identify fungi associated with avocado dieback in Brazil. Fungal isolates were collected from symptomatic avocado stems from orchards in São Paulo state. Identification was based on phenotypic characteristics and multilocus phylogenetic analysis of the translation elongation factor 1-alpha, RNA polymerase II, β-tubulin, actin, the internal transcribed spacer (ITS) region of rDNA, and the large subunit ribosomal RNA regions, according to the previously identified genus. The pathogenicity test confirmed that all species were pathogenic to avocado seedlings and fruits. This is the first report of Neopestalotiopsis arecacearum, Neocosmospora bostrycoides, Nectria pseudotrichia and Cytospora viridistroma causing avocado dieback in Brazil and worldwide. Identifying emerging pathogens that cause losses is crucial for avocado-producing countries with different climatic conditions, as it helps understand the geographic distribution of these phytopathogens and the conditions that favor their development. © 2025 Elsevier Ltd | I17: Article | J17: Crop Protection | K17: Importado | L17: scopus_export_Sep 18-2026_6573fc91-2043-414f-a3dc-1112c7ddea01.csv | M17: Fitopatológico
A18: A0015 | B18: Scopus | C18: Fungal Pathogens Associated with Aerial Symptoms of Avocado (Persea americana Mill.) in Tenerife (Canary Islands, Spain) Focused on Species of the Family Botryosphaeriaceae | D18: Hernández D.; García-Pérez O.; Perera S.; González-Carracedo M.A.; Rodríguez-Pérez A.; Siverio F. | E18: 2023 | F18: 10.3390/microorganisms11030585 | G18: canker; dieback; Lasiodiplodia brasiliensis; Neofusicoccum australe; Neofusicoccum cryptoaustrale; Neofusicoccum luteum; Neofusicoccum parvum; Neofusicoccum stellenboschiana; Persea americana; stem-end rot | H18: Fungi of the family Botryosphaeriaceae are considered responsible for various symptoms in avocado such as dieback, external necrosis of branches and inflorescences, cankers on branches and trunks, or stem-end rot of fruits. In recent years, these problems are becoming more frequent in avocado orchards in the Canary Islands (Spain). This work includes the characterization of fungal species involved in these diseases, which were isolated from avocado crops in Tenerife Island between 2018 and 2022. A total of 158 vegetal samples were collected, from which 297 fungal isolates were culture-isolated. Fifty-two of them were selected according to their morphological features as representative isolates of Botryosphaeriaceae, and their molecular characterization was carried out, sequencing the ITS1-2 region as well as the β-tubulin and the elongation factor 1-alpha genes. Five species of Botryosphaeriaceae were isolated, including Neofusicoccum australe, N. cryptoaustrale/stellenboschiana, N. luteum, N. parvum, and Lasiodiplodia brasiliensis. This is the first time that L. brasiliensis has been associated with avocado dieback and that N. cryptoaustrale/stellenboschiana has been cited in avocado causing symptoms of dieback and stem-end rot. However, it was not possible to assign our isolates unequivocally to N. cryptoaustrale or N. stellenboschiana even additionally using the rpb2 marker for their molecular characterization. Botryosphaeriaceae family seem to be involved in avocado dieback, in the premature fall of fruits during their development in the field and in post-harvest damage in Tenerife, but further studies are needed to clarify the fungal pathogens associated with symptoms in relation to phenological plant growth stages or less frequently observed. © 2023 by the authors. | I18: Article | J18: Microorganisms | K18: Importado | L18: scopus_export_Sep 18-2026_96199bb3-e2ff-4aa3-a2d7-ec2db6aced85.csv | M18: Fitopatológico
A19: A0016 | B19: Scopus | C19: Fungal Species of Botryosphaeriaceae Associated With Avocado Dieback in Southern Spain | D19: Crespo M.; Guirado-Manzano L.; Sarmiento D.; Guirado E.; de Vicente A.; Fernández-Ortuño D.; Cazorla F.M.; Arrebola E. | E19: 2026 | F19: 10.1111/ppa.70079 | G19: aetiology; cankers; Lasiodiplodia sp.; Neofusicoccum spp.; pathogenicity; Persea americana; Granada [Nicaragua]; dieback; etiology; fungal disease; fungus; irrigation system; pathogenicity; symptom | H19: Avocado (Persea americana) has become one of the most important subtropical crops in southern Spain. In recent years, the scarcity of irrigation water has made this crop susceptible to opportunistic diseases. This sensitivity has been associated with a series of symptoms characterised by the death of branches, mummification of fruits, cankers and reddening of the vascular bundles. To identify the aetiology of the disease, surveys have been carried out on avocado farms in the most affected areas, including Málaga and Granada (southern Spain). The surveys were conducted from 2019 to 2022. A total of 252 fungal isolates were recovered from trees with symptoms of dieback disease. Of these isolates, 172 were initially identified by sequencing the rDNA internal transcribed spacer (ITS) region to identify potential pathogens compatible with the symptoms. Based on the number of isolates, the most prevalent were Neofusicoccum spp. (110 isolates) and Lasiodiplodia sp. (15 isolates), although some isolates of Diaporthe sp. (four isolates) and Colletotrichum sp. (eight isolates) were also identified. Pathogenicity experiments in plants, branches and fruits confirmed these fungi as possible causal agents as they reproduced the symptoms found in diseased avocado crops. The frequency of isolates associated with dieback symptoms, along with greater severity in the reproduced symptoms, shows Botryosphaeriaceae species as the main cause of dieback in avocado in southern Spain. The main objective of the present study is to elucidate the aetiology of the disease to establish the infection time and thereby lay the groundwork for designing control studies. © 2025 The Author(s). Plant Pathology published by John Wiley & Sons Ltd on behalf of British Society for Plant Pathology. | I19: Article | J19: Plant Pathology | K19: Importado | L19: scopus_export_Sep 17-2026_64f2de15-f34e-4ffa-b356-5d490b5ac07b.csv | scopus_export_Sep 18-2026_96199bb3-e2ff-4aa3-a2d7-ec2db6aced85.csv | M19: Fitopatológico
A20: A0017 | B20: Scopus | C20: Genome assembly and annotation of Rugonectria rugulosa, a fungus associated with avocado (Persea americana cv. Hass) trunk canker in Colombia | D20: Rincón López J.D.; Chacón-Vargas K.; Clavijo-Buriticá D.C.; García-Merchán V.H. | E20: 2026 | F20: 10.1128/mra.00512-26 | G20: avocado; fungal genomics; genome assembly; Nectriaceae; plant pathogen; Rugonectria rugulosa; secondary metabolites; trunk canker; wilting; Article; avocado; Colombia; fungal genome; fungus; fungus isolation; genomics; nonhuman; phytopathogen; Rugonectria rugulosa | H20: Rugonectria rugulosa is a member of the family Nectriaceae associated with trunk canker diseases in woody plants, including avocado (Persea americana cv. Hass). Here, we report the 53 Mb draft genome assembly of a Colombian isolate, providing a genomic resource to investigate the biology and pathogenic potential of this species. Copyright © 2026 Rincón López et al. | I20: Article | J20: Microbiology Resource Announcements | K20: Importado (primer autor corregido según el PDF: Scopus lo registra como López J.D.R.) | L20: scopus_export_Sep 17-2026_64f2de15-f34e-4ffa-b356-5d490b5ac07b.csv | scopus_export_Sep 18-2026_6573fc91-2043-414f-a3dc-1112c7ddea01.csv | M20: Fitopatológico
A21: A0018 | B21: Scopus | C21: Identification and Pathogenicity of Botryosphaeriaceae, Colletotrichum, and Phytophthora Species Associated with Avocado Diseases in Italy | D21: Linaldeddu B.T.; Bregant C.; Muscas J.; Maddau L.; Vecchio L.; Polizzi G.; Aiello D. | E21: 2026 | F21: 10.3390/agriculture16101035 | G21: Botryosphaeriaceae; co-infections; holistic diagnosis; oomycetes | H21: With the rapid expansion of avocado cultivation in southern Italy, growers have had to deal with the emergence of new diseases often caused by invasive and polyphagous pathogens responsible for leaf spot, branch cankers, dieback and fruit and root rot. Given the severity of these emerging diseases, a study was conducted in the main avocado growing areas in Sardinia and Sicily (Italy) to isolate and characterize the causal agents. Specifically, a total of 430 symptomatic leaf, fruit, branch, stem and root samples were collected and examined. Isolations performed on both non-selective and selective growth media yielded 22 species (fungi and oomycetes) belonging to the genera Botryosphaeria, Colletotrichum, Diplodia, Dothiorella, Macrophomina, Neofusicoccum and Phytophthora, including 14 new host–pathogen records in Italy. Notably, Neofusicoccum australe, Phytophthora cinnamomi and Phytophthora palmivora emerged as the main pathogens involved in the emerging avocado diseases. The identified pathogens were often isolated simultaneously from the same plants, which exhibited a complex of symptoms. Pathogenicity bioassays have helped to clarify the differences in aggressiveness among the different species and their specificity towards the different plant organs. The results achieved suggest that avocado orchards’ productivity and profitability is threatened by a plethora of unrelated pathogens whose control represents a major challenge for the success of this crop in Italy. © 2026 by the authors. | I21: Article | J21: Agriculture (Switzerland) | K21: Importado | L21: scopus_export_Sep 18-2026_96199bb3-e2ff-4aa3-a2d7-ec2db6aced85.csv | M21: Fitopatológico
A22: A0019 | B22: Scopus | C22: Identification and Pathogenicity of Fungal Pathogens Associated with Stem End Rots of Avocado Fruits in Kenya | D22: Wanjiku E.K.; Waceke J.W.; Wanjala B.W.; Mbaka J.N. | E22: 2020 | F22: 10.1155/2020/4063697 | G22: No especificado | H22: Losses associated with stem end rot (SER) of avocado fruits have been reported in all avocado growing regions of the world. In Kenya, mature avocado fruits present SER symptoms during storage and marketing, but the disease causal agent(s) has not been established. This study aimed to identify the fungal pathogen(s) associated with avocado SER in Kenya and evaluate its pathogenicity. Fungal isolates were collected from symptomatic avocado fruits from randomly selected orchards and major markets within Murang'a County, a major avocado growing region in Kenya, between September 2017 and March 2018. A total of 207 and 125 fungal isolates, recovered from orchards and major markets, respectively, were identified morphologically and further confirmed by molecular techniques. The identified isolates were Lasiodiplodia theobromae (39.8%), Neofusicoccum parvum (24.4%), Nectria pseudotrichia (18.4%), Fusarium solani (7.2%), F. oxysporum (5.1%), F. equiseti (3.9%), and Geotricum candidum (1.2%). Geotricum candidum was exclusively recovered from fruits from the market. In the pathogenicity test, L. theobromae, N. parvum, and N. pseudotrichia caused the most severe SER symptoms. Consequently, they were considered to be the major pathogens of SER of avocado fruits in Kenya. To our knowledge, this is the first report of SER pathogen of avocado fruits in Kenya. Given the significant contribution of avocado fruits to household income and foreign exchange in Kenya, this information is significant to further develop management strategies of postharvest loss of avocado fruits in Kenya. © 2020 E. K. Wanjiku et al. | I22: Article | J22: International Journal of Microbiology | K22: Importado | L22: scopus_export_Sep 18-2026_6573fc91-2043-414f-a3dc-1112c7ddea01.csv | M22: Fitopatológico
... A51: A0048 | B51: Springer Link | C51: Lasiodiplodia theobromae disease symptom development in young avocado (Persea americana L.) plants depends on the inoculation method | D51: Rodríguez-Gálvez, Edgar; Haro-Diaz, Cesar; Maza-Aguirre, Samir; Canahuire-Castillo, Fátima; Sullón-Saucedo, Julio; Deising, Holger B. | E51: 2025 | F51: 10.1007/s40858-025-00700-9 | G51: Avocado · External and internal necrosis · Lasiodiplodia theobromae · Persea americana · Symptom | H51: Lasiodiplodia theobromae is a pathogenic fungus of more than 500 plant species, including avocado (Persea americana Mill.). The global production volume of avocado exceeded 911,000 metric tons in 2023. Although detailed quantitative surveys of yield losses caused by L. theobromae are not available for most avocado-producing regions, estimates indicate that this pathogen is associated with stem-end rot disease in 30-35% of plots located in the Department of Antioquia in Colombia (Ramírez-Gil et al. Heliyon 7: e05905, 2021), suggesting an enormous economic impact. As yield losses strongly depend on the virulence of isolates, a reliable method for determining their aggressiveness is indispensable for initiating disease control measures. In this study, we compared progression of external and internal necrosis caused by the aggressive L. theobromae isolate LA-VLCA3 inoculated into wounded middle parts of the stem and onto excised apices. Irrespective of the inoculation method, internal progression of necrosis preceded that of external necrosis. Spreading of external and internal necrosis was significantly more severe in plants inoculated at the apex than in mid-stem inoculated plants. We conclude that apex inoculation causes stronger symptoms and is therefore better suited to compare virulence of isolates than mid-stem inoculation. | I51: Article | J51: Tropical Plant Pathology | K51: Importado | L51: 10.1007_s40858-025-00700-9-citation.ris | M51: Fitopatológico
A52: T0001 | B52: Scopus | C52: Assessment of avocado water stress using multispectral imaging and deep learning: Toward scalable, cost-effective irrigation monitoring | D52: Estrada J.S.; Cetin N.; Sacilik K.; Ulu B.; Ulu B.; Auat Cheein F. | E52: 2026 | F52: 10.1016/j.eswa.2026.132688 | G52: Deep learning; Dehydration stage; Hyperspectral reflectance values; Machine learning; Multi-spectral images; Bayesian networks; Convolutional neural networks; Cost effectiveness; Decision trees; Dehydration; Discriminant analysis; Forestry; Fruits; Hyperspectral imaging; Irrigation; Learning systems; Logistic regression; Multilayer neural networks; Nearest neighbor search; Random forests; Support vector regression; Deep learning; Dehydration stage; Hyperspectral reflectance; Hyperspectral reflectance value; Leaf water content; Linear discriminant analyze; Machine learning models; Machine-learning; Multispectral images; Reflectance values; Deep learning | H52: The identification of leaf water content in avocados can help to improve the irrigation regimes, thus alleviating the great water consumption of the avocado production. The classification of leaves according to their dehydration stage can be used as an early assessment tool for leaf water content identification. This study focuses on classifying avocado leaves based on their dehydration stage, using two approaches: hyperspectral reflectance values with classic machine learning models, and multi-spectral images with deep convolutional neural networks. The classic machine learning algorithms trained include random forest, k-nearest neighbours, support vector machine, bagging, decision tree, reduced error pruning tree, simple classification and regression tree, Bayesian networks, logistic model tree, linear discriminant analysis, multinomial logistic regression, and multilayer perceptron. The deep learning approach employed convolutinal neural network, specifically ConvNeXt-Tiny, MobileNetV3-Large, and ResNet18. The models were evaluated using common metrics such as accuracy, precision, f1 score, receiving operating characteristic curves, area under curve and confusion matrices. Among the machine learning models, linear discriminant analysis achieved the highest accuracy of 0.98. Meanwhile, ResNet18 outperformed the other CNNs, achieving an accuracy of 0.99 on the validation dataset. These results highlight the effectiveness of the proposed methods for classifying avocado leaves based on their dehydration level. © 2026 The Authors. Published by Elsevier Ltd. This is an open access article under the CC BY-NC license. http://creativecommons.org/licenses/by-nc/4.0/ | I52: Article | J52: Expert Systems with Applications | K52: Importado | L52: export_47b321cb-1eb2-4971-9a96-aeef542f0ff6_2026-09-25T151053.275989337.csv | scopus (4).csv | M52: Tecnológico
A53: T0002 | B53: Scopus | C53: ApaltAI: a web-based diagnostic system with a sequential voting architecture for detecting anthracnose and scab in avocado fruit | D53: Moreano M.; Sosa A.; Mauricio D.; Rivera L.; Santisteban J. | E53: 2026 | F53: 10.3389/fpls.2026.1736123 | G53: avocado; convolutional neural networks; deep learning; disease detection; image processing | H53: Avocado (Persea americana Mill.), with a global production estimated at 10.4 million tons in 2023, suffers annual losses of 20-30% due to diseases such as anthracnose (Colletotrichum gloeosporioides) and scab (Sphaceloma perseae), resulting in substantial economic impacts for major producing countries (Mexico, Peru, and Colombia). This study introduces an advanced system that integrates a binary sequential voting architecture (VotingBS) with a fully functional web application, for the automated identification of two high-incidence diseases: anthracnose and scab, both of which critically affect fruit quality and yield. The proposed VotingBS architecture implements a hierarchical two-stage classification strategy. In the first stage, a five-model deep learning ensemble differentiates between healthy and diseased fruits. In the second stage, another ensemble determines which of the two diseases is present. For this purpose, a collection of 674 labeled fruit images was used for training and validation. Experimental results demonstrate outstanding model performance, achieving key metrics such as 98.92% precision, 98.89% recall, and 99.03% accuracy, significantly outperforming traditional approaches. Moreover, the solution was deployed through a web app featuring dedicated modules for crop management, phytosanitary analysis, and disease diagnosis. This architecture enhances the system’s practical utility and facilitates its adoption by farmers, field technicians, and agricultural monitoring agencies. Overall, this work demonstrates how combining hybrid deep learning models with accessible digital platforms can revolutionize plant disease diagnostics, fostering a more efficient, automated, and resilient precision agriculture. Copyright © 2026 Moreano, Sosa, Mauricio, Rivera and Santisteban. | I53: Article | J53: Frontiers in Plant Science | K53: Importado | L53: export_47b321cb-1eb2-4971-9a96-aeef542f0ff6_2026-09-25T151053.275989337.csv | M53: Tecnológico
A54: T0003 | B54: Scopus | C54: Shelf-Life Management and Ripening Assessment of ‘Hass’ Avocado (Persea americana) Using Deep Learning Approaches | D54: Xavier P.; Rodrigues P.M.; Silva C.L.M. | E54: 2024 | F54: 10.3390/foods13081150 | G54: convolutional neural network; fruit ripening; post-harvest handling; shelf-life tracking; supply chain management | H54: Avocado production is mostly confined to tropical and subtropical regions, leading to lengthy distribution channels that, coupled with their unpredictable post-harvest behavior, render avocados susceptible to significant loss and waste. To enhance the monitoring of ‘Hass’ avocado ripening, a data-driven tool was developed using a deep learning approach. This study involved monitoring 478 avocados stored in three distinct storage environments, using a 5-stage Ripening Index to classify each fruit’s ripening phase based on their shared characteristics. These categories were paired with daily photographic records of the avocados, resulting in a database of labeled images. Two convolutional neural network models, AlexNet and ResNet-18, were trained using transfer learning techniques to identify distinct ripening indicators, enabling the prediction of ripening stages and shelf-life estimations for new unseen data. The approach achieved a final prediction accuracy of 88.8% for the ripening assessment, with 96.7% of predictions deviating by no more than half a stage from their actual classifications when considering the best side of the samples. The average shelf-life estimates based on the attributed classifications were within 0.92 days of the actual shelf-life, whereas the predictions made by the models had an average deviation of 0.96 days from the actual shelf-life. © 2024 by the authors. | I54: Article | J54: Foods | K54: Importado | L54: scopus (1).csv | M54: Tecnológico
A55: T0004 | B55: Scopus | C55: A Systematic Review on the Detection and Classification of Plant Diseases Using Machine Learning | D55: Munjal D.; Singh L.; Pandey M.; Lakra S. | E55: 2023 | F55: 10.4018/ijsi.315657 | G55: Agriculture; classification; Deep learning; Image Processing; Machine learning; segmented image | H55: The occurrence of disease in plants might affect the crop production at a large scale, resulting into decline of the economic growth rate of the country. The disease in plants can be detected and treated at an early stage. Machine learning (ML), deep learning (DL), and computer vision-based techniques could play a pivotal role in detecting and classifying the diseases at an early stage. These approaches have even surpassed the human performance, as well as image processing based traditional approaches in the analysis and classification of plant diseases. Over the years, numerous authors have applied various image processing ML and DL techniques for the diagnosis of different ailments in plants that gives great hope to the farmers and landlords to cure the disease at an early stage. In this study, the authors addressed and evaluated the various currently existing state of art methods and techniques based on machine and deep learning. Besides, the authors have also focused on various limitations and challenges of these approaches that can explore greater possibly of these methods about their usability for disease detection in plants. © 2023 Taru Publications. All rights reserved. | I55: Article | J55: International Journal of Software Innovation | K55: Importado | L55: scopus (10).csv | M55: Tecnológico
A56: T0005 | B56: Scopus | C56: Utilization of Multi-Channel Hybrid Deep Neural Networks for Avocado Ripeness Classification | D56: Nuanmeesri S. | E56: 2024 | F56: 10.48084/etasr.7651 | G56: avocado ripeness classification; convolutional neural networks; EfficientNetB0; hybrid deep neural networks; visual geometry group | H56: Ripeness classification is crucial in ensuring the quality and marketability of avocados. This paper aims to develop the Multi-Channel Hybrid Deep Neural Networks (MCHDNN) model between Visual Geometry Group 16 (VGG16) and EfficientNetB0 architectures, tailored explicitly for avocado ripeness classification in five classes: firm, breaking, ripe, overripe, and rotten. Each feature extracted is concatenated in an early fusion-based to classify the ripeness. The image dataset used for each avocado fruit was captured from six sides: front, back, left, right, bottom, and pedicel to provide a multi-channel input image in of a Convolution Neural Network (CNN). The results showed that the developed fine-tuned MCHDNN had an accuracy of 94.10% in training, 90.13% in validation, and 90.18% in testing. In addition, when considering individual class classification in the confusion matrix of the training set, it was found that the 'ripe' class had the highest accuracy of 94.58%, followed by the 'firm' and 'rotten' classes with 94.50% and 93.75% accuracy, respectively. Moreover, compared with the single-channel model, the fine-tuned MCHDNN model performs 7.70% more accurately than the fine-tuned VGG16 model and 7.77% more accurately than the fine-tuned EfficientNetB0 model. © 2024, Dr D. Pylarinos. All rights reserved. | I56: Article | J56: Engineering, Technology and Applied Science Research | K56: Importado | L56: scopus (2).csv | M56: Tecnológico
A57: T0006 | B57: Scopus | C57: Comparing global and variety-specific ensemble models for avocado maturity prediction with near-infrared | D57: Ovalle C.; Jimenez J.G.; Zuñiga J.B. | E57: 2026 | F57: 10.11591/ijai.v15.i3.pp2300-2313 | G57: Avocado ripeness; Ensemble stacking; Machine learning; Near-infrared spectroscopy; Non-destructive quality control; Precision agriculture; Variety-specific models | H57: Ensuring accurate, non-destructive maturity classification of avocados is critical to supply chain optimization in agro-industrial systems. This study presents a predictive framework that integrates near-infrared (NIR) spectroscopy with ensemble stacking machine learning (ML) to enhance the precision of avocado ripeness assessment. The proposed methodology compares global versus variety-specific models for 'Hass' and 'Fuerte' avocado types, leveraging spectral data (900–1,700 nm) and multiple base classifiers, including random forest (RF), gradient boosting (GB), support vector machines (SVMs), decision trees (DT), k-nearest neighbors (KNN), and categorical boosting (CatBoost), combined via linear regression as a meta-learner. Experimental results revealed that the stacking models outperformed individual learners, with variety-specific GB model achieving the highest performance (Matthews correlation coefficient (MCC) =0.679, area under the curve (AUC) =0.931). These findings highlight the critical importance of varietal specificity in model calibration and demonstrate how ensemble strategies can improve robustness, scalability, and interpretability in intelligent agricultural systems. The proposed model provides a computationally efficient solution for real-time quality control and supports the deployment of AI-powered systems within agricultural supply chains in developing regions. This is an open access article under the CC BY-SA license. https://creativecommons.org/licenses/by-sa/4.0/ | I57: Article | J57: IAES International Journal of Artificial Intelligence | K57: Importado | L57: scopus (3).csv | M57: Tecnológico
A58: T0007 | B58: Scopus | C58: Hybrid loss for robust ripeness classification under noisy labels | D58: Ahmed M.; Babaei M.; Jeong N.; Kong L.; Gan Y. | E58: 2026 | F58: 10.1016/j.fufo.2026.101116 | G58: Agricultural machine learning; Food quality assessment; Fruit ripeness classification; Hybrid loss function; Label noise; Noise-robust learning | H58: The reliability of supervised machine learning in agricultural classification is often undermined by noisy labels, which arise from subjective human annotations and environmental variability. This study introduces a noise-robust framework that integrates dual-network architectures to create a novel Hybrid Loss function. The Hybrid Loss integrates cross-entropy with consistency regularization to tackle the problem of noisy labels. The Modified Hybrid Loss further enhances robustness for small-scale datasets by updating dual networks independently. We validated these approaches on an avocado microwave image dataset and photographic avocado dataset. Across noise rates of 10%, 20%, and 50%, the proposed methods consistently outperformed baseline loss functions, including Cross-Entropy, Co-Teaching, and JoCoR. ANOVA statistical analysis confirmed significant improvements (p ' 0.00001) in classification accuracy. Beyond benchmark validation, we demonstrated practical application by tracking avocado ripening profiles over time with microwave imaging. These results establish Hybrid and Modified Hybrid Loss as effective strategies for mitigating label noise in agricultural machine learning, advancing the development of reliable, scalable, and non-destructive fruit ripeness assessment systems in Agricultural artificial intelligence (AI). © 2026 The Authors. | I58: Article | J58: Future Foods | K58: Importado | L58: scopus (5).csv | M58: Tecnológico
A59: T0008 | B59: Scopus | C59: Spatial Mapping of Avocado Anthracnose Severity Using UAV-Derived Vegetation Indices in Amazonas, Peru | D59: Guelac-Santillan M.; Puscan-Rojas J.; Sánchez-Vega J.A.; Huaman-Pilco A.F.; Medina-Medina A.J.; Tuesta-Trauco K.M.; Canta-Ventura J.M.; Barboza E.; Zabaleta-Santisteban J.A. | E59: 2026 | F59: 10.3390/agriengineering8080340 | G59: Colletotrichum fructicola; multicriteria evaluation; severity; UAV | H59: Unmanned aerial vehicle (UAV)-based multispectral remote sensing has emerged as a promising tool for monitoring crop physiological status and supporting precision disease management. However, the capacity of multispectral vegetation indices to detect foliar diseases under commercial field conditions remains insufficiently understood, particularly in perennial crops grown in humid tropical environments. This study evaluated the potential of UAV-derived multispectral vegetation indices to assess the physiological response of avocado (Persea americana Mill.) canopies affected by anthracnose caused by Colletotrichum fructicola in Amazonas, Peru. Disease incidence and severity were assessed through field evaluations, while multispectral imagery was acquired using a UAV equipped with a MicaSense RedEdge-MX Dual sensor. Vegetation indices including the Normalized Difference Vegetation Index (NDVI), Green Normalized Difference Vegetation Index (GNDVI), Soil-Adjusted Vegetation Index (SAVI), Normalized Difference Red Edge Index (NDRE), Red Edge Chlorophyll Index (CIred-edge), Plant Senescence Reflectance Index (PSRI), and Visible Atmospherically Resistant Index (VARI) were calculated, and their relationships with anthracnose incidence were analyzed using Spearman’s rank correlation. Field observations confirmed a high incidence of foliar anthracnose with a heterogeneous spatial distribution across the orchard. Multispectral imagery successfully characterized spatial variability in the canopy physiological condition, revealing differences in vegetation vigor, chlorophyll-related reflectance, and senescence among experimental blocks. Nevertheless, none of the evaluated vegetation indices showed statistically significant correlations with anthracnose incidence (p > 0.05), indicating that spectral variability primarily reflected the general canopy physiological status rather than a disease-specific spectral response. These findings demonstrate that UAV-derived multispectral vegetation indices are valuable for monitoring spatial variability in the avocado canopy condition but have limited capability for independently detecting anthracnose under humid tropical field conditions. Future studies integrating multi-temporal UAV acquisitions, hyperspectral and thermal imagery, LiDAR, environmental variables, and machine-learning approaches are expected to improve the early detection and spatial prediction of anthracnose in avocado production systems. © 2026 by the authors. | I59: Article | J59: AgriEngineering | K59: Importado | L59: scopus (6).csv | M59: Tecnológico
A60: T0009 | B60: Scopus | C60: Plants disease detection and identification system using AI and computer vision techniques | D60: Iqbal A.; Ahmed I.; Rehman S.; Alzahrani A.S. | E60: 2026 | F60: 10.7717/peerj-cs.3509 | G60: AI; DETR; Plant disease; Transformer; VGG16; YOLO; Agricultural machinery; Computer vision; Deep learning; Deterioration; Diseases; Grain (agricultural product); Learning systems; Neural networks; Plant diseases; Plants (botany); Random forests; Transfer learning; Computer vision techniques; Convolutional neural network; Detection and identifications; DETR; Disease detection; Learning models; Plant disease; Transformer; VGG16; You only look once; Crops | H60: Thespread of plant diseases is influenced by a variety of environmental and pathogen factors that not only lower the production of fruits and grains but also cause quality deterioration. The timely detection and evaluation of diseases in food plants are crucial for the health of the agricultural industry and the country’s capacity to produce enough food. This research focused on prevalent illnesses in wheat and pea plants to explore the creation of an autonomous disease detection system designed for the unique traits of the examined crops, which can be adapted to the particularities of other crops. The experiments with artificial intelligence (AI) models included both traditional machine learning and sophisticated deep learning models, including customized models and transfer learning models. In this study, our framework employed the capabilities of Transformers, Random Forest, VGG16, a custom convolutional neural network (CNN) model, and two versions of You Only Look Once (YOLO), including both v5 and v8. The employability of classical machine learning techniques aims to gauge the computational feasibility of advanced techniques such as transformers and YOLO. This work also focused on the development of a standard dataset, which was developed by collecting healthy and diseased samples from various crop fields in Pakistan. The obtained results demonstrate the improved performance of the fine-tuned VGG16 model, transformers, and the customized version of CNN as compared to the Random Forest model and YOLOv8 algorithms, in terms of disease detection and classification accuracy. Moreover, the usability of YOLO versions and detection transformers for real-time disease identification has shown promising results, which is evident in its prospects for plant disease monitoring systems. Copyright 2026 Iqbal et al. Distributed under Creative Commons CC-BY 4.0. http://www.creativecommons.org/licenses/by/4.0/ | I60: Article | J60: PeerJ Computer Science | K60: Importado (autores corregidos según el PDF: Scopus registra a Ahmed I. como primer autor y lo duplica) | L60: scopus (7).csv | M60: Tecnológico
A61: T0010 | B61: Scopus | C61: Deep Learning Based Mobile Application for Automated Plant Disease Detection | D61: Ramana Reddy B.; Kalnoor G.; Devashish M.; Sai Karthik Reddy P. | E61: 2025 | F61: 10.1109/access.2025.3581099 | G61: agriculture; convolutional neural networks (CNN); deep learning; disease severity estimation; image processing; mobile application; Plant disease detection; Convolution; Convolutional neural networks; Crops; Deep neural networks; Diagnosis; Error detection; Image enhancement; Mobile applications; Plant diseases; Plants (botany); Convolutional neural network; Deep learning; Disease detection; Disease severity; Disease severity estimation; Images processing; Mobile applications; Plant disease; Plant disease detection; Mobile computing | H61: Plant diseases remain a significant threat to global agriculture, necessitating rapid and accurate detection to minimize crop loss. This paper presents a lightweight, end-to-end system for plant leaf disease detection and severity estimation, optimized for real-time field deployment. We propose a custom Convolutional Neural Network (CNN), built using PyTorch, trained on the PlantVillage dataset to classify leaves as healthy or diseased with a test accuracy of 92.06%. To enhance its practical relevance, we incorporate a classical image processing pipeline using OpenCV and NumPy to estimate the severity of infection by computing the ratio of diseased to total leaf area. These capabilities are integrated into a cross-platform mobile application developed using React Native, with inference served via a Flask-based backend API. The mobile app enables users to capture or upload images and instantly receive diagnostic results, and severity percentages. Our system bridges the gap between deep learning research and real-world agricultural application by combining accurate classification, interpretable severity estimation, and mobile accessibility. This approach offers farmers a powerful, on-device digital assistant to monitor crop health and make informed intervention decisions. Experimental results demonstrate strong generalization performance, visual alignment of model attention with infected regions, and real-time usability in field conditions. © 2013 IEEE. | I61: Article | J61: IEEE Access | K61: Importado | L61: scopus (8).csv | M61: Tecnológico
A62: T0011 | B62: Scopus | C62: Smartphone-Based Citizen Science Tool for Plant Disease and Insect Pest Detection Using Artificial Intelligence | D62: Christakakis P.; Papadopoulou G.; Mikos G.; Kalogiannidis N.; Ioannidis D.; Tzovaras D.; Pechlivani E.M. | E62: 2024 | F62: 10.3390/technologies12070101 | G62: citizen science; decision support system; deep learning; mobile applications; pests; Tuta absoluta | H62: In recent years, the integration of smartphone technology with novel sensing technologies, Artificial Intelligence (AI), and Deep Learning (DL) algorithms has revolutionized crop pest and disease surveillance. Efficient and accurate diagnosis is crucial to mitigate substantial economic losses in agriculture caused by diseases and pests. An innovative Apple® and Android™ mobile application for citizen science has been developed, to enable real-time detection and identification of plant leaf diseases and pests, minimizing their impact on horticulture, viticulture, and olive cultivation. Leveraging DL algorithms, this application facilitates efficient data collection on crop pests and diseases, supporting crop yield protection and cost reduction in alignment with the Green Deal goal for 2030 by reducing pesticide use. The proposed citizen science tool involves all Farm to Fork stakeholders and farm citizens in minimizing damage to plant health by insect and fungal diseases. It utilizes comprehensive datasets, including images of various diseases and insects, within a robust Decision Support System (DSS) where DL models operate. The DSS connects directly with users, allowing them to upload crop pest data via the mobile application, providing data-driven support and information. The application stands out for its scalability and interoperability, enabling the continuous integration of new data to enhance its capabilities. It supports AI-based imaging analysis of quarantine pests, invasive alien species, and emerging and native pests, thereby aiding post-border surveillance programs. The mobile application, developed using a Python-based REST API, PostgreSQL, and Keycloak, has been field-tested, demonstrating its effectiveness in real-world agriculture scenarios, such as detecting Tuta absoluta (Meyrick) infestation in tomato cultivations. The outcomes of this study in T. absoluta detection serve as a showcase scenario for the proposed citizen science tool’s applicability and usability, demonstrating a 70.2% accuracy (mAP50) utilizing advanced DL models. Notably, during field testing, the model achieved detection confidence levels of up to 87%, enhancing pest management practices. © 2024 by the authors. | I62: Article | J62: Technologies | K62: Importado | L62: scopus (9).csv | M62: Tecnológico
A63: T0012 | B63: Scopus | C63: Automated and Enhanced Classification of Persea Americana Using Optimized Deep Convolutional Neural Networks With Improved Training Strategies for Agro-Industrial Settings | D63: Vera O.; Cruz J.; Huaquipaco S.; Mamani W.; Yana-Mamani V.; Huaquipaco S. | E63: 2024 | F63: 10.1109/access.2024.3496728 | G63: Classification Persea Americana; convolutional neuronal network; DenseNet; EfficientNet; ResNet; Agribusiness; Convolutional neural networks; Classification perseum americanum; Convolutional neural network; Convolutional neuronal network; Densenet; Efficientnet; Neuronal networks; Persea americana; Skill Score; Threat scores; Training strategy; Agri-food | H63: The agro-industrial sector faces significant challenges in product classification, which directly affect product quality, production efficiency and food safety. This paper proposes a machine learning model that correctly identifies the different attributes of Persea americana. For this, an automatic agro-industrial plant was implemented following industrial standards where advanced image processing techniques were used on a dataset of 346 images for training and 146 images for testing, with three deep convolutional neural networks with improved training strategies and advanced validation techniques including True Skill Statistic (TSS), Cohen's Kappa (K), Threat Score (TS), Heidke Skill Score (HSS) and Probability of Error (Pe). The results showed that the DenseNet model outperforms other state-of-the-art models in accuracy, reaching an F1 score of 99.27%, ResNet 50 reached 99.26% and EfficientNet B4 reached 99.19%, also in the validation phase TSS, K, TS and HSS for all models were higher than 0.98 while the Pe index was higher than 0.55. It is concluded that the DenseNet model is shown to be the effective and reliable technique for the classification of Persea Americana. These promising results open new possibilities for the implementation of machine learning in the agri-food industry. For future research, the possibility of expanding the data set and extending the application of this model to other varieties of fruits is proposed. © 2013 IEEE. | I63: Article | J63: IEEE Access | K63: Importado | L63: scopus.csv | M63: Tecnológico
A64: T0013 | B64: Springer Link | C64: A three-tier deep learning framework with mobile application integration for multi-crop disease diagnosis | D64: Kochhar, Aarti; Narang, Gagan; Patel, Shashikant; Kaur, Harleen; Singla, Chetan; Pateriya, Brijendra; Galdelli, Alessandro | E64: 2026 | F64: 10.1007/s44163-026-01062-0 | G64: No especificado | H64: Crop diseases remain a critical threat to global food security, contributing to substantial yield losses and reduced farmer incomes. Timely and accurate identification of these diseases is essential to mitigate their impact. Traditional diagnostic methods, dependent on expert visual inspection, are labour-intensive, time-consuming, and prone to judgment errors. Accurate and timely detection of crop diseases supports sustainable agricultural management and contributes to achieving global objectives under the United Nations Sustainable Development Goal 2 on Zero Hunger. This study proposes a three step framework that relies on pattern recognition and classification of visual disease symptoms to deliver reliable, field-applicable diagnostics. The approach combines image acquisition through smartphone camera with a structured processing pipeline that includes feature extraction, classification, and result delivery via a mobile application built on a three-tier architecture. Convolutional Neural Networks and an optimized VGG-16 model form the core classification engine, trained to recognize 19 leaf based diseases across wheat, rice, fodder, maize, and sugarcane. The models were trained and evaluated on a dataset comprising both field-collected and publicly available images using repeated stratified k-fold cross-validation. The framework achieves accuracies of 84.61% for wheat, 44.15% for rice, 85.71% for fodder, 95.23% for maize, and 64.28% for sugarcane (testing accuracy of the best-performing model per crop, where VGG-16 demonstrated superior generalization). The framework is able to support farmers, by integrating a technically robust backend with a simple and oriented interface, with diagnosis of multiple crops from a single platform, offering a scalable solution for precision agriculture and sustainable crop protection. | I64: Article | J64: Discover Artificial Intelligence | K64: Importado | L64: 10.1007_s44163-026-01062-0-citation.ris | M64: Tecnológico
A65: T0014 | B65: Science Direct | C65: Deep learning methods for enhanced stress and pest management in market garden crops: A comprehensive analysis | D65: Odounfa, Mireille Gloria Founmilayo; Gbemavo, Charlemagne D.S.J.; Tahi, Souand Peace Gloria; Glèlè Kakaï, Romain L. | E65: 2024 | F65: 10.1016/j.atech.2024.100521 | G65: Artificial intelligence; Vegetable crops disease detections; Pests; Severity estimation; Review | H65: Various deep learning methods are employed to detect stress and diseases in market garden crops, as well as to assess their severity. This study aims to comprehensively analyze these techniques and identify potential research avenues. The diversity of deep learning techniques was explored through a literature review based on the PRISMA guidelines. Research equations were defined, resulting in a sample of 1,422 publications, of which 72 were deemed usable and considered in the final analysis. For classification tasks, hybrid CNN models were the most widely used (19.2%). Commonly utilized models included VGG16 (10%), InceptionV3 (6.1%), DCNN (5%), and YoloV5 (5%). In object detection tasks, Fast R-CNN was used six times, followed by YoloV5 (three occurrences) and YoloV3 (two occurrences). In segmentation tasks, Mask R-CNN accounted for 28.67% of the models, while DeepLabV3+ accounted for 24.98%. Assessing disease severity in market garden crops is complex due to the unique criteria for each plant disease and the presence of multiple diseases across different crop types. To address this complexity, establishing a standardized method is crucial. Further research is essential to enhance the application of deep learning techniques in the study of market garden crops. This includes gathering extensive datasets that encompass various scenarios of crop diseases and considering the impact of climate variations on stress manifestation. | I65: Article | J65: Smart Agricultural Technology | K65: Importado | L65: ScienceDirect_citations_1790890165413.ris (C16) | M65: Tecnológico
A66: T0015 | B66: Science Direct | C66: A review of cattle behavior recognition methods based on computer vision and deep learning | D66: Yuan, Lei; Li, Weiran; Yue, Jun; Li, Zhenbo; Zhao, Yixun; Li, Qiaoyu; Feng, Wenjie; Kou, Guangjie | E66: 2026 | F66: 10.1016/j.atech.2026.101867 | G66: Cattle behavior recognition; Computer vision; Deep learning; Precision livestock farming; Smart ranch | H66: Cattle behavior recognition is vital for precision livestock farming, supporting welfare assessment, health monitoring, and intelligent management. With advances in computer vision and deep learning, automated behavior analysis has evolved rapidly. This review comprehensively summarizes recent progress in cattle behavior recognition, focusing on datasets, model architectures, algorithmic strategies, and practical challenges. Methods based on convolutional networks, temporal and spatiotemporal modeling, and Transformer architectures are analyzed, highlighting their contributions to recognition accuracy and robustness. To address current limitations regarding weak generalization across complex environments and deployment constraints, future research must prioritize multimodal data fusion, lightweight edge models, and interpreted learning frameworks to facilitate the transition from experimental models to practical on-farm applications. | I66: Article | J66: Smart Agricultural Technology | K66: Importado | L66: ScienceDirect_citations_1790890165413.ris (C16) | M66: Tecnológico
A67: T0016 | B67: Science Direct | C67: Knowledge distillation for smart agriculture: methods, applications, and future directions | D67: Lin, Xinyu; Chen, Shan; Yan, Nina; Pi, Jie; Zhu, Tingting; Xu, Lei | E67: 2026 | F67: 10.1016/j.atech.2026.102019 | G67: Knowledge distillation; Model compression; Deep learning; Smart agriculture | H67: Knowledge Distillation (KD) has emerged as a powerful paradigm for optimizing deep learning models in agriculture, enabling the transfer of knowledge from complex teacher networks to lightweight student models. Following PRISMA guidelines, this review surveys 92 studies across key domains, including plant disease recognition, crop and weed detection, pest recognition, and animal monitoring. To address the lack of standardized benchmarking across heterogeneous agricultural tasks, we adopt the Performance Retention Ratio (PRR) as a novel metric for quantifying distillation efficiency. We evaluate the efficacy of response-based, feature-based, and relation-based KD strategies, identifying critical challenges, including data scarcity, environmental variability, mismatched teacher and student architectures, limited interpretability, and dynamic agricultural conditions. The review further highlights emerging solutions, such as adaptive distillation, hardware-aware distillation, cross-domain learning, explainable distillation, dynamic distillation and lifelong learning frameworks. Our findings underscore the growing potential of KD to advance precision and sustainable agriculture by enabling efficient, interpretable, and field-deployable artificial intelligence systems. | I67: Article | J67: Smart Agricultural Technology | K67: Importado | L67: ScienceDirect_citations_1790890165413.ris (C16) | M67: Tecnológico
A68: T0017 | B68: Science Direct | C68: Precision agriculture in the age of AI: A systematic review of machine learning methods for crop disease detection | D68: Majdalawieh, Munir; Martins, Carla; Radi, Mohammed; Alaraj, Maher; Khan, Shafaq | E68: 2025 | F68: 10.1016/j.atech.2025.101491 | G68: Computer vision; Crop disease detection; Deep learning; Machine learning; Precision agriculture; Plant pathology | H68: Artificial Intelligence (AI) has become a critical tool in modern precision agriculture, particularly in the detection of plant diseases and pests. This study provides a comprehensive review of current AI methodologies applied to crop disease detection, with a focus on machine learning models, dataset availability, and performance metrics. Our findings indicate that Convolutional Neural Networks (CNNs) are the most widely used and cost-effective approach, while Vision Transformers (ViTs) exhibit superior accuracy but require significantly higher computational resources. We identify key research gaps, including the geographic bias in dataset origins, the trade-off between data quality and quantity, and the limited exploration of hybrid AI models. Additionally, challenges related to the scalability and real-time applicability of AI solutions in resource-constrained agricultural environments highlight the need for more efficient computational techniques. Cost-effectiveness remains a concern, as high-performance models often demand expensive infrastructure and expertise, limiting their adoption by smallholder farmers. Furthermore, cybersecurity risks in digital agriculture and disparities in research focus across different crops and disease types underscore the necessity for broader investigations. Unlike prior reviews, this study uniquely integrates methodological performance, dataset characteristics, and cybersecurity perspectives, offering a holistic synthesis that highlights not only technical advances but also practical barriers to large-scale adoption. Future work should prioritize model robustness, efficiency, and accessibility. | I68: Article | J68: Smart Agricultural Technology | K68: Importado | L68: ScienceDirect_citations_1790890165413.ris (C16) | ScienceDirect_citations_1790890637540.ris (C17) | M68: Tecnológico
A69: T0018 | B69: Science Direct | C69: Critical analysis of advanced machine learning and deep learning models for crop disease detection: Challenges, innovations, and future directions | D69: Saini, Yashika; Somani, Vikas; Khatri, Narendra | E69: 2026 | F69: 10.1016/j.fraope.2026.100584 | G69: Crop disease detection; Deep learning; Edge computing; Internet of things; Machine learning; Smart agriculture | H69: The rapid development of machine learning (ML) and deep learning (DL) technologies has brought a significant change in disease detection of crops. This review emphasizes the analysis of different ML and DL models applied on agricultural crops, focusing on detection accuracy, model efficiency, and adaptability across various disease types. A critical examination is conducted on the primary challenges of achieving real-time, scalable, and robust models in dynamic agricultural environments. The key challenges such as data imbalance, lack of rare disease data, technological barriers, model scalability and generalization challenges are explored in depth. Furthermore, the review investigates how integrating advanced technologies such as the Internet of Things (IoT), big data analytics, and edge computing can support real-time deployment and enhance the responsiveness of AI-driven disease detection systems in real-world agricultural settings. While current DL models demonstrate strong potential, limitations in generalization and field-level scalability highlight the need for further innovation. Future directions are proposed for developing holistic, AI-powered frameworks that are efficient, adaptive, and suitable for varied agro ecological conditions. Overall, the review offers a comprehensive synthesis of the current landscape, technological enablers, and persistent gaps in the field of AI-based crop disease management. | I69: Article | J69: Franklin Open | K69: Importado | L69: ScienceDirect_citations_1790890637540.ris (C17) | M69: Tecnológico
A70: T0019 | B70: Science Direct | C70: A review on machine learning and deep learning image-based plant disease classification for industrial farming systems | D70: Sajitha, P.; Andrushia, A. Diana; Anand, N.; Naser, M.Z. | E70: 2024 | F70: 10.1016/j.jii.2024.100572 | G70: Plant disease detection; Agriculture; Machine learning, Deep Learning | H70: Plants can be affected by various diseases. As such, the early detection of crop diseases plays an essential role in the farming industry. However, such detection requires extensive pathogen knowledge and is costly and labor-intensive. These challenges present an attractive opportunity to leverage machine learning (ML) and deep learning (DL) techniques to automate the detection of crop diseases. From this perspective, we present a review paper that showcases image-based plant disease detection and classification systems and discusses success stories using ML and DL techniques. In this review paper, we examine various aspects of these systems, including the sources of plant datasets, algorithm types and techniques used in ML and DL. The findings of this review paper inspire future research by highlighting the potential challenges in applying ML and DL to plant disease and pest detection. Additionally, it proposes potential solutions to overcome these challenges, paving the way for further advancements in developing and implementing automated systems for plant disease detection and classification. This work serves as a valuable resource for researchers and practitioners in the field, guiding their efforts toward more effective and accessible solutions for crop disease management. | I70: Article | J70: Journal of Industrial Information Integration | K70: Importado | L70: ScienceDirect_citations_1790890637540.ris (C17) | M70: Tecnológico
A71: T0020 | B71: Science Direct | C71: UX Research practices related to Long-Term UX: A Systematic Literature Review | D71: Martinelli, Suéllen; Lopes, Larissa; Zaina, Luciana | E71: 2024 | F71: 10.1016/j.infsof.2024.107431 | G71: Systematic Literature Review; User eXperience; UX Research; Long-Term UX; Established company; Software startup | H71: Context: | I71: Article | J71: Information and Software Technology | K71: Importado | L71: ScienceDirect_citations_1790891064720.ris (C18) | M71: Tecnológico

Sheet Duplicados_y_exclusion
A1: Duplicados_y_exclusion
A2: Se completa en la Actividad 4 del itinerario. Primer filtro: marca y descarta duplicados (mismo DOI/título) y exclusiones (revisiones/surveys). Conserva un único registro por estudio. Cada descarte lleva su motivo.
A3: ID original | B3: Base de datos | C3: Título completo | D3: DOI | E3: Tipo de exclusión | F3: Motivo de exclusión | G3: Duplicado | H3: Tipo de estudio detectado | I3: Decisión | L3: RESUMEN DEL PRIMER FILTRO (duplicados y revisiones)
A4: A0001 | B4: Scopus | C4: Avocado rhizobacteria emit volatile organic compounds with antifungal activity against Fusarium solani, Fusarium sp. associated with Kuroshio shot hole borer, and Colletotrichum gloeosporioides | D4: 10.1016/j.micres.2018.11.009 | E4: No aplica | F4: Registro único y estudio primario; continúa al cribado. | G4: No | H4: Primario | I4: Mantener | L4: Registros exportados (Cadenas_de_busqueda) | M4: =Cadenas_de_busqueda!H29 -> 78
A5: A0002 | B5: Scopus | C5: Colletotrichum fructicola, a Member of Colletotrichum gloeosporioides sensu lato, is the causal agent of anthracnose and soft rot in avocado fruits cv. "Hass" | D5: 10.1080/12298093.2018.1454010 | E5: No aplica | F5: Registro único y estudio primario; continúa al cribado. | G5: No | H5: Primario | I5: Mantener | L5: Duplicados dentro de la misma base (depurados en la Act. 3) | M5: =Cadenas_de_busqueda!H30 -> 10
A6: A0003 | B6: Scopus | C6: Colletotrichum perseae and Colletotrichum gloeosporioides sensu strictu Causing Stem Lesion and Dieback in Avocado in Italy | D6: 10.3390/horticulturae12010111 | E6: No aplica | F6: Registro único y estudio primario; continúa al cribado. | G6: No | H6: Primario | I6: Mantener | L6: Registros en la base consolidada | M6: =COUNTA($A$4:$A$71) -> 68
A7: A0004 | B7: Scopus | C7: Colletotrichum siamense is the main aetiological agent of anthracnose of avocado in south-eastern Brazil | D7: 10.1111/ppa.13262 | E7: No aplica | F7: Registro único y estudio primario; continúa al cribado. | G7: No | H7: Primario | I7: Mantener | L7: Excluidos en esta hoja | M7: =COUNTIF($I$4:$I$71,"Excluir") -> 13
A8: A0005 | B8: Scopus | C8: Colletotrichum species causing anthracnose on avocado fruit in Mexico: Current status | D8: 10.1111/ppa.13234 | E8: No aplica | F8: Registro único y estudio primario; continúa al cribado. | G8: No | H8: Primario | I8: Mantener | L8: Duplicados entre bases | M8: =COUNTIF($E$4:$E$71,"Duplicado") -> 4
A9: A0006 | B9: Scopus | C9: Ecofriendly management of anthracnose on avocado caused by Colletotrichum perseae in the Mediterranean basin | D9: 10.1002/jsf2.70088 | E9: No aplica | F9: Registro único y estudio primario; continúa al cribado. | G9: No | H9: Primario | I9: Mantener | L9: Revisiones sistemáticas | M9: =COUNTIF($E$4:$E$71,"Revisión sistemática") -> 8
A10: A0007 | B10: Scopus | C10: Effect of pectin-based edible emulsion coating on changes in quality of avocado exposed to Lasiodiplodia theobromae infection | D10: 10.1016/j.carbpol.2006.11.020 | E10: No aplica | F10: Registro único y estudio primario; continúa al cribado. | G10: No | H10: Primario | I10: Mantener | L10: Revisiones de literatura | M10: =COUNTIF($E$4:$E$71,"Revisión de literatura") -> 1
A11: A0008 | B11: Scopus | C11: Effect of seaweed extract on avocado root growth, yield and post-harvest quality in far north Queensland, Australia | D11: 10.1007/s10811-023-02933-0 | E11: No aplica | F11: Registro único y estudio primario; continúa al cribado. | G11: No | H11: Primario | I11: Mantener | L11: Registros que pasan al cribado (Mantener) | M11: =COUNTIF($I$4:$I$71,"Mantener") -> 55
A12: A0009 | B12: Scopus | C12: Emerging pathogens and disease dynamics threatening avocado production in southern Türkiye | D12: 10.1007/s41348-024-00954-6 | E12: No aplica | F12: Registro único y estudio primario; continúa al cribado. | G12: No | H12: Primario | I12: Mantener | L12: Fitopatológicos (A) | M12: =COUNTIFS($A$4:$A$71,"A*",$I$4:$I$71,"Mantener") -> 43
A13: A0010 | B13: Scopus | C13: Expression of several Phytophthora cinnamomi putative RxLRs provides evidence for virulence roles in avocado | D13: 10.1371/journal.pone.0254645 | E13: No aplica | F13: Registro único y estudio primario; continúa al cribado. | G13: No | H13: Primario | I13: Mantener | L13: Tecnológicos (T) | M13: =COUNTIFS($A$4:$A$71,"T*",$I$4:$I$71,"Mantener") -> 12
A14: A0011 | B14: Scopus | C14: First Record of Colletotrichum anthrisci Causing Anthracnose on Avocado Fruits in Chile | D14: 10.3390/pathogens11101204 | E14: No aplica | F14: Registro único y estudio primario; continúa al cribado. | G14: No | H14: Primario | I14: Mantener | L14: Pasan al cribado por base
A15: A0012 | B15: Scopus | C15: First Report of Fusarium equiseti Causing Postharvest Fruit Rot of Avocado in Türkiye | D15: 10.1111/jph.70131 | E15: No aplica | F15: Registro único y estudio primario; continúa al cribado. | G15: No | H15: Primario | I15: Mantener | L15: Scopus | M15: =COUNTIFS($B$4:$B$71,"Scopus",$I$4:$I$71,"Mantener") -> 49
A16: A0013 | B16: Scopus | C16: First report of Phytophthora cinnamomi causing avocado root rot in India | D16: 10.1007/s42161-023-01471-5 | E16: No aplica | F16: Registro único y estudio primario; continúa al cribado. | G16: No | H16: Primario | I16: Mantener | L16: ScienceDirect | M16: =COUNTIFS($B$4:$B$71,"Science Direct",$I$4:$I$71,"Mantener") -> 5
A17: A0014 | B17: Scopus | C17: Four new fungal pathogens causing avocado dieback in Brazil | D17: 10.1016/j.cropro.2025.107168 | E17: No aplica | F17: Registro único y estudio primario; continúa al cribado. | G17: No | H17: Primario | I17: Mantener | L17: Springer Link | M17: =COUNTIFS($B$4:$B$71,"Springer Link",$I$4:$I$71,"Mantener") -> 1
A18: A0015 | B18: Scopus | C18: Fungal Pathogens Associated with Aerial Symptoms of Avocado (Persea americana Mill.) in Tenerife (Canary Islands, Spain) Focused on Species of the Family Botryosphaeriaceae | D18: 10.3390/microorganisms11030585 | E18: No aplica | F18: Registro único y estudio primario; continúa al cribado. | G18: No | H18: Primario | I18: Mantener | L18: Comprobación: exportados − duplicados internos − excluidos = cribados | M18: =IF(M4-M5-M7=M11,"Correcto","Revisar") -> Correcto
A19: A0016 | B19: Scopus | C19: Fungal Species of Botryosphaeriaceae Associated With Avocado Dieback in Southern Spain | D19: 10.1111/ppa.70079 | E19: No aplica | F19: Registro único y estudio primario; continúa al cribado. | G19: No | H19: Primario | I19: Mantener
A20: A0017 | B20: Scopus | C20: Genome assembly and annotation of Rugonectria rugulosa, a fungus associated with avocado (Persea americana cv. Hass) trunk canker in Colombia | D20: 10.1128/mra.00512-26 | E20: No aplica | F20: Registro único y estudio primario; continúa al cribado. | G20: No | H20: Primario | I20: Mantener
A21: A0018 | B21: Scopus | C21: Identification and Pathogenicity of Botryosphaeriaceae, Colletotrichum, and Phytophthora Species Associated with Avocado Diseases in Italy | D21: 10.3390/agriculture16101035 | E21: No aplica | F21: Registro único y estudio primario; continúa al cribado. | G21: No | H21: Primario | I21: Mantener
A22: A0019 | B22: Scopus | C22: Identification and Pathogenicity of Fungal Pathogens Associated with Stem End Rots of Avocado Fruits in Kenya | D22: 10.1155/2020/4063697 | E22: No aplica | F22: Registro único y estudio primario; continúa al cribado. | G22: No | H22: Primario | I22: Mantener
A23: A0020 | B23: Scopus | C23: Identification and pathogenicity of fungal pathogens on avocado 034 in Vietnam | D23: 10.26656/fr.2017.9(5).332 | E23: No aplica | F23: Registro único y estudio primario; continúa al cribado. | G23: No | H23: Primario | I23: Mantener
A24: A0021 | B24: Scopus | C24: Identification of Phytophthora cinnamomi CRN effectors and their roles in manipulating cell death during Persea americana infection | D24: 10.1186/s12864-024-10358-3 | E24: No aplica | F24: Registro único y estudio primario; continúa al cribado. | G24: No | H24: Primario | I24: Mantener
A25: A0022 | B25: Scopus | C25: Identification, pathogenicity and distribution of the causal agents of dieback in avocado orchards in Spain | D25: 10.5424/sjar/2019171-13561 | E25: No aplica | F25: Registro único y estudio primario; continúa al cribado. | G25: No | H25: Primario | I25: Mantener
A26: A0023 | B26: Scopus | C26: Integrated proposal for management of root rot caused by Phytophthora cinnamomi in avocado cv. Hass crops | D26: 10.1016/j.cropro.2020.105271 | E26: No aplica | F26: Registro único y estudio primario; continúa al cribado. | G26: No | H26: Primario | I26: Mantener
A27: A0024 | B27: Scopus | C27: Integrated Strategies to Reduce Botryosphaeriaceae-Associated Dieback in Avocado Under Mediterranean Climatic Stress | D27: 10.3390/horticulturae12060673 | E27: No aplica | F27: Registro único y estudio primario; continúa al cribado. | G27: No | H27: Primario | I27: Mantener
A28: A0025 | B28: Scopus | C28: Lasiodiplodia theobromae disease symptom development in young avocado (Persea americana L.) plants depends on the inoculation method | D28: 10.1007/s40858-025-00700-9 | E28: No aplica | F28: Registro único y estudio primario; continúa al cribado. | G28: No | H28: Primario | I28: Mantener
A29: A0026 | B29: Scopus | C29: Multigene phylogeny and diversity of Phytophthora and Phytopythium species associated with avocado root rot in India and development of a point-of-care LAMP assay for Phytophthora cinnamomi and Phytopythium vexans | D29: 10.1016/j.pmpp.2025.102735 | E29: No aplica | F29: Registro único y estudio primario; continúa al cribado. | G29: No | H29: Primario | I29: Mantener
A30: A0027 | B30: Scopus | C30: Penetration by Botryosphaeriaceae species in avocado, guava and persimmon fruit during postharvest | D30: 10.1111/jph.13055 | E30: No aplica | F30: Registro único y estudio primario; continúa al cribado. | G30: No | H30: Primario | I30: Mantener
... A71: T0020 | B71: Science Direct | C71: UX Research practices related to Long-Term UX: A Systematic Literature Review | D71: 10.1016/j.infsof.2024.107431 | E71: Revisión sistemática | F71: Estudio secundario (revisión): se retira antes del cribado por "otros motivos" (protocolo v3, CE-F2/CE-T3) y se usa como fuente de los antecedentes y del estado del arte. Revisión sistemática (Kitchenham y Charters) de 45 artículos sobre UX. | G71: No | H71: Revisión | I71: Excluir
A73: Nota | C73: Los 10 duplicados dentro de una misma base (A0003, A0009, A0012, A0016, A0017, A0025, A0032, A0038, T0001 y Majdalawieh 2025 en C16 y C17) ya se depuraron al consolidar (78 exportados - 68 registros; ver Cadenas_de_busqueda). En esta hoja se marcan los 4 duplicados entre bases (se conserva el registro de Scopus) y las 9 revisiones, que se retiran antes del cribado por "otros motivos".

Sheet Tamizaje_Tit_Abs_Keys
A1: Tamizaje_Titulo_Abstract_Keywords
A2: Se completa en la Actividad 4 del itinerario. Cribado por título, resumen y palabras clave de los registros con decisión “Mantener”. Criterios del protocolo: CI-F/CE-F (fitopatológicos) y CI-T/CE-T (tecnológicos). “¿Pasa?” = pasa a evaluación a texto completo.
A3: ID | B3: Base de datos | C3: Título completo | D3: Keywords principales | E3: Resumen técnico del abstract | F3: Grupo de patógeno (1–6) | G3: Especie identificada (o 'spp.') | H3: Órgano/tejido reportado | I3: ¿Evidencia de TALLO / tronco / rama? | J3: Enfermedad y síntoma reportados | K3: Tipo de estudio (Primario / Revisión / Otro) | L3: Nivel de alineación con el objetivo | M3: Motivo de clasificación | N3: ¿Pasa a texto completo? | O3: Categoría | P3: Código de exclusión | R3: VERIFICACIÓN DE LA TUTORA (protocolo v3)
A4: A0001 | B4: Scopus | C4: Avocado rhizobacteria emit volatile organic compounds with antifungal activity against Fusarium solani, Fusarium sp. associated with Kuroshio shot hole borer, and Colletotrichum gloeosporioides | D4: Bacillus spp.; Bacterial volatiles; Biological control; Persea americana; Pseudomonas sp.; Rhizosphere | E4: Rizobacterias del aguacate emiten compuestos volátiles que inhiben in vitro a Fusarium, Colletotrichum y P. cinnamomi. | F4: Varios | G4: Fusarium solani; Fusarium sp. (KSHB); C. gloeosporioides; P. cinnamomi | H4: No reportado | I4: No | J4: Muerte descendente por Fusarium, antracnosis y PRR (solo mencionadas) | K4: Primario | L4: Bajo | M4: Excluir: ensayo in vitro de compuestos volátiles de rizobacterias; no aporta información del tallo (CI-F3). | N4: No | O4: Fitopatológico | P4: CI-F3 Sin información del tallo | R4: Casos dudosos que pasaron a texto completo | S4: A0029, A0031, A0035, A0042, T0012
A5: A0002 | B5: Scopus | C5: Colletotrichum fructicola, a Member of Colletotrichum gloeosporioides sensu lato, is the causal agent of anthracnose and soft rot in avocado fruits cv. "Hass" | D5: Bayesian inference; Colletotrichum species complex; Fungal infection; Multilocus sequencing typing; Persea americana; Phylogenetic reconstruction | E5: Identifica a C. fructicola como causante de antracnosis en frutos Hass en México. | F5: 4. Colletotrichum | G5: C. fructicola | H5: Fruto | I5: No | J5: Antracnosis y pudrición blanda del fruto; cancros del pericarpio | K5: Primario | L5: Bajo | M5: Excluir: solo fruto (CE-F1). | N5: No | O5: Fitopatológico | P5: CE-F1 Solo fruto | R5: Muestra del 10 % de los excluidos (4 de 33; sorteo con semilla 2026) | S5: A0010, A0011, A0034, T0008
A6: A0003 | B6: Scopus | C6: Colletotrichum perseae and Colletotrichum gloeosporioides sensu strictu Causing Stem Lesion and Dieback in Avocado in Italy | D6: Colletotrichum species; Persea americana; stem and fruit infections | E6: En un vivero de Sicilia, C. perseae y C. gloeosporioides causan lesiones en el tallo y muerte descendente; pruebas de patogenicidad. | F6: 4. Colletotrichum | G6: C. perseae; C. gloeosporioides s.s. | H6: Tallo/tronco | I6: Sí, explícita | J6: Lesiones en tallo, decoloración de la madera y muerte descendente desde el injerto | K6: Primario | L6: Alto | M6: Pasa: especies identificadas y síntomas en el tallo (CI-F1 a CI-F4). | N6: Sí | O6: Fitopatológico | R6: Registros cribados | S6: =COUNTA($A$4:$A$58) -> 55
A7: A0004 | B7: Scopus | C7: Colletotrichum siamense is the main aetiological agent of anthracnose of avocado in south-eastern Brazil | D7: infectious process; multilocus phylogeny; pathogenicity; Persea americana; post-harvest disease; Brazil | E7: C. siamense es el principal agente de la antracnosis del fruto en el sureste de Brasil. | F7: 4. Colletotrichum | G7: C. siamense; C. karstii | H7: Fruto | I7: No | J7: Antracnosis del fruto | K7: Primario | L7: Bajo | M7: Excluir: solo fruto (CE-F1). | N7: No | O7: Fitopatológico | P7: CE-F1 Solo fruto | R7: Pasan a texto completo | S7: =COUNTIF($N$4:$N$58,"Sí") -> 22
A8: A0005 | B8: Scopus | C8: Colletotrichum species causing anthracnose on avocado fruit in Mexico: Current status | D8: Colletotrichum jiangxiense sexual morph; Colletotrichum species; multilocus phylogenetic analyses; pathogenicity test; Persea americana; Mexico [North America] | E8: Especies de Colletotrichum que causan antracnosis del fruto en seis regiones de México. | F8: 4. Colletotrichum | G8: C. siamense, C. karstii y otras | H8: Fruto | I8: No | J8: Antracnosis del fruto | K8: Primario | L8: Bajo | M8: Excluir: solo fruto (CE-F1). | N8: No | O8: Fitopatológico | P8: CE-F1 Solo fruto | R8: Excluidos en el cribado | S8: =COUNTIF($N$4:$N$58,"No") -> 33
A9: A0006 | B9: Scopus | C9: Ecofriendly management of anthracnose on avocado caused by Colletotrichum perseae in the Mediterranean basin | D9: anthracnose; avocado; Bacillus; biological control agents; sustainable agriculture; Trichoderma | E9: Evalúa bioformulados contra C. perseae en ramillas desprendidas, plantas en maceta y frutos. | F9: 4. Colletotrichum | G9: C. perseae | H9: Varios | I9: Sí, explícita | J9: Lesiones en tallo y ramillas, muerte descendente y pudrición del fruto | K9: Primario | L9: Medio | M9: Pasa: el resumen indica lesiones en tallo y ramillas por C. perseae y ensayos en ramillas (CI-F3). | N9: Sí | O9: Fitopatológico | R9: CE-F1 Solo fruto | S9: =COUNTIF($P$4:$P$58,"CE-F1 Solo fruto") -> 13
A10: A0007 | B10: Scopus | C10: Effect of pectin-based edible emulsion coating on changes in quality of avocado exposed to Lasiodiplodia theobromae infection | D10: Avocado; Coating; Color; Edible film; Lasiodiplodia theobromae; Pectin | E10: Recubrimiento de pectina para frenar la pudrición peduncular por L. theobromae en frutos. | F10: 2. Lasiodiplodia | G10: L. theobromae | H10: Fruto | I10: No | J10: Pudrición peduncular del fruto | K10: Primario | L10: Bajo | M10: Excluir: solo fruto; la pudrición peduncular es del fruto (CE-F1). | N10: No | O10: Fitopatológico | P10: CE-F1 Solo fruto | R10: CE-F1 Solo raíz | S10: =COUNTIF($P$4:$P$58,"CE-F1 Solo raíz") -> 12
A11: A0008 | B11: Scopus | C11: Effect of seaweed extract on avocado root growth, yield and post-harvest quality in far north Queensland, Australia | D11: Ascophyllum nodosum; Biostimulant; Durvillaea potatorum; Persea americana; Phytophthora cinnamomi | E11: Un extracto de algas aumentó el rendimiento, la calidad del fruto y el crecimiento radicular en Australia. | F11: 1. Phytophthora | G11: P. cinnamomi (presión de inóculo) | H11: Varios | I11: No | J11: No describe síntomas | K11: Primario | L11: Bajo | M11: Excluir: evalúa extracto de algas sobre rendimiento, calidad del fruto y raíces; sin información del tallo (CI-F3). | N11: No | O11: Fitopatológico | P11: CI-F3 Sin información del tallo | R11: CI-F3 Sin información del tallo | S11: =COUNTIF($P$4:$P$58,"CI-F3 Sin información del tallo") -> 2
A12: A0009 | B12: Scopus | C12: Emerging pathogens and disease dynamics threatening avocado production in southern Türkiye | D12: Anthracnose; Avocado; Branch canker; Dieback; Fungal diseases; Soil-borne pathogens | E12: Encuesta de 2537 árboles en Antalya (Turquía); identifica patógenos y evalúa su severidad en ramas y hojas. | F12: Varios | G12: C. gloeosporioides, P. cinnamomi, F. solani, F. oxysporum, N. parvum, L. theobromae, N. rosae | H12: Varios | I12: Sí, explícita | J12: Muerte descendente, cancro de rama, antracnosis y pudrición radicular | K12: Primario | L12: Alto | M12: Pasa: encuesta de campo con síntomas en copa, ramillas y ramas (CI-F1 a CI-F4). | N12: Sí | O12: Fitopatológico | R12: CE-T2 No aborda enfermedades | S12: =COUNTIF($P$4:$P$58,"CE-T2 No aborda enfermedades") -> 5
A13: A0010 | B13: Scopus | C13: Expression of several Phytophthora cinnamomi putative RxLRs provides evidence for virulence roles in avocado | D13: Persea; Phylogeny; Phytophthora; Virulence; fungal protein; RxLR protein | E13: Expresión de efectores RxLR de P. cinnamomi durante la infección de un portainjerto. | F13: 1. Phytophthora | G13: P. cinnamomi | H13: Raíz | I13: No | J13: Pudrición radicular (PRR) | K13: Primario | L13: Bajo | M13: Excluir: solo raíz; estudio molecular de efectores (CE-F1). | N13: No | O13: Fitopatológico | P13: CE-F1 Solo raíz | R13: CE-T1 No usa IA | S13: =COUNTIF($P$4:$P$58,"CE-T1 No usa IA") -> 1
A14: A0011 | B14: Scopus | C14: First Record of Colletotrichum anthrisci Causing Anthracnose on Avocado Fruits in Chile | D14: etiology; Persea americana; postharvest disease; streptomycin; anthracnose; Article | E14: Primer registro de C. anthrisci causando antracnosis en frutos Hass en Chile. | F14: 4. Colletotrichum | G14: C. anthrisci | H14: Fruto | I14: No | J14: Antracnosis del fruto | K14: Primario | L14: Bajo | M14: Excluir: solo fruto (CE-F1). | N14: No | O14: Fitopatológico | P14: CE-F1 Solo fruto | R14: Por categoría
A15: A0012 | B15: Scopus | C15: First Report of Fusarium equiseti Causing Postharvest Fruit Rot of Avocado in Türkiye | D15: Fusarium equiseti; Persea americana; postharvest fruit rot; rpb2 phylogeny; stem-end rot; tef1 | E15: Primer reporte de F. equiseti en poscosecha de aguacate en Turquía. | F15: 5. Fusarium | G15: F. equiseti | H15: Fruto | I15: No | J15: Pudrición del fruto y pudrición peduncular | K15: Primario | L15: Bajo | M15: Excluir: solo fruto; la pudrición peduncular es del fruto (CE-F1). | N15: No | O15: Fitopatológico | P15: CE-F1 Solo fruto | R15: Fitopatológicos cribados | S15: =COUNTIF($O$4:$O$58,"Fitopatológico") -> 43
A16: A0013 | B16: Scopus | C16: First report of Phytophthora cinnamomi causing avocado root rot in India | D16: Avocado; Phytophthora cinnamomi; Root rot | E16: Primer reporte de P. cinnamomi causando pudrición radicular en India (sin resumen). | F16: 1. Phytophthora | G16: P. cinnamomi | H16: Raíz | I16: No | J16: Pudrición radicular | K16: Primario | L16: Bajo | M16: Excluir: solo raíz según el título; sin resumen disponible (CE-F1). | N16: No | O16: Fitopatológico | P16: CE-F1 Solo raíz | R16: Fitopatológicos que pasan | S16: =COUNTIFS($O$4:$O$58,"Fitopatológico",$N$4:$N$58,"Sí") -> 16
A17: A0014 | B17: Scopus | C17: Four new fungal pathogens causing avocado dieback in Brazil | D17: Canker; Diagnosis; Persea americana; Phylogeny; Plant disease complex; Brazil | E17: Cuatro hongos nuevos causantes de muerte descendente aislados de tallos de aguacate en São Paulo (Brasil). | F17: Varios | G17: Neopestalotiopsis arecacearum; Neocosmospora bostrycoides; Nectria pseudotrichia; Cytospora viridistroma | H17: Tallo/tronco | I17: Sí, explícita | J17: Muerte descendente | K17: Primario | L17: Alto | M17: Pasa: aislamientos de tallos sintomáticos con muerte descendente (CI-F1 a CI-F4). | N17: Sí | O17: Fitopatológico | R17: Tecnológicos cribados | S17: =COUNTIF($O$4:$O$58,"Tecnológico") -> 12
A18: A0015 | B18: Scopus | C18: Fungal Pathogens Associated with Aerial Symptoms of Avocado (Persea americana Mill.) in Tenerife (Canary Islands, Spain) Focused on Species of the Family Botryosphaeriaceae | D18: canker; dieback; Lasiodiplodia brasiliensis; Neofusicoccum australe; Neofusicoccum cryptoaustrale; Neofusicoccum luteum | E18: Caracteriza los hongos de Botryosphaeriaceae asociados a síntomas aéreos en Tenerife (2018–2022). | F18: 3. Botryosphaeriaceae | G18: N. australe; N. cryptoaustrale/stellenboschiana; N. luteum; N. parvum; L. brasiliensis | H18: Varios | I18: Sí, explícita | J18: Muerte descendente, necrosis de ramas e inflorescencias, cancros en ramas y tronco, pudrición peduncular | K18: Primario | L18: Alto | M18: Pasa: síntomas aéreos en ramas y tronco con especies identificadas (CI-F1 a CI-F4). | N18: Sí | O18: Fitopatológico | R18: Tecnológicos que pasan | S18: =COUNTIFS($O$4:$O$58,"Tecnológico",$N$4:$N$58,"Sí") -> 6
A19: A0016 | B19: Scopus | C19: Fungal Species of Botryosphaeriaceae Associated With Avocado Dieback in Southern Spain | D19: aetiology; cankers; Lasiodiplodia sp.; Neofusicoccum spp.; pathogenicity; Persea americana | E19: Identifica Botryosphaeriaceae como causa principal de la muerte descendente en el sur de España (2019–2022). | F19: 3. Botryosphaeriaceae | G19: Neofusicoccum spp.; Lasiodiplodia sp.; Diaporthe sp.; Colletotrichum sp. | H19: Varios | I19: Sí, explícita | J19: Muerte de ramas, cancros, enrojecimiento vascular y momificación de frutos | K19: Primario | L19: Alto | M19: Pasa: etiología de la muerte descendente con síntomas en ramas (CI-F1 a CI-F4). | N19: Sí | O19: Fitopatológico | R19: Comprobación: pasan + excluidos = cribados | S19: =IF(S7+S8=S6,"Correcto","Revisar") -> Correcto
A20: A0017 | B20: Scopus | C20: Genome assembly and annotation of Rugonectria rugulosa, a fungus associated with avocado (Persea americana cv. Hass) trunk canker in Colombia | D20: avocado; fungal genomics; genome assembly; Nectriaceae; plant pathogen; Rugonectria rugulosa | E20: Anuncio del genoma de R. rugulosa, asociado al cancro del tronco del aguacate en Colombia. | F20: 6. Nectria | G20: Rugonectria rugulosa | H20: Tallo/tronco | I20: Sí, parcial | J20: Cancro del tronco | K20: Primario | L20: Medio | M20: Pasa: hongo asociado al cancro del tronco; verificar a texto completo cuánto aporta sobre síntomas. | N20: Sí | O20: Fitopatológico
A21: A0018 | B21: Scopus | C21: Identification and Pathogenicity of Botryosphaeriaceae, Colletotrichum, and Phytophthora Species Associated with Avocado Diseases in Italy | D21: Botryosphaeriaceae; co-infections; holistic diagnosis; oomycetes | E21: Identifica y prueba la patogenicidad de 22 especies asociadas a enfermedades del aguacate en Italia. | F21: Varios | G21: Botryosphaeriaceae, Colletotrichum y Phytophthora (22 especies) | H21: Varios | I21: Sí, explícita | J21: Manchas foliares, cancros de rama, muerte descendente y pudriciones de fruto y raíz | K21: Primario | L21: Alto | M21: Pasa: 430 muestras que incluyen ramas y tallos; bioensayos por órgano (CI-F1 a CI-F4). | N21: Sí | O21: Fitopatológico
A22: A0019 | B22: Scopus | C22: Identification and Pathogenicity of Fungal Pathogens Associated with Stem End Rots of Avocado Fruits in Kenya | D22: No especificado | E22: Hongos asociados a la pudrición peduncular del fruto en Kenia. | F22: Varios | G22: L. theobromae; N. parvum; Nectria pseudotrichia; Fusarium spp. | H22: Fruto | I22: No | J22: Pudrición peduncular del fruto | K22: Primario | L22: Bajo | M22: Excluir: la pudrición peduncular es del fruto, no del tallo (CE-F1). | N22: No | O22: Fitopatológico | P22: CE-F1 Solo fruto
A23: A0020 | B23: Scopus | C23: Identification and pathogenicity of fungal pathogens on avocado 034 in Vietnam | D23: Avocado; Fungal pathogen; Pathogenicity; Post-harvest; Article; Aspergillus flavus | E23: Hongos causantes de deterioro poscosecha en el aguacate 034 en Vietnam. | F23: Varios | G23: Lasiodiplodia spp.; Colletotrichum spp.; Fusarium spp. y otros | H23: Fruto | I23: No | J23: Deterioro poscosecha del fruto | K23: Primario | L23: Bajo | M23: Excluir: solo fruto (CE-F1). | N23: No | O23: Fitopatológico | P23: CE-F1 Solo fruto
A24: A0021 | B24: Scopus | C24: Identification of Phytophthora cinnamomi CRN effectors and their roles in manipulating cell death during Persea americana infection | D24: Alleles; Crinkler effectors; Hemibiotroph; In silico; Molecular characterization; Phytophthora | E24: Identifica efectores CRN de P. cinnamomi durante la infección del aguacate. | F24: 1. Phytophthora | G24: P. cinnamomi | H24: Raíz | I24: No | J24: Pudrición radicular (PRR) | K24: Primario | L24: Bajo | M24: Excluir: solo raíz; estudio molecular de efectores (CE-F1). | N24: No | O24: Fitopatológico | P24: CE-F1 Solo raíz
A25: A0022 | B25: Scopus | C25: Identification, pathogenicity and distribution of the causal agents of dieback in avocado orchards in Spain | D25: Botryosphaeriaceae; Colletotrichum; Lasiodiplodia; Neofusicoccum; Persea americana | E25: Identifica los agentes de la muerte descendente de ramas en Málaga y su patogenicidad. | F25: Varios | G25: N. parvum; C. gloeosporioides; N. luteum; N. australe; N. mediterraneum; L. theobromae | H25: Rama | I25: Sí, explícita | J25: Muerte descendente y cancros de rama | K25: Primario | L25: Alto | M25: Pasa: primer estudio de cancros de rama del aguacate en España (CI-F1 a CI-F4). | N25: Sí | O25: Fitopatológico
A26: A0023 | B26: Scopus | C26: Integrated proposal for management of root rot caused by Phytophthora cinnamomi in avocado cv. Hass crops | D26: Biological control; New alternatives; Reduction of disease; Sustainable diseases management; Bacillus sp.; Basidiomycota | E26: Propuesta de manejo integrado de la pudrición radicular por P. cinnamomi. | F26: 1. Phytophthora | G26: P. cinnamomi | H26: Raíz | I26: No | J26: Pudrición radicular (PRR) | K26: Primario | L26: Bajo | M26: Excluir: solo raíz; manejo de la pudrición radicular (CE-F1). | N26: No | O26: Fitopatológico | P26: CE-F1 Solo raíz
A27: A0024 | B27: Scopus | C27: Integrated Strategies to Reduce Botryosphaeriaceae-Associated Dieback in Avocado Under Mediterranean Climatic Stress | D27: autumn pruning; avocado; eco-friendly control; gibberellic acid; integrated disease management; Neofusicoccum | E27: Compara estrategias de manejo de la muerte descendente por Botryosphaeriaceae en clima mediterráneo. | F27: 3. Botryosphaeriaceae | G27: Neofusicoccum spp. | H27: Rama | I27: Sí, explícita | J27: Muerte descendente | K27: Primario | L27: Medio | M27: Pasa: evalúa la muerte descendente en campo (CI-F1 a CI-F4). | N27: Sí | O27: Fitopatológico
A28: A0025 | B28: Scopus | C28: Lasiodiplodia theobromae disease symptom development in young avocado (Persea americana L.) plants depends on the inoculation method | D28: Avocado; External and internal necrosis; Lasiodiplodia theobromae; Persea americana; Symptom development; Virulence | E28: Compara la necrosis externa e interna del tallo según el método de inoculación de L. theobromae. | F28: 2. Lasiodiplodia | G28: L. theobromae | H28: Tallo/tronco | I28: Sí, explícita | J28: Necrosis externa e interna del tallo | K28: Primario | L28: Alto | M28: Pasa: describe el desarrollo de síntomas en el tallo (CI-F1 a CI-F4). | N28: Sí | O28: Fitopatológico
A29: A0026 | B29: Scopus | C29: Multigene phylogeny and diversity of Phytophthora and Phytopythium species associated with avocado root rot in India and development of a point-of-care LAMP assay for Phytophthora cinnamomi and Phytopythium vexans | D29: Avocado; LAMP; Phytophthora cinnamomi; Phytophthora species; Phytopythium vexans | E29: Diversidad de oomicetos de la pudrición radicular en India y prueba LAMP. | F29: 1. Phytophthora | G29: P. cinnamomi y otras especies de Phytophthora y Phytopythium | H29: Raíz | I29: No | J29: Pudrición radicular | K29: Primario | L29: Bajo | M29: Excluir: solo raíz (CE-F1). | N29: No | O29: Fitopatológico | P29: CE-F1 Solo raíz
A30: A0027 | B30: Scopus | C30: Penetration by Botryosphaeriaceae species in avocado, guava and persimmon fruit during postharvest | D30: Botryosphaeria dothidea; Diospyros kaki; Lasiodiplodia pseudotheobromae; Neofusicoccum parvum; Persea americana; postharvest diseases | E30: Mecanismos de penetración de Botryosphaeriaceae en frutos de aguacate, guayaba y caqui. | F30: 3. Botryosphaeriaceae | G30: B. dothidea; L. pseudotheobromae; N. parvum | H30: Fruto | I30: No | J30: Penetración y pudrición del fruto en poscosecha | K30: Primario | L30: Bajo | M30: Excluir: solo fruto (CE-F1). | N30: No | O30: Fitopatológico | P30: CE-F1 Solo fruto
A31: A0028 | B31: Scopus | C31: Phylogenetic diversity and pathogenicity of Colletotrichum species associated with avocado anthracnose in Chile | D31: Etiology; Persea americana; postharvest disease | E31: Diversidad y patogenicidad de Colletotrichum asociado a la antracnosis del fruto en Chile. | F31: 4. Colletotrichum | G31: 10 especies de Colletotrichum | H31: Fruto | I31: No | J31: Antracnosis del fruto | K31: Primario | L31: Bajo | M31: Excluir: solo fruto (CE-F1). | N31: No | O31: Fitopatológico | P31: CE-F1 Solo fruto
A32: A0029 | B32: Scopus | C32: Phytophthora cinnamomi Populations Affecting Avocado in California Show Low Differentiation, Phenotypic Variability, and Introductions from Mexico | D32: oomycete; Phytophthora root rot; ploidy; population biology; potassium phosphite; California | E32: Estructura poblacional y variabilidad fenotípica de P. cinnamomi en California y México. | F32: 1. Phytophthora | G32: P. cinnamomi | H32: Varios | I32: No | J32: Pudrición radicular (PRR); virulencia según el tejido | K32: Primario | L32: Medio | M32: Dudoso: el resumen indica virulencia distinta según el tejido infectado, sin precisarlo; se verifica a texto completo. | N32: Sí | O32: Fitopatológico
A33: A0030 | B33: Scopus | C33: Phytophthora root rot induces compositional and functional changes in avocado rhizosphere bacterial communities | D33: Dysbiosis; Metatranscriptomics; Persea americana; Phytophthora cinnamomi; Rhizobacteria; Stress response | E33: Cambios de la comunidad bacteriana de la rizosfera causados por la pudrición radicular. | F33: 1. Phytophthora | G33: P. cinnamomi | H33: Raíz | I33: No | J33: Pudrición radicular; cambios en la rizosfera | K33: Primario | L33: Bajo | M33: Excluir: solo raíz (rizosfera) (CE-F1). | N33: No | O33: Fitopatológico | P33: CE-F1 Solo raíz
A34: A0031 | B34: Scopus | C34: Phytophthora Root Rot Modifies the Composition of the Avocado Rhizosphere Microbiome and Increases the Abundance of Opportunistic Fungal Pathogens | D34: Fusarium; Mortierella; Persea americana; rhizosphere microbial communities; root necrotizing fungi; chloramphenicol | E34: Efecto de la pudrición radicular en el microbioma de la rizosfera y patogenicidad de hongos oportunistas. | F34: Varios | G34: Fusarium spp.; Lasiodiplodia sp.; Mortierella sp.; Scytalidium sp. | H34: Varios | I34: No | J34: Pudrición radicular; patogenicidad de hongos oportunistas | K34: Primario | L34: Medio | M34: Dudoso: evalúa la patogenicidad de Fusarium y Lasiodiplodia "en aguacate" sin indicar el órgano; se verifica a texto completo. | N34: Sí | O34: Fitopatológico
A35: A0032 | B35: Scopus | C35: Phytophthora species causing root rot in avocado seedlings at Colombian nurseries: Morphological, molecular, and pathogenic analysis | D35: P. heveae; PCR; Persea americana; Phytophthora cinnamomi; wilting | E35: Especies de Phytophthora causantes de pudrición radicular en viveros de Colombia. | F35: 1. Phytophthora | G35: P. cinnamomi; P. heveae | H35: Raíz | I35: No | J35: Pudrición radicular en vivero | K35: Primario | L35: Bajo | M35: Excluir: solo raíz (CE-F1). | N35: No | O35: Fitopatológico | P35: CE-F1 Solo raíz
A36: A0033 | B36: Scopus | C36: Positive effect of lippia sidoides essential oil associated with carboxymethylcellulose in the control of anthracnose in avocado | D36: Alternative control; Colletotrichum gloeosporioides; Edible coatings; Persea americana; Postharvest; Coatings | E36: Aceite esencial con recubrimiento para controlar la antracnosis en poscosecha. | F36: 4. Colletotrichum | G36: C. gloeosporioides | H36: Fruto | I36: No | J36: Antracnosis del fruto | K36: Primario | L36: Bajo | M36: Excluir: solo fruto (CE-F1). | N36: No | O36: Fitopatológico | P36: CE-F1 Solo fruto
A37: A0034 | B37: Scopus | C37: Rainfall and High Humidity Influence the Seasonal Dynamics of Spores of Glomerellaceae and Botryosphaeriaceae Genera in Avocado Orchards and Their Fruit Rot Association | D37: avocado; Botryosphaeriaceae; climatic factors; Glomerellaceae; spore dispersion; Chile | E37: Dinámica de esporas y su relación con las pudriciones del fruto en Chile. | F37: Varios | G37: Botryosphaeriaceae y Glomerellaceae | H37: Fruto | I37: No | J37: Pudriciones del fruto (pudrición peduncular y antracnosis) | K37: Primario | L37: Bajo | M37: Excluir: el objeto son las pudriciones del fruto (CE-F1). | N37: No | O37: Fitopatológico | P37: CE-F1 Solo fruto
A38: A0035 | B38: Scopus | C38: Role of the oxidative metabolism in induced resistance or susceptibility mechanism during the interaction of avocado with Phytophthora cinnamomi Rands.; [Papel do metabolismo oxidativo na resistência induzida ou mecanismo de suscetibilidade durante a interação do abacate com Phytophthora cinnamomi Rands.] | D38: antioxidant; apoptosis; oxidative stress; Persea americana; Phytophthora root rot; plant defense | E38: Metabolismo oxidativo en clones tolerante y susceptible tras inocular P. cinnamomi en la base del tallo. | F38: 1. Phytophthora | G38: P. cinnamomi | H38: Varios | I38: Sí, parcial | J38: Lesión en la base del tallo (inoculación); respuesta de defensa en hojas | K38: Primario | L38: Medio | M38: Dudoso: inoculación en la base del tallo; se verifica a texto completo si describe síntomas. | N38: Sí | O38: Fitopatológico
A39: A0036 | B39: Scopus | C39: Suppression of Stem-End Rot on Avocado Fruit Using Trichoderma spp. In the Central Highlands of Kenya | D39: No especificado | E39: Trichoderma spp. para suprimir la pudrición peduncular del fruto en Kenia. | F39: Varios | G39: L. theobromae; N. parvum; N. pseudotrichia; F. solani | H39: Fruto | I39: No | J39: Pudrición peduncular del fruto | K39: Primario | L39: Bajo | M39: Excluir: la pudrición peduncular es del fruto (CE-F1). | N39: No | O39: Fitopatológico | P39: CE-F1 Solo fruto
A40: A0037 | B40: Scopus | C40: The expression of the NPR1-dependent defense response pathway genes in Persea americana (Mill.) following infection with Phytophthora cinnamomi | D40: NPR1; Pathogenesis-related; Persea americana; Phytophthora cinnamomi; RNA-sequencing; Salicylic acid | E40: Genes de la vía NPR1 en portainjertos tras la infección por P. cinnamomi. | F40: 1. Phytophthora | G40: P. cinnamomi | H40: Raíz | I40: No | J40: Pudrición radicular (PRR) | K40: Primario | L40: Bajo | M40: Excluir: solo raíz; expresión génica en portainjertos (CE-F1). | N40: No | O40: Fitopatológico | P40: CE-F1 Solo raíz
A41: A0038 | B41: Scopus | C41: Unveiling the Predisposing Factors for the Development of Branch Canker and Dieback in Avocado: A Case of Study in Chilean Orchards | D41: Botryosphaeriaceae; incidence; multivariate analysis; Persea americana; wood diseases | E41: Factores de clima, plantación y manejo asociados al cancro de rama y la muerte descendente en Chile. | F41: 3. Botryosphaeriaceae | G41: Botryosphaeriaceae spp. | H41: Varios | I41: Sí, explícita | J41: Cancro de rama y muerte descendente | K41: Primario | L41: Medio | M41: Pasa: cancro y muerte descendente en ramas y factores asociados (CI-F1 a CI-F4). | N41: Sí | O41: Fitopatológico
A42: A0039 | B42: Science Direct | C42: Anti-oomycete activity and plant growth promoting properties of avocado fungal endophytes | D42: Endophytic fungi; Indoles | E42: Endófitos fúngicos de raíces de aguacate con actividad contra P. cinnamomi y promoción del crecimiento. | F42: 1. Phytophthora | G42: P. cinnamomi | H42: Raíz | I42: No | J42: No describe síntomas (antagonismo in vitro) | K42: Primario | L42: Bajo | M42: Excluir: endófitos de raíz y antagonismo in vitro contra P. cinnamomi (CE-F1). | N42: No | O42: Fitopatológico | P42: CE-F1 Solo raíz
A43: A0041 | B43: Science Direct | C43: Bioprospecting of microbial agents and their metabolites as potential inhibitors of Phytophthora cinnamomi, the causal agent of avocado root rot | D43: Avocado; SEM; GC-MS | E43: Caracteriza el patógeno de la pudrición radicular en India y busca agentes de biocontrol. | F43: 1. Phytophthora | G43: P. cinnamomi | H43: Raíz | I43: No | J43: Pudrición radicular (PRR) | K43: Primario | L43: Bajo | M43: Excluir: solo raíz (CE-F1). | N43: No | O43: Fitopatológico | P43: CE-F1 Solo raíz
A44: A0042 | B44: Science Direct | C44: Comparison of cross inoculation potential of South African avocado and mango isolates of Colletotrichum gloeosporioides | D44: avocado; mango; inoculation study | E44: Compara el potencial de inoculación cruzada de aislamientos de aguacate y mango (sin resumen). | F44: 4. Colletotrichum | G44: C. gloeosporioides | H44: No reportado | I44: No | J44: No indicado (sin resumen) | K44: Primario | L44: Medio | M44: Dudoso: sin resumen disponible; se verifica a texto completo. | N44: Sí | O44: Fitopatológico
A45: A0043 | B45: Science Direct | C45: Flooding and Phytophthora cinnamomi: Effects on photosynthesis and chlorophyll fluorescence in shoots of non-grafted Persea americana (Mill.) rootstocks differing in tolerance to Phytophthora root rot | D45: Avocado; Fluorescence; Gas exchange; Flooding | E45: Efecto del encharcamiento y de P. cinnamomi en la fotosíntesis de portainjertos. | F45: 1. Phytophthora | G45: P. cinnamomi | H45: Raíz | I45: No | J45: Pudrición radicular; fotosíntesis de los brotes | K45: Primario | L45: Bajo | M45: Excluir: pudrición radicular y fisiología del brote, sin síntomas en el tallo (CE-F1). | N45: No | O45: Fitopatológico | P45: CE-F1 Solo raíz
A46: A0045 | B46: Science Direct | C46: Shifts in the structure of rhizosphere bacterial communities of avocado after Fusarium dieback | D46: Biological control; Microbial diversity; Rhizosphere core microbiome | E46: Cambios de la comunidad bacteriana de la rizosfera en árboles con muerte descendente por Fusarium. | F46: 5. Fusarium | G46: Fusarium spp. (muerte descendente por Fusarium) | H46: Raíz | I46: No | J46: Cambios en la rizosfera tras la muerte descendente | K46: Primario | L46: Bajo | M46: Excluir: estudia la rizosfera, no los síntomas del tallo (CE-F1). | N46: No | O46: Fitopatológico | P46: CE-F1 Solo raíz
A47: T0001 | B47: Scopus | C47: Assessment of avocado water stress using multispectral imaging and deep learning: Toward scalable, cost-effective irrigation monitoring | D47: Deep learning; Dehydration stage; Hyperspectral reflectance values; Machine learning; Multi-spectral images; Bayesian networks | E47: Clasifica la deshidratación de hojas de aguacate con imágenes multiespectrales y CNN. | F47: Otro/No aplica | G47: Aguacate | H47: Hoja | I47: No | J47: Estrés hídrico (deshidratación foliar) | K47: Primario | L47: Bajo | M47: Excluir: estrés hídrico, no enfermedades (CE-T2). | N47: No | O47: Tecnológico | P47: CE-T2 No aborda enfermedades
A48: T0002 | B48: Scopus | C48: ApaltAI: a web-based diagnostic system with a sequential voting architecture for detecting anthracnose and scab in avocado fruit | D48: avocado; convolutional neural networks; deep learning; disease detection; image processing | E48: ApaltAI: ensamble de aprendizaje profundo y aplicación web para diagnosticar antracnosis y roña. | F48: Otro/No aplica | G48: Aguacate | H48: Fruto | I48: No | J48: Antracnosis y roña del fruto | K48: Primario | L48: Alto | M48: Pasa: diagnóstico de enfermedades con IA desplegado en una aplicación web (CI-T1 a CI-T4). | N48: Sí | O48: Tecnológico
A49: T0003 | B49: Scopus | C49: Shelf-Life Management and Ripening Assessment of ‘Hass’ Avocado (Persea americana) Using Deep Learning Approaches | D49: convolutional neural network; fruit ripening; post-harvest handling; shelf-life tracking; supply chain management | E49: Predice la etapa de maduración y la vida útil del aguacate Hass con CNN. | F49: Otro/No aplica | G49: Aguacate | H49: Fruto | I49: No | J49: Maduración (no es enfermedad) | K49: Primario | L49: Bajo | M49: Excluir: maduración y vida útil (CE-T2). | N49: No | O49: Tecnológico | P49: CE-T2 No aborda enfermedades
A50: T0005 | B50: Scopus | C50: Utilization of Multi-Channel Hybrid Deep Neural Networks for Avocado Ripeness Classification | D50: avocado ripeness classification; convolutional neural networks; EfficientNetB0; hybrid deep neural networks; visual geometry group | E50: Red híbrida multicanal para clasificar la madurez del aguacate. | F50: Otro/No aplica | G50: Aguacate | H50: Fruto | I50: No | J50: Madurez (no es enfermedad) | K50: Primario | L50: Bajo | M50: Excluir: clasificación de madurez (CE-T2). | N50: No | O50: Tecnológico | P50: CE-T2 No aborda enfermedades
A51: T0006 | B51: Scopus | C51: Comparing global and variety-specific ensemble models for avocado maturity prediction with near-infrared | D51: Avocado ripeness; Ensemble stacking; Machine learning; Near-infrared spectroscopy; Non-destructive quality control; Precision agriculture | E51: Ensambles de aprendizaje automático con NIR para predecir la madurez. | F51: Otro/No aplica | G51: Aguacate | H51: Fruto | I51: No | J51: Madurez (no es enfermedad) | K51: Primario | L51: Bajo | M51: Excluir: madurez con espectroscopía NIR (CE-T2). | N51: No | O51: Tecnológico | P51: CE-T2 No aborda enfermedades
A52: T0007 | B52: Scopus | C52: Hybrid loss for robust ripeness classification under noisy labels | D52: Agricultural machine learning; Food quality assessment; Fruit ripeness classification; Hybrid loss function; Label noise; Noise-robust learning | E52: Función de pérdida híbrida para clasificar la maduración con etiquetas ruidosas. | F52: Otro/No aplica | G52: Aguacate | H52: Fruto | I52: No | J52: Maduración (no es enfermedad) | K52: Primario | L52: Bajo | M52: Excluir: clasificación de maduración con etiquetas ruidosas (CE-T2). | N52: No | O52: Tecnológico | P52: CE-T2 No aborda enfermedades
A53: T0008 | B53: Scopus | C53: Spatial Mapping of Avocado Anthracnose Severity Using UAV-Derived Vegetation Indices in Amazonas, Peru | D53: Colletotrichum fructicola; multicriteria evaluation; severity; UAV | E53: Relaciona índices de vegetación de UAV con la antracnosis foliar en Amazonas (Perú). | F53: Otro/No aplica | G53: Aguacate | H53: Hoja | I53: No | J53: Antracnosis foliar | K53: Primario | L53: Bajo | M53: Excluir: índices de vegetación desde UAV sin modelos de IA (CE-T1). | N53: No | O53: Tecnológico | P53: CE-T1 No usa IA
A54: T0009 | B54: Scopus | C54: Plants disease detection and identification system using AI and computer vision techniques | D54: AI; DETR; Plant disease; Transformer; VGG16; YOLO | E54: Compara RF, VGG16, CNN, YOLO y DETR con un conjunto propio de Pakistán. | F54: Otro/No aplica | G54: Trigo y guisante | H54: Hoja | I54: No | J54: Enfermedades foliares de trigo y guisante | K54: Primario | L54: Medio | M54: Pasa: detección con IA y análisis de su uso en tiempo real (CI-T1 a CI-T4). | N54: Sí | O54: Tecnológico
A55: T0010 | B55: Scopus | C55: Deep Learning Based Mobile Application for Automated Plant Disease Detection | D55: agriculture; convolutional neural networks (CNN); deep learning; disease severity estimation; image processing; mobile application | E55: App React Native con CNN y estimación de severidad. | F55: Otro/No aplica | G55: Varios cultivos | H55: Hoja | I55: No | J55: Enfermedades foliares y su severidad | K55: Primario | L55: Alto | M55: Pasa: aplicación móvil con CNN para detectar enfermedades (CI-T1 a CI-T4). | N55: Sí | O55: Tecnológico
A56: T0011 | B56: Scopus | C56: Smartphone-Based Citizen Science Tool for Plant Disease and Insect Pest Detection Using Artificial Intelligence | D56: citizen science; decision support system; deep learning; mobile applications; pests; Tuta absoluta | E56: Herramienta de ciencia ciudadana para iOS y Android que detecta enfermedades y plagas. | F56: Otro/No aplica | G56: Tomate, vid y olivo | H56: Hoja | I56: No | J56: Enfermedades y plagas foliares | K56: Primario | L56: Alto | M56: Pasa: aplicación para teléfono con aprendizaje profundo, probada en campo (CI-T1 a CI-T4). | N56: Sí | O56: Tecnológico
A57: T0012 | B57: Scopus | C57: Automated and Enhanced Classification of Persea Americana Using Optimized Deep Convolutional Neural Networks With Improved Training Strategies for Agro-Industrial Settings | D57: Classification Persea Americana; convolutional neuronal network; DenseNet; EfficientNet; ResNet; Agribusiness | E57: Clasificación de frutos de Persea americana con CNN optimizadas en una planta agroindustrial. | F57: Otro/No aplica | G57: Aguacate | H57: Fruto | I57: No | J57: Atributos del fruto (no se precisa si hay enfermedad) | K57: Primario | L57: Medio | M57: Dudoso: clasifica "atributos" del fruto en un entorno agroindustrial sin precisar si son enfermedades; se verifica a texto completo. | N57: Sí | O57: Tecnológico
A58: T0013 | B58: Springer Link | C58: A three-tier deep learning framework with mobile application integration for multi-crop disease diagnosis | D58: No especificado | E58: Marco de tres capas con app Android para diagnosticar enfermedades en cinco cultivos. | F58: Otro/No aplica | G58: Trigo, arroz, forraje, maíz y caña | H58: Hoja | I58: No | J58: 19 enfermedades foliares | K58: Primario | L58: Alto | M58: Pasa: marco de tres capas con aplicación móvil y CNN (CI-T1 a CI-T4). | N58: Sí | O58: Tecnológico

Sheet Texto_completo
A1: Texto_completo
A2: Se completa en la Actividad 4 del itinerario. Evaluación de elegibilidad a texto completo de los registros que pasaron el cribado. Se registra el motivo principal de exclusión.
A3: ID | B3: Base de datos | C3: Título completo | D3: Categoría | E3: ¿PDF recuperado? | F3: Archivo PDF | G3: Decisión | H3: Motivo de exclusión | I3: Justificación | K3: RESUMEN DE LA EVALUACIÓN A TEXTO COMPLETO
A4: A0003 | B4: Scopus | C4: Colletotrichum perseae and Colletotrichum gloeosporioides sensu strictu Causing Stem Lesion and Dieback in Avocado in Italy | D4: Fitopatológico | E4: Sí | F4: Grupos v2/Todos/scopus/A0003 - horticulturae-12-00111-v2.pdf | G4: Incluir | I4: Lesiones necróticas en brotes y tallos y muerte descendente desde el injerto (incidencia > 45 % en vivero); patogenicidad con lesiones externas e internas en el tallo (Fig. 1 y 3). | K4: Informes buscados (pasan el cribado) | L4: =COUNTA($A$4:$A$25) -> 22
A5: A0006 | B5: Scopus | C5: Ecofriendly management of anthracnose on avocado caused by Colletotrichum perseae in the Mediterranean basin | D5: Fitopatológico | E5: Sí | F5: Grupos v2/Todos/scopus/A0006 - Ecofriendly management of anthracnose on avocado caused by Colletotrichum perseae in the M.pdf | G5: Incluir | I5: Mide las lesiones internas por C. perseae en ramillas desprendidas y en plantas en maceta (Tabla 4, Fig. 2). | K5: Informes no recuperados | L5: =COUNTIF($E$4:$E$25,"No") -> 0
A6: A0009 | B6: Scopus | C6: Emerging pathogens and disease dynamics threatening avocado production in southern Türkiye | D6: Fitopatológico | E6: Sí | F6: Grupos v2/Todos/scopus/A0009 - s41348-024-00954-6.pdf | G6: Incluir | I6: Encuesta de 2537 árboles con síntomas en ramillas, ramas y tallo; patogenicidad en ramas inoculadas (Fig. 5). | K6: Informes evaluados (PDF leído) | L6: =COUNTIF($E$4:$E$25,"Sí") -> 22
A7: A0014 | B7: Scopus | C7: Four new fungal pathogens causing avocado dieback in Brazil | D7: Fitopatológico | E7: Sí | F7: Grupos v2/Todos/scopus/A0014 - 1-s2.0-S0261219425000602-main.pdf | G7: Incluir | I7: Aislamientos de tallos con muerte descendente; la patogenicidad en plántulas reproduce marchitez y oscurecimiento vascular. | K7: Excluidos a texto completo | L7: =COUNTIF($G$4:$G$25,"Excluir") -> 4
A8: A0015 | B8: Scopus | C8: Fungal Pathogens Associated with Aerial Symptoms of Avocado (Persea americana Mill.) in Tenerife (Canary Islands, Spain) Focused on Species of the Family Botryosphaeriaceae | D8: Fitopatológico | E8: Sí | F8: Grupos v2/Todos/scopus/A0015 - microorganisms-11-00585-v4.pdf | G8: Incluir | I8: Necrosis de ramas en el 90 % de los huertos, cancros en ramas y tronco; inoculaciones en el tallo con exudados y necrosis interna. | K8: Solo raíz | L8: =COUNTIFS($G$4:$G$25,"Excluir",$H$4:$H$25,"Solo raíz") -> 1
A9: A0016 | B9: Scopus | C9: Fungal Species of Botryosphaeriaceae Associated With Avocado Dieback in Southern Spain | D9: Fitopatológico | E9: Sí | F9: Grupos v2/Todos/scopus/A0016 - Fungal Species of Botryosphaeriaceae Associated With Avocado Dieback in Southern Spain.pdf | G9: Incluir | I9: Síntomas de muerte descendente (ramas secas, haces vasculares rojizos, perseitol; Fig. 2) y patogenicidad en plantas, tallos y frutos. | K9: Solo fruto | L9: =COUNTIFS($G$4:$G$25,"Excluir",$H$4:$H$25,"Solo fruto") -> 1
A10: A0017 | B10: Scopus | C10: Genome assembly and annotation of Rugonectria rugulosa, a fungus associated with avocado (Persea americana cv. Hass) trunk canker in Colombia | D10: Fitopatológico | E10: Sí | F10: Grupos v2/Todos/scopus/A0017 - Genome assembly and annotation of Rugonectria rugulosa, a fungus associated with avocado (.pdf | G10: Incluir | I10: Cumple los criterios: especie identificada y aislada de lesiones activas de cancro del tronco en Colombia; aporta poca información de síntomas. | K10: Sin información de síntomas en tallo | L10: =COUNTIFS($G$4:$G$25,"Excluir",$H$4:$H$25,"Sin información de síntomas en tallo") -> 1
A11: A0018 | B11: Scopus | C11: Identification and Pathogenicity of Botryosphaeriaceae, Colletotrichum, and Phytophthora Species Associated with Avocado Diseases in Italy | D11: Fitopatológico | E11: Sí | F11: Grupos v2/Todos/scopus/A0018 - agriculture-16-01035.pdf | G11: Incluir | I11: Cancros en el 86 % de los árboles; describe síntomas de Botryosphaeriaceae y Phytophthora en ramas y tallo (Fig. 3) y bioensayos por órgano. | K11: No aborda el diagnóstico de enfermedades | L11: =COUNTIFS($G$4:$G$25,"Excluir",$H$4:$H$25,"No aborda el diagnóstico de enfermedades") -> 1
A12: A0022 | B12: Scopus | C12: Identification, pathogenicity and distribution of the causal agents of dieback in avocado orchards in Spain | D12: Fitopatológico | E12: Sí | F12: Grupos v2/Todos/scopus/A0022 - View of Identification, pathogenicity and distribution of the causal agents of dieback in.pdf | G12: Incluir | I12: Fig. 1: ramas secas, necrosis externa en ramillas, lesiones internas y lesiones externas con exudado; patogenicidad de seis especies. | K12: Elegibles (pasan a la evaluación de calidad, Act. 5) | L12: =COUNTIF($G$4:$G$25,"Incluir") -> 18
A13: A0024 | B13: Scopus | C13: Integrated Strategies to Reduce Botryosphaeriaceae-Associated Dieback in Avocado Under Mediterranean Climatic Stress | D13: Fitopatológico | E13: Sí | F13: Grupos v2/Todos/scopus/A0024 - horticulturae-12-00673-v2.pdf | G13: Incluir | I13: Evalúa la muerte descendente en campo durante varias temporadas con una escala visual de severidad (0–3). | K13: Fitopatológicos | L13: =COUNTIFS($G$4:$G$25,"Incluir",$D$4:$D$25,"Fitopatológico") -> 13
A14: A0025 | B14: Scopus | C14: Lasiodiplodia theobromae disease symptom development in young avocado (Persea americana L.) plants depends on the inoculation method | D14: Fitopatológico | E14: Sí | F14: Grupos v2/Todos/scopus/A0025 - s40858-025-00700-9.pdf | G14: Incluir | I14: Cuantifica la necrosis externa e interna del tallo con dos métodos de inoculación (Fig. 1 y 2, Tabla 1). | K14: Tecnológicos | L14: =COUNTIFS($G$4:$G$25,"Incluir",$D$4:$D$25,"Tecnológico") -> 5
A15: A0029 | B15: Scopus | C15: Phytophthora cinnamomi Populations Affecting Avocado in California Show Low Differentiation, Phenotypic Variability, and Introductions from Mexico | D15: Fitopatológico | E15: Sí | F15: Grupos v2/Todos/scopus/A0029 - Phytophthora cinnamomi Populations Affecting Avocado in California Show Low Differentiatio.pdf | G15: Excluir | H15: Solo raíz | I15: Las pruebas de virulencia se hicieron en raíces de aguacate y en frutos de pera; no evalúa el tallo. | K15: Comprobación: evaluados − excluidos = elegibles | L15: =IF(L6-L7=L12,"Correcto","Revisar") -> Correcto
A16: A0031 | B16: Scopus | C16: Phytophthora Root Rot Modifies the Composition of the Avocado Rhizosphere Microbiome and Increases the Abundance of Opportunistic Fungal Pathogens | D16: Fitopatológico | E16: Sí | F16: Grupos v2/Todos/scopus/A0031 - fmicb-11-574110.pdf | G16: Incluir | I16: Además de la rizosfera, prueba Fusarium spp., Lasiodiplodia sp. y otros hongos en tallos desprendidos, con una escala de necrosis 0–3 (necrosis vascular, necrosis externa y marchitez). Caso dudoso para la tutora.
A17: A0035 | B17: Scopus | C17: Role of the oxidative metabolism in induced resistance or susceptibility mechanism during the interaction of avocado with Phytophthora cinnamomi Rands.; [Papel do metabolismo oxidativo na resistência induzida ou mecanismo de suscetibilidade durante a interação do abacate com Phytophthora cinnamomi Rands.] | D17: Fitopatológico | E17: Sí | F17: Grupos v2/Todos/scopus/A0035 - descarga.pdf | G17: Excluir | H17: Sin información de síntomas en tallo | I17: El tallo solo es el sitio de inoculación y el diámetro de la lesión se usa como medida de virulencia (AUDPC); analiza enzimas en hojas y no describe síntomas del tallo. Caso dudoso para la tutora.
A18: A0038 | B18: Scopus | C18: Unveiling the Predisposing Factors for the Development of Branch Canker and Dieback in Avocado: A Case of Study in Chilean Orchards | D18: Fitopatológico | E18: Sí | F18: Grupos v2/Todos/scopus/A0038 - horticulturae-08-01121.pdf | G18: Incluir | I18: Describe cancros, corteza friable, protuberancias y necrosis interna en ramas y tronco (Fig. 1); incidencia por huerto.
A19: A0042 | B19: Science Direct | C19: Comparison of cross inoculation potential of South African avocado and mango isolates of Colletotrichum gloeosporioides | D19: Fitopatológico | E19: Sí | F19: Grupos v2/Todos/Science Direct/A0042 - 1-s2.0-S0944501304701135-main.pdf | G19: Excluir | H19: Solo fruto | I19: Inoculaciones cruzadas en frutos de aguacate y mango; no evalúa el tallo.
A20: T0002 | B20: Scopus | C20: ApaltAI: a web-based diagnostic system with a sequential voting architecture for detecting anthracnose and scab in avocado fruit | D20: Tecnológico | E20: Sí | F20: Grupos v2/Todos/scopus/T0002 - fpls-17-1736123.pdf | G20: Incluir | I20: Diagnóstico de antracnosis y roña con un ensamble de aprendizaje profundo desplegado en una aplicación web (CI-T1 a CI-T4).
A21: T0009 | B21: Scopus | C21: Plants disease detection and identification system using AI and computer vision techniques | D21: Tecnológico | E21: Sí | F21: Grupos v2/Todos/scopus/T0009 - peerj-cs-3509.pdf | G21: Incluir | I21: Compara modelos clásicos y profundos, analiza su viabilidad en tiempo real y propone una aplicación móvil (CI-T3).
A22: T0010 | B22: Scopus | C22: Deep Learning Based Mobile Application for Automated Plant Disease Detection | D22: Tecnológico | E22: Sí | F22: Grupos v2/Todos/scopus/T0010 - Deep_Learning_Based_Mobile_Application_for_Automated_Plant_Disease_Detection.pdf | G22: Incluir | I22: Aplicación React Native con CNN e inferencia en servidor; reporta tiempo de respuesta y pruebas de usuario.
A23: T0011 | B23: Scopus | C23: Smartphone-Based Citizen Science Tool for Plant Disease and Insect Pest Detection Using Artificial Intelligence | D23: Tecnológico | E23: Sí | F23: Grupos v2/Todos/scopus/T0011 - technologies-12-00101.pdf | G23: Incluir | I23: Aplicación iOS/Android con YOLOv8 y sistema de apoyo a la decisión; probada en campo con 50 usuarios.
A24: T0012 | B24: Scopus | C24: Automated and Enhanced Classification of Persea Americana Using Optimized Deep Convolutional Neural Networks With Improved Training Strategies for Agro-Industrial Settings | D24: Tecnológico | E24: Sí | F24: Grupos v2/Todos/scopus/T0012 - Automated_and_Enhanced_Classification_of_Persea_Americana_Using_Optimized_Deep_Convol.pdf | G24: Excluir | H24: No aborda el diagnóstico de enfermedades | I24: Clasifica frutos en "buen" o "mal" estado con imágenes de Kaggle; no diagnostica enfermedades.
A25: T0013 | B25: Springer Link | C25: A three-tier deep learning framework with mobile application integration for multi-crop disease diagnosis | D25: Tecnológico | E25: Sí | F25: Grupos v2/Todos/springer/T0013 - s44163-026-01062-0.pdf | G25: Incluir | I25: Aplicación Android de tres capas con CNN y VGG-16 para 19 enfermedades foliares, con validación cruzada.

Sheet Calidad_articulos
A1: Calidad_articulos
A2: Se completa en la Actividad 5 del itinerario. Calidad Q1–Q10 de los estudios elegibles tras el texto completo (0 = no cumple, 1 = parcial, 2 = cumple). Los criterios Q1–Q10 difieren según la categoría (ver hoja Protocolo). Total y nivel se calculan solos.
A3: ID | B3: Base de datos | C3: Título completo | D3: Q1 | E3: Q2 | F3: Q3 | G3: Q4 | H3: Q5 | I3: Q6 | J3: Q7 | K3: Q8 | L3: Q9 | M3: Q10 | N3: Puntaje total | O3: Nivel de calidad | P3: Observaciones de calidad | Q3: Categoría | S3: RESUMEN DE LA EVALUACIÓN DE CALIDAD
A4: A0003 | B4: Scopus | C4: Colletotrichum perseae and Colletotrichum gloeosporioides sensu strictu Causing Stem Lesion and Dieback in Avocado in Italy | D4: 2 | E4: 2 | F4: 2 | G4: 2 | H4: 2 | I4: 2 | J4: 2 | K4: 2 | L4: 2 | M4: 2 | N4: =IF(COUNT(D4:M4)=0,"",SUM(D4:M4)) -> 20 | O4: =IF(N4="","",IF(N4>=16,"Alta calidad",IF(N4>=11,"Media calidad","Baja calidad"))) -> Alta calidad | P4: Identificación multilocus (7 loci); síntomas en tallo con figuras; muestreo amplio en vivero (~20 000 plantas); patogenicidad con reaislamiento (Koch). Sin riesgos relevantes. | Q4: Fitopatológico | S4: Estudios evaluados | U4: =COUNTA($A$4:$A$21) -> 18
A5: A0006 | B5: Scopus | C5: Ecofriendly management of anthracnose on avocado caused by Colletotrichum perseae in the Mediterranean basin | D5: 2 | E5: 2 | F5: 1 | G5: 2 | H5: 2 | I5: 2 | J5: 0 | K5: 2 | L5: 2 | M5: 2 | N5: =IF(COUNT(D5:M5)=0,"",SUM(D5:M5)) -> 17 | O5: =IF(N5="","",IF(N5>=16,"Alta calidad",IF(N5>=11,"Media calidad","Baja calidad"))) -> Alta calidad | P5: Estudio de manejo: el aislamiento de C. perseae se identificó en un estudio previo. Las lesiones del tallo se miden (destructivamente) pero apenas se describen (Q3 = 1). No trata métodos de detección (Q7 = 0). | Q5: Fitopatológico | S5: Alta calidad (16–20) | U5: =COUNTIF($O$4:$O$21,"Alta calidad") -> 17
A6: A0009 | B6: Scopus | C6: Emerging pathogens and disease dynamics threatening avocado production in southern Türkiye | D6: 2 | E6: 1 | F6: 1 | G6: 2 | H6: 2 | I6: 2 | J6: 2 | K6: 2 | L6: 1 | M6: 2 | N6: =IF(COUNT(D6:M6)=0,"",SUM(D6:M6)) -> 17 | O6: =IF(N6="","",IF(N6>=16,"Alta calidad",IF(N6>=11,"Media calidad","Baja calidad"))) -> Alta calidad | P6: Muestra grande (2537 árboles). P. cinnamomi y M. phaseolina solo se identificaron por morfología (Q2 = 1). Síntomas del tallo descritos de forma breve (Q3 = 1). Inoculación en ramas sin reaislamiento (Koch incompleto); severidad foliar no analizada estadísticamente (Q9 = 1). | Q6: Fitopatológico | S6: Media calidad (11–15) | U6: =COUNTIF($O$4:$O$21,"Media calidad") -> 1
A7: A0014 | B7: Scopus | C7: Four new fungal pathogens causing avocado dieback in Brazil | D7: 2 | E7: 2 | F7: 1 | G7: 2 | H7: 2 | I7: 2 | J7: 1 | K7: 2 | L7: 2 | M7: 2 | N7: =IF(COUNT(D7:M7)=0,"",SUM(D7:M7)) -> 18 | O7: =IF(N7="","",IF(N7>=16,"Alta calidad",IF(N7>=11,"Media calidad","Baja calidad"))) -> Alta calidad | P7: Identificación multilocus y patogenicidad en plántulas y frutos. Muestra pequeña (2 plantaciones, 7 aislamientos). Síntomas del tallo descritos brevemente (Q3 = 1); solo métodos de laboratorio (Q7 = 1). | Q7: Fitopatológico | S7: Baja calidad (≤ 10) | U7: =COUNTIF($O$4:$O$21,"Baja calidad") -> 0
A8: A0015 | B8: Scopus | C8: Fungal Pathogens Associated with Aerial Symptoms of Avocado (Persea americana Mill.) in Tenerife (Canary Islands, Spain) Focused on Species of the Family Botryosphaeriaceae | D8: 2 | E8: 2 | F8: 2 | G8: 2 | H8: 2 | I8: 2 | J8: 2 | K8: 2 | L8: 2 | M8: 2 | N8: =IF(COUNT(D8:M8)=0,"",SUM(D8:M8)) -> 20 | O8: =IF(N8="","",IF(N8>=16,"Alta calidad",IF(N8>=11,"Media calidad","Baja calidad"))) -> Alta calidad | P8: 158 muestras de 40 huertos; tres marcadores; descripción detallada de cancros y necrosis en ramas y tronco; patogenicidad en tallo. Algunos aislamientos no se asignaron a una sola especie (complejo N. cryptoaustrale/stellenboschiana). | Q8: Fitopatológico | S8: Fitopatológicos evaluados | U8: =COUNTIF($Q$4:$Q$21,"Fitopatológico") -> 13
A9: A0016 | B9: Scopus | C9: Fungal Species of Botryosphaeriaceae Associated With Avocado Dieback in Southern Spain | D9: 2 | E9: 2 | F9: 2 | G9: 2 | H9: 2 | I9: 2 | J9: 2 | K9: 2 | L9: 2 | M9: 2 | N9: =IF(COUNT(D9:M9)=0,"",SUM(D9:M9)) -> 20 | O9: =IF(N9="","",IF(N9>=16,"Alta calidad",IF(N9>=11,"Media calidad","Baja calidad"))) -> Alta calidad | P9: 252 aislamientos de 28 fincas (2019–2022); síntomas ilustrados (Fig. 2); patogenicidad en plantas, tallos y frutos con reidentificación (Koch). Sin riesgos relevantes. | Q9: Fitopatológico | S9: de alta calidad | U9: =COUNTIFS($Q$4:$Q$21,"Fitopatológico",$O$4:$O$21,"Alta calidad") -> 12
A10: A0017 | B10: Scopus | C10: Genome assembly and annotation of Rugonectria rugulosa, a fungus associated with avocado (Persea americana cv. Hass) trunk canker in Colombia | D10: 2 | E10: 2 | F10: 0 | G10: 2 | H10: 1 | I10: 1 | J10: 1 | K10: 2 | L10: 2 | M10: 2 | N10: =IF(COUNT(D10:M10)=0,"",SUM(D10:M10)) -> 15 | O10: =IF(N10="","",IF(N10>=16,"Alta calidad",IF(N10>=11,"Media calidad","Baja calidad"))) -> Media calidad | P10: Anuncio de genoma: un solo aislamiento identificado por ITS. No describe síntomas (Q3 = 0) ni prueba la patogenicidad (Koch no aplicado). Aporta un recurso genómico, no evidencia de síntomas. | Q10: Fitopatológico | S10: puntaje medio | U10: =AVERAGEIF($Q$4:$Q$21,"Fitopatológico",$N$4:$N$21) -> 18.615385
A11: A0018 | B11: Scopus | C11: Identification and Pathogenicity of Botryosphaeriaceae, Colletotrichum, and Phytophthora Species Associated with Avocado Diseases in Italy | D11: 2 | E11: 2 | F11: 2 | G11: 2 | H11: 2 | I11: 2 | J11: 2 | K11: 2 | L11: 2 | M11: 2 | N11: =IF(COUNT(D11:M11)=0,"",SUM(D11:M11)) -> 20 | O11: =IF(N11="","",IF(N11>=16,"Alta calidad",IF(N11>=11,"Media calidad","Baja calidad"))) -> Alta calidad | P11: 430 muestras de 115 plantas; identificación con varios marcadores; síntomas por órgano con figuras; bioensayos por órgano. Advierte que Phytophthora y Botryosphaeriaceae pueden verse iguales en el tronco. | Q11: Fitopatológico | S11: Tecnológicos evaluados | U11: =COUNTIF($Q$4:$Q$21,"Tecnológico") -> 5
A12: A0022 | B12: Scopus | C12: Identification, pathogenicity and distribution of the causal agents of dieback in avocado orchards in Spain | D12: 2 | E12: 2 | F12: 2 | G12: 2 | H12: 2 | I12: 2 | J12: 2 | K12: 2 | L12: 2 | M12: 2 | N12: =IF(COUNT(D12:M12)=0,"",SUM(D12:M12)) -> 20 | O12: =IF(N12="","",IF(N12>=16,"Alta calidad",IF(N12>=11,"Media calidad","Baja calidad"))) -> Alta calidad | P12: 68 aislamientos de 10 huertos; tres marcadores; síntomas ilustrados (Fig. 1); patogenicidad y AUDPC. Sin riesgos relevantes. | Q12: Fitopatológico | S12: de alta calidad | U12: =COUNTIFS($Q$4:$Q$21,"Tecnológico",$O$4:$O$21,"Alta calidad") -> 5
A13: A0024 | B13: Scopus | C13: Integrated Strategies to Reduce Botryosphaeriaceae-Associated Dieback in Avocado Under Mediterranean Climatic Stress | D13: 2 | E13: 2 | F13: 1 | G13: 2 | H13: 2 | I13: 2 | J13: 2 | K13: 2 | L13: 2 | M13: 2 | N13: =IF(COUNT(D13:M13)=0,"",SUM(D13:M13)) -> 19 | O13: =IF(N13="","",IF(N13>=16,"Alta calidad",IF(N13>=11,"Media calidad","Baja calidad"))) -> Alta calidad | P13: Ensayos de campo y mesocosmos en varias temporadas; escala visual de severidad 0–3 y qPCR de esporas. El síntoma (muerte descendente de ramillas florales) se describe de forma general (Q3 = 1). | Q13: Fitopatológico | S13: puntaje medio | U13: =AVERAGEIF($Q$4:$Q$21,"Tecnológico",$N$4:$N$21) -> 16.8
A14: A0025 | B14: Scopus | C14: Lasiodiplodia theobromae disease symptom development in young avocado (Persea americana L.) plants depends on the inoculation method | D14: 2 | E14: 2 | F14: 2 | G14: 2 | H14: 2 | I14: 2 | J14: 1 | K14: 2 | L14: 2 | M14: 2 | N14: =IF(COUNT(D14:M14)=0,"",SUM(D14:M14)) -> 19 | O14: =IF(N14="","",IF(N14>=16,"Alta calidad",IF(N14>=11,"Media calidad","Baja calidad"))) -> Alta calidad | P14: Un solo aislamiento virulento identificado en un estudio previo; mide la necrosis externa e interna con estadística. Es un método de inoculación, no de diagnóstico (Q7 = 1). | Q14: Fitopatológico | S14: Casos en el límite entre categorías (15–16 puntos), para la tutora | U14: A0017 (15), T0002 (16), T0010 (16)
A15: A0031 | B15: Scopus | C15: Phytophthora Root Rot Modifies the Composition of the Avocado Rhizosphere Microbiome and Increases the Abundance of Opportunistic Fungal Pathogens | D15: 2 | E15: 1 | F15: 1 | G15: 2 | H15: 2 | I15: 2 | J15: 1 | K15: 2 | L15: 2 | M15: 2 | N15: =IF(COUNT(D15:M15)=0,"",SUM(D15:M15)) -> 17 | O15: =IF(N15="","",IF(N15>=16,"Alta calidad",IF(N15>=11,"Media calidad","Baja calidad"))) -> Alta calidad | P15: Lasiodiplodia identificado solo a género (Q2 = 1). La información del tallo proviene de ensayos en tallos desprendidos con escala 0–3, como objetivo secundario (Q3 = 1). Patogenicidad con reaislamiento (Koch). | Q15: Fitopatológico
A16: A0038 | B16: Scopus | C16: Unveiling the Predisposing Factors for the Development of Branch Canker and Dieback in Avocado: A Case of Study in Chilean Orchards | D16: 2 | E16: 2 | F16: 2 | G16: 2 | H16: 2 | I16: 2 | J16: 2 | K16: 2 | L16: 2 | M16: 2 | N16: =IF(COUNT(D16:M16)=0,"",SUM(D16:M16)) -> 20 | O16: =IF(N16="","",IF(N16>=16,"Alta calidad",IF(N16>=11,"Media calidad","Baja calidad"))) -> Alta calidad | P16: 16 huertos y 76 variables con análisis multivariado; escala visual de severidad (0–9); síntomas ilustrados (Fig. 1). Las especies se identificaron por ADN en un estudio previo; no hay pruebas de patogenicidad porque no era su objetivo. | Q16: Fitopatológico
A17: T0002 | B17: Scopus | C17: ApaltAI: a web-based diagnostic system with a sequential voting architecture for detecting anthracnose and scab in avocado fruit | D17: 2 | E17: 2 | F17: 2 | G17: 2 | H17: 1 | I17: 2 | J17: 1 | K17: 1 | L17: 1 | M17: 2 | N17: =IF(COUNT(D17:M17)=0,"",SUM(D17:M17)) -> 16 | O17: =IF(N17="","",IF(N17>=16,"Alta calidad",IF(N17>=11,"Media calidad","Baja calidad"))) -> Alta calidad | P17: Dataset pequeño (674 imágenes de fuentes mixtas, 3 clases). Validación hold-out 85/15 sin conjunto de prueba independiente ni validación en campo (Q5 = 1). Plataforma web adaptable al móvil, sin inferencia sin conexión (Q7 = 1). Sin evaluación con usuarios (Q8 = 1). Ni código ni datos públicos (Q9 = 1). | Q17: Tecnológico | S17: REGLAS DE PUNTUACIÓN APLICADAS (operacionalización del protocolo v3)
A18: T0009 | B18: Scopus | C18: Plants disease detection and identification system using AI and computer vision techniques | D18: 2 | E18: 2 | F18: 2 | G18: 2 | H18: 2 | I18: 2 | J18: 1 | K18: 0 | L18: 2 | M18: 2 | N18: =IF(COUNT(D18:M18)=0,"",SUM(D18:M18)) -> 17 | O18: =IF(N18="","",IF(N18>=16,"Alta calidad",IF(N18>=11,"Media calidad","Baja calidad"))) -> Alta calidad | P18: Dataset propio de campo (Pakistán), fotografiado con teléfono; división 80/20 estratificada y validación cruzada; compara seis modelos. Solo propone la app y analiza el tiempo real (Q7 = 1). No considera la IPO (Q8 = 0). Código y datos públicos. | Q18: Tecnológico | S18: Estudios fitopatológicos
A19: T0010 | B19: Scopus | C19: Deep Learning Based Mobile Application for Automated Plant Disease Detection | D19: 2 | E19: 2 | F19: 1 | G19: 2 | H19: 2 | I19: 1 | J19: 2 | K19: 1 | L19: 1 | M19: 2 | N19: =IF(COUNT(D19:M19)=0,"",SUM(D19:M19)) -> 16 | O19: =IF(N19="","",IF(N19>=16,"Alta calidad",IF(N19>=11,"Media calidad","Baja calidad"))) -> Alta calidad | P19: Datos de laboratorio (PlantVillage), sin indicar el número de imágenes del subconjunto (Q3 = 1); prueba hold-out sin validación en campo. Compara solo con un modelo (Q6 = 1). Pruebas de usuario informales (Q8 = 1). Inconsistencia entre la clasificación binaria y una tabla de 39 clases (Q9 = 1). | Q19: Tecnológico | S19: Q1 Objetivo | T19: 2: objetivo o preguntas explícitos · 1: implícito o general · 0: ausente
A20: T0011 | B20: Scopus | C20: Smartphone-Based Citizen Science Tool for Plant Disease and Insect Pest Detection Using Artificial Intelligence | D20: 2 | E20: 2 | F20: 2 | G20: 2 | H20: 1 | I20: 1 | J20: 2 | K20: 2 | L20: 1 | M20: 2 | N20: =IF(COUNT(D20:M20)=0,"",SUM(D20:M20)) -> 17 | O20: =IF(N20="","",IF(N20>=16,"Alta calidad",IF(N20>=11,"Media calidad","Baja calidad"))) -> Alta calidad | P20: 659 imágenes de campo anotadas por agrónomos; métricas sobre el conjunto de validación, sin prueba independiente (Q5 = 1); compara solo variantes de YOLOv8 (Q6 = 1). Prueba de campo con 50 usuarios y cuestionario (Q8 = 2). Datos disponibles a pedido (Q9 = 1). | Q20: Tecnológico | S20: Q2 Patógeno | T20: 2: especie identificada (molecularmente en el estudio o en un estudio previo citado) · 1: solo género, o especie solo por morfología · 0: no identificado
A21: T0013 | B21: Springer Link | C21: A three-tier deep learning framework with mobile application integration for multi-crop disease diagnosis | D21: 2 | E21: 2 | F21: 2 | G21: 2 | H21: 2 | I21: 2 | J21: 2 | K21: 1 | L21: 1 | M21: 2 | N21: =IF(COUNT(D21:M21)=0,"",SUM(D21:M21)) -> 18 | O21: =IF(N21="","",IF(N21>=16,"Alta calidad",IF(N21>=11,"Media calidad","Baja calidad"))) -> Alta calidad | P21: Imágenes de campo y públicas; validación cruzada estratificada repetida; compara 10 modelos. Algunas clases tienen muy pocas imágenes (22–30 por clase). Diseño centrado en el usuario sin evaluación formal (Q8 = 1). Ni código ni datos completos públicos (Q9 = 1). | Q21: Tecnológico | S21: Q3 Síntomas en tallo | T21: 2: síntomas del tallo, ramas o tronco descritos con detalle (texto y figuras) · 1: mencionados brevemente o como objetivo secundario · 0: no se describen
N22: =IF(COUNT(D22:M22)=0,"",SUM(D22:M22)) | O22: =IF(N22="","",IF(N22>=16,"Alta calidad",IF(N22>=11,"Media calidad","Baja calidad"))) | S22: Q4 Aguacate | T22: 2: estudio sobre aguacate · 1: extrapolable · 0: no aplicable
N23: =IF(COUNT(D23:M23)=0,"",SUM(D23:M23)) | O23: =IF(N23="","",IF(N23>=16,"Alta calidad",IF(N23>=11,"Media calidad","Baja calidad"))) | S23: Q5 Metodología | T23: 2: muestreo, aislamiento, identificación y patogenicidad replicables · 1: descripción parcial o muestra mínima · 0: ausente
N24: =IF(COUNT(D24:M24)=0,"",SUM(D24:M24)) | O24: =IF(N24="","",IF(N24>=16,"Alta calidad",IF(N24>=11,"Media calidad","Baja calidad"))) | S24: Q6 Evidencia | T24: 2: imágenes, mediciones, secuencias o estadística · 1: evidencia limitada (sin patogenicidad ni síntomas) · 0: ninguna
N25: =IF(COUNT(D25:M25)=0,"",SUM(D25:M25)) | O25: =IF(N25="","",IF(N25>=16,"Alta calidad",IF(N25>=11,"Media calidad","Baja calidad"))) | S25: Q7 Detección útil | T25: 2: rasgos visuales o escala de severidad + confirmación de laboratorio · 1: solo uno de los dos · 0: ninguno
N26: =IF(COUNT(D26:M26)=0,"",SUM(D26:M26)) | O26: =IF(N26="","",IF(N26>=16,"Alta calidad",IF(N26>=11,"Media calidad","Baja calidad"))) | S26: Q8 Contexto | T26: 2: lugar, fechas y condiciones · 1: solo el país · 0: no se indica
N27: =IF(COUNT(D27:M27)=0,"",SUM(D27:M27)) | O27: =IF(N27="","",IF(N27>=16,"Alta calidad",IF(N27>=11,"Media calidad","Baja calidad"))) | S27: Q9 Coherencia | T27: 2: conclusiones respaldadas por los datos · 1: con inconsistencias o identificaciones tentativas · 0: incoherente
N28: =IF(COUNT(D28:M28)=0,"",SUM(D28:M28)) | O28: =IF(N28="","",IF(N28>=16,"Alta calidad",IF(N28>=11,"Media calidad","Baja calidad"))) | S28: Q10 Fuente | T28: 2: revista revisada por pares, 2003–2026 · 1: sin revisión por pares clara · 0: fuera de periodo
N29: =IF(COUNT(D29:M29)=0,"",SUM(D29:M29)) | O29: =IF(N29="","",IF(N29>=16,"Alta calidad",IF(N29>=11,"Media calidad","Baja calidad"))) | S29: Estudios tecnológicos
N30: =IF(COUNT(D30:M30)=0,"",SUM(D30:M30)) | O30: =IF(N30="","",IF(N30>=16,"Alta calidad",IF(N30>=11,"Media calidad","Baja calidad"))) | S30: Q1 Objetivo | T30: 2: explícito · 1: general · 0: ausente
N31: =IF(COUNT(D31:M31)=0,"",SUM(D31:M31)) | O31: =IF(N31="","",IF(N31>=16,"Alta calidad",IF(N31>=11,"Media calidad","Baja calidad"))) | S31: Q2 Problema | T31: 2: tarea (clasificación, detección o segmentación), cultivo y enfermedades definidos · 1: parcial · 0: ausente
N32: =IF(COUNT(D32:M32)=0,"",SUM(D32:M32)) | O32: =IF(N32="","",IF(N32>=16,"Alta calidad",IF(N32>=11,"Media calidad","Baja calidad"))) | S32: Q3 Dataset | T32: 2: tamaño, clases y origen · 1: falta uno de los tres · 0: no se describe
N33: =IF(COUNT(D33:M33)=0,"",SUM(D33:M33)) | O33: =IF(N33="","",IF(N33>=16,"Alta calidad",IF(N33>=11,"Media calidad","Baja calidad"))) | S33: Q4 Modelo | T33: 2: arquitectura e hiperparámetros de entrenamiento · 1: solo arquitectura · 0: ausente
N34: =IF(COUNT(D34:M34)=0,"",SUM(D34:M34)) | O34: =IF(N34="","",IF(N34>=16,"Alta calidad",IF(N34>=11,"Media calidad","Baja calidad"))) | S34: Q5 Métricas | T34: 2: varias métricas con prueba independiente o validación cruzada · 1: una métrica o solo validación hold-out · 0: sin métricas
N35: =IF(COUNT(D35:M35)=0,"",SUM(D35:M35)) | O35: =IF(N35="","",IF(N35>=16,"Alta calidad",IF(N35>=11,"Media calidad","Baja calidad"))) | S35: Q6 Comparación | T35: 2: compara con varios modelos u otros métodos · 1: con uno o con variantes del mismo modelo · 0: no compara
N36: =IF(COUNT(D36:M36)=0,"",SUM(D36:M36)) | O36: =IF(N36="","",IF(N36>=16,"Alta calidad",IF(N36>=11,"Media calidad","Baja calidad"))) | S36: Q7 App o dispositivo | T36: 2: app móvil o dispositivo implementado y probado · 1: plataforma web o solo análisis de viabilidad · 0: no aborda
N37: =IF(COUNT(D37:M37)=0,"",SUM(D37:M37)) | O37: =IF(N37="","",IF(N37>=16,"Alta calidad",IF(N37>=11,"Media calidad","Baja calidad"))) | S37: Q8 IPO/UX | T37: 2: evaluación formal con usuarios · 1: diseño centrado en el usuario o pruebas informales · 0: no considera
N38: =IF(COUNT(D38:M38)=0,"",SUM(D38:M38)) | O38: =IF(N38="","",IF(N38>=16,"Alta calidad",IF(N38>=11,"Media calidad","Baja calidad"))) | S38: Q9 Reproducible | T38: 2: coherente y con código o datos públicos · 1: coherente sin datos o código, o con inconsistencias · 0: no reproducible
N39: =IF(COUNT(D39:M39)=0,"",SUM(D39:M39)) | O39: =IF(N39="","",IF(N39>=16,"Alta calidad",IF(N39>=11,"Media calidad","Baja calidad"))) | S39: Q10 Fuente | T39: 2: revisada por pares, 2015–2026 · 1: dudosa · 0: fuera de periodo
N40: =IF(COUNT(D40:M40)=0,"",SUM(D40:M40)) | O40: =IF(N40="","",IF(N40>=16,"Alta calidad",IF(N40>=11,"Media calidad","Baja calidad")))
N41: =IF(COUNT(D41:M41)=0,"",SUM(D41:M41)) | O41: =IF(N41="","",IF(N41>=16,"Alta calidad",IF(N41>=11,"Media calidad","Baja calidad")))
N42: =IF(COUNT(D42:M42)=0,"",SUM(D42:M42)) | O42: =IF(N42="","",IF(N42>=16,"Alta calidad",IF(N42>=11,"Media calidad","Baja calidad")))
N43: =IF(COUNT(D43:M43)=0,"",SUM(D43:M43)) | O43: =IF(N43="","",IF(N43>=16,"Alta calidad",IF(N43>=11,"Media calidad","Baja calidad")))
N44: =IF(COUNT(D44:M44)=0,"",SUM(D44:M44)) | O44: =IF(N44="","",IF(N44>=16,"Alta calidad",IF(N44>=11,"Media calidad","Baja calidad")))
N45: =IF(COUNT(D45:M45)=0,"",SUM(D45:M45)) | O45: =IF(N45="","",IF(N45>=16,"Alta calidad",IF(N45>=11,"Media calidad","Baja calidad")))
N46: =IF(COUNT(D46:M46)=0,"",SUM(D46:M46)) | O46: =IF(N46="","",IF(N46>=16,"Alta calidad",IF(N46>=11,"Media calidad","Baja calidad")))
N47: =IF(COUNT(D47:M47)=0,"",SUM(D47:M47)) | O47: =IF(N47="","",IF(N47>=16,"Alta calidad",IF(N47>=11,"Media calidad","Baja calidad")))
N48: =IF(COUNT(D48:M48)=0,"",SUM(D48:M48)) | O48: =IF(N48="","",IF(N48>=16,"Alta calidad",IF(N48>=11,"Media calidad","Baja calidad")))
N49: =IF(COUNT(D49:M49)=0,"",SUM(D49:M49)) | O49: =IF(N49="","",IF(N49>=16,"Alta calidad",IF(N49>=11,"Media calidad","Baja calidad")))
N50: =IF(COUNT(D50:M50)=0,"",SUM(D50:M50)) | O50: =IF(N50="","",IF(N50>=16,"Alta calidad",IF(N50>=11,"Media calidad","Baja calidad")))
N51: =IF(COUNT(D51:M51)=0,"",SUM(D51:M51)) | O51: =IF(N51="","",IF(N51>=16,"Alta calidad",IF(N51>=11,"Media calidad","Baja calidad")))
... N303: =IF(COUNT(D303:M303)=0,"",SUM(D303:M303)) | O303: =IF(N303="","",IF(N303>=16,"Alta calidad",IF(N303>=11,"Media calidad","Baja calidad")))

Sheet Articulos_finales
A1: Articulos_finales
A2: Se completa en la Actividad 6 del itinerario. Selección final razonada. Regla: Incluir si la calidad es Alta o Media y la alineación es Alta o Media; en otro caso, Reserva (se cita, pero no se usa en la síntesis). Columnas T–X solo para estudios tecnológicos.
A3: ID | B3: Base de datos | C3: Título completo | D3: Año | E3: Autores | F3: DOI | G3: Tipo de estudio | H3: Aporte principal | I3: Relación con el objetivo | J3: Grupo de patógeno | K3: Especie(s) confirmada(s) | L3: Órgano afectado | M3: Enfermedad y síntomas en TALLO | N3: Método de detección / diagnóstico | O3: Nivel de alineación con el objetivo | P3: Nivel de calidad | Q3: Decisión final (Incluir / Reserva) | R3: Justificación final | S3: Categoría | T3: Modelo / técnica de IA | U3: Dataset | V3: Métrica (resultado) | W3: Tipo de app / plataforma | X3: Principios IPO / UX | Y3: País | AA3: RESUMEN DE LA SELECCIÓN FINAL
A4: A0003 | B4: Scopus | C4: Colletotrichum perseae and Colletotrichum gloeosporioides sensu strictu Causing Stem Lesion and Dieback in Avocado in Italy | D4: 2026 | E4: Vecchio L.; Martino I.; Guarnaccia V.; Polizzi G.; Aiello D. | F4: 10.3390/horticulturae12010111 | G4: Primario: observación en vivero, identificación y patogenicidad | H4: Primer reporte de lesiones en el tallo y muerte descendente por Colletotrichum en aguacate y primera detección de C. perseae en Europa. | I4: RQ1 y RQ2: agente, síntomas del tallo y diferencia entre la lesión externa y la interna. | J4: 4. Colletotrichum | K4: C. perseae; C. gloeosporioides s.s. | L4: Tallo y brotes de plantas jóvenes injertadas (fruto en inoculación) | M4: Lesiones necróticas en brotes y tallos, decoloración de la madera, estrías pardo-rojizas y muerte descendente desde el injerto (incidencia > 45 %). La lesión externa medía 2,5–3,2 cm y la decoloración interna 12,0–12,6 cm. | N4: Inspección visual en vivero; aislamiento en PDA; filogenia multilocus (gapdh, chs-1, act, tub2, cal, gs, ApMat); patogenicidad con reaislamiento (Koch). | O4: Alto | P4: =INDEX(Calidad_articulos!$O$4:$O$21,MATCH(A4,Calidad_articulos!$A$4:$A$21,0)) -> Alta calidad | Q4: =IF(AND(OR(P4="Alta calidad",P4="Media calidad"),OR(O4="Alto",O4="Medio")),"Incluir","Reserva") -> Incluir | R4: Calidad alta y síntomas del tallo descritos con detalle; aporta la evidencia de que lo visible subestima el daño interno. | S4: Fitopatológico | T4: — | U4: — | V4: — | W4: — | X4: — | Y4: Italia (Sicilia) | AA4: Estudios evaluados (elegibles) | AB4: =COUNTA($A$4:$A$21) -> 18
A5: A0006 | B5: Scopus | C5: Ecofriendly management of anthracnose on avocado caused by Colletotrichum perseae in the Mediterranean basin | D5: 2026 | E5: Vecchio L.; Arrebola E.; Polizzi G.; Vitale A. | F5: 10.1002/jsf2.70088 | G5: Primario: experimental de manejo (biocontrol) | H5: Los bioformulados redujeron entre 37 y 91 % las lesiones por C. perseae en ramillas; Trichoderma asperellum T34 redujo un 76,78 % la lesión interna en plantas. | I5: RQ1 y RQ2: confirma lesiones en ramillas y tallo por C. perseae; aporte secundario para el diagnóstico. | J5: 4. Colletotrichum | K5: C. perseae (aislamiento APIN16) | L5: Ramillas desprendidas, tallo de plantas en maceta y fruto | M5: Lesiones necróticas oscuras y alargadas en ramillas y tallos (Fig. 2); lesión interna media de 5,47 cm en el testigo. | N5: Medición destructiva de la lesión interna; ANOVA y comparación de medias. | O5: Medio | P5: =INDEX(Calidad_articulos!$O$4:$O$21,MATCH(A5,Calidad_articulos!$A$4:$A$21,0)) -> Alta calidad | Q5: =IF(AND(OR(P5="Alta calidad",P5="Media calidad"),OR(O5="Alto",O5="Medio")),"Incluir","Reserva") -> Incluir | R5: Calidad alta; es un estudio de manejo, pero documenta visualmente las lesiones del tallo. | S5: Fitopatológico | T5: — | U5: — | V5: — | W5: — | X5: — | Y5: Italia y España (ensayo en invernadero en Málaga) | AA5: Incluidos en la síntesis | AB5: =COUNTIF($Q$4:$Q$21,"Incluir") -> 17
A6: A0009 | B6: Scopus | C6: Emerging pathogens and disease dynamics threatening avocado production in southern Türkiye | D6: 2024 | E6: Çalış Ö.; Çelik S.; Fidan H.; Tek M.I.; Shah M.; Tozlu I.; Wani S.H. | F6: 10.1007/s41348-024-00954-6 | G6: Primario: encuesta de campo, identificación y patogenicidad | H6: Incidencia de 33,89 % en 2537 árboles de 11 regiones; P. cinnamomi, F. solani y F. oxysporum causaron los cancros de rama más severos en inoculación. | I6: RQ1 y RQ2: agentes, región, síntomas en ramillas y ramas, e incidencia. | J6: Varios | K6: C. gloeosporioides; F. solani; F. oxysporum; N. parvum; L. theobromae; N. rosae; P. cinnamomi y M. phaseolina (tentativas, por morfología) | L6: Copa, ramillas, ramas, hojas y raíz | M6: Muerte descendente de 1 a 5 ramillas en la copa con lesiones > 10 cm en el 60–65 % de los árboles jóvenes; cancro de rama. | N6: Registro visual de síntomas; aislamiento en PDA; morfología; PCR con cebadores específicos e ITS; inoculación en ramas (área de lesión). | O6: Alto | P6: =INDEX(Calidad_articulos!$O$4:$O$21,MATCH(A6,Calidad_articulos!$A$4:$A$21,0)) -> Alta calidad | Q6: =IF(AND(OR(P6="Alta calidad",P6="Media calidad"),OR(O6="Alto",O6="Medio")),"Incluir","Reserva") -> Incluir | R6: Calidad alta; muestra amplia con síntomas del tallo y de las ramas. | S6: Fitopatológico | T6: — | U6: — | V6: — | W6: — | X6: — | Y6: Turquía (Antalya) | AA6: Fitopatológicos | AB6: =COUNTIFS($Q$4:$Q$21,"Incluir",$S$4:$S$21,"Fitopatológico") -> 12
A7: A0014 | B7: Scopus | C7: Four new fungal pathogens causing avocado dieback in Brazil | D7: 2025 | E7: Silva T.F.; Pimentel Duarte J.L.; Vélez-Olmedo J.B.; Anderson dos Santos Vieira W.; Bassay Blum L.E.; Pinho D.B. | F7: 10.1016/j.cropro.2025.107168 | G7: Primario: nota de enfermedad con identificación y patogenicidad | H7: Primer reporte mundial de cuatro hongos causantes de muerte descendente del aguacate. | I7: RQ1 y RQ2: nuevos agentes de la muerte descendente en Sudamérica. | J7: Varios | K7: Neopestalotiopsis arecacearum; Neocosmospora bostrycoides; Nectria pseudotrichia; Cytospora viridistroma | L7: Tallo | M7: Marchitez, caída intensa de hojas, muerte descendente y necrosis interna; en plántulas, oscurecimiento del sistema vascular. | N7: Aislamiento de tallos sintomáticos; morfología; filogenia multilocus (TEF1-α, RPB2, β-tubulina, ACT, ITS y LSU); patogenicidad en plántulas y frutos. | O7: Alto | P7: =INDEX(Calidad_articulos!$O$4:$O$21,MATCH(A7,Calidad_articulos!$A$4:$A$21,0)) -> Alta calidad | Q7: =IF(AND(OR(P7="Alta calidad",P7="Media calidad"),OR(O7="Alto",O7="Medio")),"Incluir","Reserva") -> Incluir | R7: Calidad alta; identifica agentes del tallo, aunque la muestra es pequeña. | S7: Fitopatológico | T7: — | U7: — | V7: — | W7: — | X7: — | Y7: Brasil (São Paulo) | AA7: Tecnológicos | AB7: =COUNTIFS($Q$4:$Q$21,"Incluir",$S$4:$S$21,"Tecnológico") -> 5
A8: A0015 | B8: Scopus | C8: Fungal Pathogens Associated with Aerial Symptoms of Avocado (Persea americana Mill.) in Tenerife (Canary Islands, Spain) Focused on Species of the Family Botryosphaeriaceae | D8: 2023 | E8: Hernández D.; García-Pérez O.; Perera S.; González-Carracedo M.A.; Rodríguez-Pérez A.; Siverio F. | F8: 10.3390/microorganisms11030585 | G8: Primario: prospección de campo, identificación y patogenicidad | H8: La necrosis de ramas apareció en el 90 % de 40 huertos; primer reporte de L. brasiliensis y de N. cryptoaustrale/stellenboschiana en aguacate. | I8: RQ1 y RQ2: síntomas aéreos detallados y advertencia sobre síntomas parecidos causados por otros hongos. | J8: 3. Botryosphaeriaceae | K8: N. australe; N. cryptoaustrale/stellenboschiana; N. luteum; N. parvum; L. brasiliensis | L8: Ramas, tronco, inflorescencias y fruto | M8: Necrosis de ramas desde el ápice; cancros en ramas y tronco (7,5 % de los huertos) con exudado azucarado que seca en polvo blanco-amarillento; corteza agrietada, oscura y hundida; necrosis en cuña en el xilema. | N8: Aislamiento; ITS, tub2 y tef1 (y rpb2); patogenicidad en el tallo (herida e inoculación en el corte de poda). | O8: Alto | P8: =INDEX(Calidad_articulos!$O$4:$O$21,MATCH(A8,Calidad_articulos!$A$4:$A$21,0)) -> Alta calidad | Q8: =IF(AND(OR(P8="Alta calidad",P8="Media calidad"),OR(O8="Alto",O8="Medio")),"Incluir","Reserva") -> Incluir | R8: Calidad alta y descripción muy detallada de síntomas del tallo. | S8: Fitopatológico | T8: — | U8: — | V8: — | W8: — | X8: — | Y8: España (Tenerife, Islas Canarias) | AA8: En reserva (se citan, no entran en la síntesis) | AB8: =COUNTIF($Q$4:$Q$21,"Reserva") -> 1
A9: A0016 | B9: Scopus | C9: Fungal Species of Botryosphaeriaceae Associated With Avocado Dieback in Southern Spain | D9: 2026 | E9: Crespo M.; Guirado-Manzano L.; Sarmiento D.; Guirado E.; de Vicente A.; Fernández-Ortuño D.; Cazorla F.M.; Arrebola E. | F9: 10.1111/ppa.70079 | G9: Primario: prospección de campo, identificación y patogenicidad | H9: Botryosphaeriaceae, sobre todo Neofusicoccum (110 de 252 aislamientos), es la causa principal de la muerte descendente en el sur de España, en relación con la escasez de agua. | I9: RQ1 y RQ2: agentes, región y síntomas visibles e internos del tallo. | J9: 3. Botryosphaeriaceae | K9: N. parvum; N. luteum; N. australe; L. theobromae; Diaporthe foeniculina | L9: Ramas, haces vasculares y fruto | M9: Tejidos secos y necróticos desde las yemas florales hacia hojas, tallos y ramas; frutos momificados adheridos; haces vasculares rojizos; depósitos de perseitol en las ramas. | N9: Aislamiento en PDA; ITS, β-tubulina y EF1; UP-PCR; patogenicidad en plantas, tallos desprendidos y frutos con reidentificación (Koch). | O9: Alto | P9: =INDEX(Calidad_articulos!$O$4:$O$21,MATCH(A9,Calidad_articulos!$A$4:$A$21,0)) -> Alta calidad | Q9: =IF(AND(OR(P9="Alta calidad",P9="Media calidad"),OR(O9="Alto",O9="Medio")),"Incluir","Reserva") -> Incluir | R9: Calidad alta; síntomas del tallo ilustrados y muestra amplia. | S9: Fitopatológico | T9: — | U9: — | V9: — | W9: — | X9: — | Y9: España (Málaga, Granada y Huelva) | AA9: Alineación alta | AB9: =COUNTIF($O$4:$O$21,"Alto") -> 11
A10: A0017 | B10: Scopus | C10: Genome assembly and annotation of Rugonectria rugulosa, a fungus associated with avocado (Persea americana cv. Hass) trunk canker in Colombia | D10: 2026 | E10: Rincón López J.D.; Chacón-Vargas K.; Clavijo-Buriticá D.C.; García-Merchán V.H. | F10: 10.1128/mra.00512-26 | G10: Primario: anuncio de genoma | H10: Genoma de 53 Mb de R. rugulosa aislado de cancros activos del tronco. | I10: RQ1: registra un agente del cancro del tronco en Latinoamérica. | J10: 6. Nectria | K10: Rugonectria rugulosa | L10: Tronco | M10: Lesiones activas de cancro del tronco; no se describen síntomas. | N10: Aislamiento en PDA; ITS; secuenciación del genoma (Illumina). | O10: Bajo | P10: =INDEX(Calidad_articulos!$O$4:$O$21,MATCH(A10,Calidad_articulos!$A$4:$A$21,0)) -> Media calidad | Q10: =IF(AND(OR(P10="Alta calidad",P10="Media calidad"),OR(O10="Alto",O10="Medio")),"Incluir","Reserva") -> Reserva | R10: Calidad media, pero alineación baja: no describe síntomas ni prueba la patogenicidad. Queda en reserva (se cita como antecedente regional, no entra en la síntesis). | S10: Fitopatológico | T10: — | U10: — | V10: — | W10: — | X10: — | Y10: Colombia (Quindío) | AA10: Alineación media | AB10: =COUNTIF($O$4:$O$21,"Medio") -> 6
A11: A0018 | B11: Scopus | C11: Identification and Pathogenicity of Botryosphaeriaceae, Colletotrichum, and Phytophthora Species Associated with Avocado Diseases in Italy | D11: 2026 | E11: Linaldeddu B.T.; Bregant C.; Muscas J.; Maddau L.; Vecchio L.; Polizzi G.; Aiello D. | F11: 10.3390/agriculture16101035 | G11: Primario: prospección en vivero y huerto, identificación y patogenicidad | H11: 22 especies en 430 muestras; coinfecciones frecuentes; advierte que Phytophthora y Botryosphaeriaceae pueden verse iguales en el tronco, lo que limita el diagnóstico por imagen con IA. | I11: RQ1, RQ2 y RQ5: agentes, síntomas diferenciales y límites del diagnóstico por imagen. | J11: Varios | K11: N. australe; N. parvum; P. cinnamomi; P. palmivora; P. citrophthora; Colletotrichum spp. (22 especies) | L11: Hojas, fruto, ramas, tallo, cuello y raíz | M11: Cancros hundidos con exudado blanco duro y sector necrótico en V (Botryosphaeriaceae); necrosis oscura de corteza con exudado negruzco sin hundimiento (Phytophthora); cancros en el 86 % de los árboles. | N11: Aislamiento en medios no selectivos y selectivos; cebos para Phytophthora; ITS, tef1-α y gapdh; bioensayos por órgano. | O11: Alto | P11: =INDEX(Calidad_articulos!$O$4:$O$21,MATCH(A11,Calidad_articulos!$A$4:$A$21,0)) -> Alta calidad | Q11: =IF(AND(OR(P11="Alta calidad",P11="Media calidad"),OR(O11="Alto",O11="Medio")),"Incluir","Reserva") -> Incluir | R11: Calidad alta; es el estudio que mejor distingue visualmente los síntomas del tronco. | S11: Fitopatológico | T11: — | U11: — | V11: — | W11: — | X11: — | Y11: Italia (Cerdeña y Sicilia) | AA11: Alineación baja | AB11: =COUNTIF($O$4:$O$21,"Bajo") -> 1
A12: A0022 | B12: Scopus | C12: Identification, pathogenicity and distribution of the causal agents of dieback in avocado orchards in Spain | D12: 2019 | E12: Arjona-Girona I.; Ruano-Rosa D.; López-Herrera C.J. | F12: 10.5424/sjar/2019171-13561 | G12: Primario: prospección de campo, identificación y patogenicidad | H12: Primer estudio de cancros de rama en España: N. parvum fue el 50 % de 68 aislamientos y el más virulento. | I12: RQ1 y RQ2: agentes, distribución y síntomas de los cancros de rama. | J12: Varios | K12: N. parvum; C. gloeosporioides; N. luteum; N. australe; N. mediterraneum; L. theobromae | L12: Ramas y ramillas | M12: Ramas secas, necrosis externa en ramillas, lesiones internas en ramas y lesiones externas con exudado (cancros pardo-rojizos con exudado blanco). | N12: Aislamiento en PDA; morfología; ITS, β-tubulina y EF1-α; patogenicidad y AUDPC. | O12: Alto | P12: =INDEX(Calidad_articulos!$O$4:$O$21,MATCH(A12,Calidad_articulos!$A$4:$A$21,0)) -> Alta calidad | Q12: =IF(AND(OR(P12="Alta calidad",P12="Media calidad"),OR(O12="Alto",O12="Medio")),"Incluir","Reserva") -> Incluir | R12: Calidad alta y síntomas de la rama ilustrados. | S12: Fitopatológico | T12: — | U12: — | V12: — | W12: — | X12: — | Y12: España (Málaga) | AA12: Comprobación: incluidos + reserva = evaluados | AB12: =IF(AB5+AB8=AB4,"Correcto","Revisar") -> Correcto
A13: A0024 | B13: Scopus | C13: Integrated Strategies to Reduce Botryosphaeriaceae-Associated Dieback in Avocado Under Mediterranean Climatic Stress | D13: 2026 | E13: Guirado-Manzano L.; Santamaría-Ortega J.F.; Sarmiento D.; Guirado E.; Pulido-Ruiz M.; de Vicente A.; Fernández-Ortuño D.; Cazorla F.M.; Arrebola E. | F13: 10.3390/horticulturae12060673 | G13: Primario: experimental de manejo en campo y mesocosmos | H13: El ácido giberélico redujo un 28 % la incidencia de la muerte descendente; el estrés hídrico produjo la mayor severidad y los árboles de 1–2 años fueron los más susceptibles. | I13: RQ2: escala visual de severidad útil para etiquetar imágenes; factores de estrés. | J13: 3. Botryosphaeriaceae | K13: N. parvum; N. luteum; Lasiodiplodia sp. (inoculación) | L13: Ramillas florales y ramas | M13: Muerte descendente que inicia en las ramillas florales. | N13: Escala visual de 4 categorías (0; ≤ 15 %; 15–50 %; > 50 %); aislamiento; trampas de esporas con qPCR. | O13: Medio | P13: =INDEX(Calidad_articulos!$O$4:$O$21,MATCH(A13,Calidad_articulos!$A$4:$A$21,0)) -> Alta calidad | Q13: =IF(AND(OR(P13="Alta calidad",P13="Media calidad"),OR(O13="Alto",O13="Medio")),"Incluir","Reserva") -> Incluir | R13: Calidad alta; estudio de manejo cuyo aporte principal para la app es la escala visual. | S13: Fitopatológico | T13: — | U13: — | V13: — | W13: — | X13: — | Y13: España (Málaga)
A14: A0025 | B14: Scopus | C14: Lasiodiplodia theobromae disease symptom development in young avocado (Persea americana L.) plants depends on the inoculation method | D14: 2025 | E14: Rodríguez-Gálvez E.; Haro-Diaz C.; Maza-Aguirre S.; Canahuire-Castillo F.; Sullón-Saucedo J.; Deising H.B. | F14: 10.1007/s40858-025-00700-9 | G14: Primario: experimental (método de inoculación) | H14: La necrosis interna del tallo avanza antes que la externa, con cualquier método de inoculación. | I14: RQ2 y RQ5: el síntoma visible subestima el avance de la infección. | J14: 2. Lasiodiplodia | K14: L. theobromae (aislamiento LA-VLCA3) | L14: Tallo de plantas jóvenes | M14: Necrosis externa e interna del tallo; la interna avanza antes y más lejos que la externa. | N14: Inoculación en el tallo medio y en el ápice; medición longitudinal de la necrosis externa e interna. | O14: Alto | P14: =INDEX(Calidad_articulos!$O$4:$O$21,MATCH(A14,Calidad_articulos!$A$4:$A$21,0)) -> Alta calidad | Q14: =IF(AND(OR(P14="Alta calidad",P14="Media calidad"),OR(O14="Alto",O14="Medio")),"Incluir","Reserva") -> Incluir | R14: Calidad alta y evidencia directa sobre lo que puede ver una fotografía. | S14: Fitopatológico | T14: — | U14: — | V14: — | W14: — | X14: — | Y14: Perú (Piura)
A15: A0031 | B15: Scopus | C15: Phytophthora Root Rot Modifies the Composition of the Avocado Rhizosphere Microbiome and Increases the Abundance of Opportunistic Fungal Pathogens | D15: 2021 | E15: Solís-García I.A.; Ceballos-Luna O.; Cortazar-Murillo E.M.; Desgarennes D.; Garay-Serrano E.; Patiño-Conde V.; Guevara-Avendaño E.; Méndez-Bravo A.; Reverchon F. | F15: 10.3389/fmicb.2020.574110 | G15: Primario: microbioma de la rizosfera y patogenicidad | H15: Además de los cambios en la rizosfera, Fusarium spp. y Lasiodiplodia sp. causaron necrosis en tallos de aguacate inoculados. | I15: RQ1 y RQ2: patógenos oportunistas capaces de necrosar el tallo; escala de necrosis 0–3. | J15: Varios | K15: F. solani (Fusarium spp.); Lasiodiplodia sp.; Mortierella sp.; Scytalidium sp. | L15: Rizosfera y tallos desprendidos (ensayo) | M15: En tallos inoculados: necrosis vascular interna, necrosis externa y marchitez (escala 0–3). | N15: Secuenciación de 16S e ITS; aislamiento; ensayo en tallo desprendido con escala de necrosis 0–3; reaislamiento (Koch). | O15: Medio | P15: =INDEX(Calidad_articulos!$O$4:$O$21,MATCH(A15,Calidad_articulos!$A$4:$A$21,0)) -> Alta calidad | Q15: =IF(AND(OR(P15="Alta calidad",P15="Media calidad"),OR(O15="Alto",O15="Medio")),"Incluir","Reserva") -> Incluir | R15: Calidad alta; la información del tallo es un objetivo secundario. | S15: Fitopatológico | T15: — | U15: — | V15: — | W15: — | X15: — | Y15: México (Veracruz)
